Workbook
Name ApplicablePTList1: AND(LEN('[1]Changes to the template'!$B1)>0,NOT('[1]Changes to the template'!$B1="NON_RIDING_TOY_VEHICLE"))
Name CONDITION_LIST_0: '[1]Conditions List'!$A$2
Name CONDITION_LIST_1: '[1]Conditions List'!$B$2:$B$3
Name CONDITION_LIST_10: '[1]Conditions List'!$K$2:$K$4
Name CONDITION_LIST_11: '[1]Conditions List'!$L$2:$L$3
Name CONDITION_LIST_12: '[1]Conditions List'!$M$2:$M$7
Name CONDITION_LIST_13: '[1]Conditions List'!$N$2:$N$10
Name CONDITION_LIST_14: '[1]Conditions List'!$O$2:$O$4
Name CONDITION_LIST_15: '[1]Conditions List'!$P$2:$P$5
Name CONDITION_LIST_16: '[1]Conditions List'!$Q$2
Name CONDITION_LIST_17: '[1]Conditions List'!$R$2
Name CONDITION_LIST_18: '[1]Conditions List'!$S$2
Name CONDITION_LIST_19: '[1]Conditions List'!$T$2:$T$6
Name CONDITION_LIST_2: '[1]Conditions List'!$C$2:$C$9
Name CONDITION_LIST_20: '[1]Conditions List'!$U$2:$U$14
Name CONDITION_LIST_21: '[1]Conditions List'!$V$2:$V$6
Name CONDITION_LIST_22: '[1]Conditions List'!$W$2:$W$5
Name CONDITION_LIST_23: '[1]Conditions List'!$X$2
Name CONDITION_LIST_24: '[1]Conditions List'!$Y$2:$Y$11
Name CONDITION_LIST_25: '[1]Conditions List'!$Z$2:$Z$3
Name CONDITION_LIST_26: '[1]Conditions List'!$AA$2:$AA$5
Name CONDITION_LIST_27: '[1]Conditions List'!$AB$2:$AB$4
Name CONDITION_LIST_28: '[1]Conditions List'!$AC$2
Name CONDITION_LIST_29: '[1]Conditions List'!$AD$2
Name CONDITION_LIST_3: '[1]Conditions List'!$D$2:$D$3
Name CONDITION_LIST_30: '[1]Conditions List'!$AE$2:$AE$4
Name CONDITION_LIST_31: '[1]Conditions List'!$AF$2:$AF$3
Name CONDITION_LIST_32: '[1]Conditions List'!$AG$2
Name CONDITION_LIST_33: '[1]Conditions List'!$AH$2
Name CONDITION_LIST_34: '[1]Conditions List'!$AI$2
Name CONDITION_LIST_35: '[1]Conditions List'!$AJ$2:$AJ$3
Name CONDITION_LIST_36: '[1]Conditions List'!$AK$2:$AK$8
Name CONDITION_LIST_37: '[1]Conditions List'!$AL$2
Name CONDITION_LIST_38: '[1]Conditions List'!$AM$2
Name CONDITION_LIST_39: '[1]Conditions List'!$AN$2
Name CONDITION_LIST_4: '[1]Conditions List'!$E$2:$E$17
Name CONDITION_LIST_40: '[1]Conditions List'!$AO$2
Name CONDITION_LIST_5: '[1]Conditions List'!$F$2:$F$11
Name CONDITION_LIST_6: '[1]Conditions List'!$G$2
Name CONDITION_LIST_7: '[1]Conditions List'!$H$2
Name CONDITION_LIST_8: '[1]Conditions List'!$I$2:$I$5
Name CONDITION_LIST_9: '[1]Conditions List'!$J$2
Name for_maxfPTList0batterymarketplace_idATVPDKIKX0DER1.cell_composition_other_than_listedlanguage_tagen_US1.value: AND(AND(OR(AND(AND(IF(COUNTIF([1]!CONDITION_LIST_37,'[1]Changes to the template'!$FQ1)>0,FALSE,TRUE)))),'[1]Changes to the template'!$B1<>""))
Name for_maxfPTList0child_parent_sku_relationshipmarketplace_idATVPDKIKX0DER1.parent_sku: AND(AND(OR(AND(OR(OR('[1]Changes to the template'!$D1<>"Child",'[1]Changes to the template'!$D1="")))),'[1]Changes to the template'!$B1<>""))
Name for_maxfPTList0compliance_age_rangemarketplace_idATVPDKIKX0DER1.value: AND(AND(OR(AND(AND(IF(COUNTIF([1]!CONDITION_LIST_35,'[1]Changes to the template'!$JN1)>0,FALSE,TRUE)))),'[1]Changes to the template'!$B1<>""))
Name for_maxfPTList0compliance_operation_modemarketplace_idATVPDKIKX0DER1.value: AND(AND(OR(AND(AND(IF(COUNTIF([1]!CONDITION_LIST_35,'[1]Changes to the template'!$JN1)>0,FALSE,TRUE)))),'[1]Changes to the template'!$B1<>""))
Name for_maxfPTList0compliance_recommended_agemarketplace_idATVPDKIKX0DER1.value: AND(AND(OR(AND(AND(IF(COUNTIF([1]!CONDITION_LIST_35,'[1]Changes to the template'!$JN1)>0,FALSE,TRUE)))),'[1]Changes to the template'!$B1<>""))
Name for_maxfPTList0compliance_toy_materialmarketplace_idATVPDKIKX0DER1.value: AND(AND(OR(AND(AND(IF(COUNTIF([1]!CONDITION_LIST_35,'[1]Changes to the template'!$JN1)>0,FALSE,TRUE)))),'[1]Changes to the template'!$B1<>""))
Name for_maxfPTList0compliance_toy_typemarketplace_idATVPDKIKX0DER1.value: AND(AND(OR(AND(AND(IF(COUNTIF([1]!CONDITION_LIST_35,'[1]Changes to the template'!$JN1)>0,FALSE,TRUE)))),'[1]Changes to the template'!$B1<>""))
Name for_maxfPTList0fulfillment_availability1.is_inventory_available: AND(AND(OR(AND(AND(IF(COUNTIF([1]!CONDITION_LIST_31,'[1]Changes to the template'!$DP1)>0,FALSE,TRUE))),AND(AND(NOT('[1]Changes to the template'!$DQ1="")))),'[1]Changes to the template'!$B1<>""))
Name for_maxfPTList0fulfillment_availability1.lead_time_to_ship_max_days: AND(AND(OR(AND(AND(IF(COUNTIF([1]!CONDITION_LIST_31,'[1]Changes to the template'!$DP1)>0,FALSE,TRUE)))),'[1]Changes to the template'!$B1<>""))
Name for_maxfPTList0fulfillment_availability1.quantity: AND(AND(OR(AND(AND(IF(COUNTIF([1]!CONDITION_LIST_31,'[1]Changes to the template'!$DP1)>0,FALSE,TRUE))),AND(AND(NOT('[1]Changes to the template'!$DT1="")))),'[1]Changes to the template'!$B1<>""))
Name for_maxfPTList0fulfillment_availability1.restock_date: AND(AND(OR(AND(AND(IF(COUNTIF([1]!CONDITION_LIST_31,'[1]Changes to the template'!$DP1)>0,FALSE,TRUE)))),'[1]Changes to the template'!$B1<>""))
Name for_minPTList0child_parent_sku_relationshipmarketplace_idATVPDKIKX0DER1.parent_sku: AND('[1]Changes to the template'!$B1<>"",OR(OR(AND(OR(OR(IF(COUNTIF([1]!CONDITION_LIST_20,'[1]Changes to the template'!$D1)>0,TRUE,FALSE)))))))
Name for_minPTList0fulfillment_availability1.is_inventory_available: AND('[1]Changes to the template'!$B1<>"",OR(OR(AND(OR(OR(IF(COUNTIF([1]!CONDITION_LIST_31,'[1]Changes to the template'!$DP1)>0,TRUE,FALSE))),OR(OR(('[1]Changes to the template'!$DQ1="")))))))
Name for_minPTList0fulfillment_availability1.quantity: AND('[1]Changes to the template'!$B1<>"",OR(OR(AND(OR(OR(IF(COUNTIF([1]!CONDITION_LIST_31,'[1]Changes to the template'!$DP1)>0,TRUE,FALSE))),OR(OR(('[1]Changes to the template'!$DT1="")))))))
Name for_minPTList0pesticide_markingmarketplace_idATVPDKIKX0DER1.certification_number: AND('[1]Changes to the template'!$B1<>"",OR(OR(AND(OR(OR(IF(COUNTIF([1]!for_minPTList0fulfillment_availability1.quantity,'[1]Changes to the template'!$HR1)>0,TRUE,FALSE)))))))
Name for_minPTList0pesticide_markingmarketplace_idATVPDKIKX0DER2.certification_number: AND('[1]Changes to the template'!$B1<>"",OR(OR(AND(OR(OR(IF(COUNTIF([1]!for_minPTList0fulfillment_availability1.quantity,'[1]Changes to the template'!$HU1)>0,TRUE,FALSE)))))))
Name for_minPTList0pesticide_markingmarketplace_idATVPDKIKX0DER3.certification_number: AND('[1]Changes to the template'!$B1<>"",OR(OR(AND(OR(OR(IF(COUNTIF([1]!for_minPTList0fulfillment_availability1.quantity,'[1]Changes to the template'!$HX1)>0,TRUE,FALSE)))))))
Name form_rgPTList0amzn1.volt.ca.product_id_type: AND(AND(AND((AND(OR(OR(OR(NOT('[1]Changes to the template'!$D1<>"Parent")))),'[1]Changes to the template'!$B1<>"")),1=1)),1=1)

Sheet Sheet1
D13: 50的asin | J13: 500 | K13: 0.03 | L13: 700 | M13: 0.05 | N13: 1200 | O13: 0.08
B14: S/SS 级别产品则 * 2 否则 *1 | C14: 级别 | H14: purchasable_offer[marketplace_id=ATVPDKIKX0DER][audience=B2B]#1.our_price#1.schedule#1.value_with_tax | I14: purchasable_offer[marketplace_id=ATVPDKIKX0DER][audience=B2B]#1.quantity_discount_plan#1.schedule#1.discount_type | J14: purchasable_offer[marketplace_id=ATVPDKIKX0DER][audience=B2B]#1.quantity_discount_plan#1.schedule#1.levels#1.lower_bound | K14: purchasable_offer[marketplace_id=ATVPDKIKX0DER][audience=B2B]#1.quantity_discount_plan#1.schedule#1.levels#1.value | L14: purchasable_offer[marketplace_id=ATVPDKIKX0DER][audience=B2B]#1.quantity_discount_plan#1.schedule#1.levels#2.lower_bound | M14: purchasable_offer[marketplace_id=ATVPDKIKX0DER][audience=B2B]#1.quantity_discount_plan#1.schedule#1.levels#2.value | N14: purchasable_offer[marketplace_id=ATVPDKIKX0DER][audience=B2B]#1.quantity_discount_plan#1.schedule#1.levels#3.lower_bound | O14: purchasable_offer[marketplace_id=ATVPDKIKX0DER][audience=B2B]#1.quantity_discount_plan#1.schedule#1.levels#3.value | P14: purchasable_offer[marketplace_id=ATVPDKIKX0DER][audience=B2B]#1.quantity_discount_plan#1.schedule#1.levels#4.lower_bound | Q14: purchasable_offer[marketplace_id=ATVPDKIKX0DER][audience=B2B]#1.quantity_discount_plan#1.schedule#1.levels#4.value | R14: purchasable_offer[marketplace_id=ATVPDKIKX0DER][audience=B2B]#1.quantity_discount_plan#1.schedule#1.levels#5.lower_bound | S14: purchasable_offer[marketplace_id=ATVPDKIKX0DER][audience=B2B]#1.quantity_discount_plan#1.schedule#1.levels#5.value
A15: 2 | B15: =IF(OR(VLOOKUP(D15,Sheet4!$F$9:$G$245,2,0)="SS",VLOOKUP(D15,Sheet4!$F$9:$G$245,2,0)="S"),2,1) -> 1 | C15: =VLOOKUP(D15,Sheet4!$F$9:$G$245,2,0) -> P | D15: B0DTP8B4FZ | E15: =VLOOKUP(D15,'50库存'!$C$2:$D$313,2,0) -> 50US-MaiGanYaZi-013 | F15: =VLOOKUP(E15,'50库存'!$D$2:$U$313,18,0) -> 25.74 | G15: =COUNTIF('50库存'!$C$2:$C$313,D15) -> 1 | H15: =VLOOKUP(D15,'50库存'!$C$2:$U$313,19,0) -> 25.74 | I15: Percent | J15: =CEILING($J$13*B15/H15,1) -> 20 | K15: 3 | L15: =CEILING($L$13*B15/H15,1) -> 28 | M15: 5 | N15: =CEILING($N$13*B15/H15,1) -> 47 | O15: 8
A16: 1 | B16: =IF(OR(VLOOKUP(D16,Sheet4!$F$9:$G$245,2,0)="SS",VLOOKUP(D16,Sheet4!$F$9:$G$245,2,0)="S"),2,1) -> 1 | C16: =VLOOKUP(D16,Sheet4!$F$9:$G$245,2,0) -> P | D16: B0DTP4VV5V | E16: =VLOOKUP(D16,'50库存'!$C$2:$D$313,2,0) -> 50US-MaiGanYaZi-005 | F16: =VLOOKUP(E16,'50库存'!$D$2:$U$313,18,0) -> 29.99 | G16: =COUNTIF('50库存'!$C$2:$C$313,D16) -> 1 | H16: =VLOOKUP(D16,'50库存'!$C$2:$U$313,19,0) -> 29.99 | I16: Percent | J16: =CEILING($J$13*B16/H16,1) -> 17 | K16: 3 | L16: =CEILING($L$13*B16/H16,1) -> 24 | M16: 5 | N16: =CEILING($N$13*B16/H16,1) -> 41 | O16: 8
B17: =IF(OR(VLOOKUP(D17,Sheet4!$F$9:$G$245,2,0)="SS",VLOOKUP(D17,Sheet4!$F$9:$G$245,2,0)="S"),2,1) -> 1 | C17: =VLOOKUP(D17,Sheet4!$F$9:$G$245,2,0) -> P | D17: B0C7G7W43V | E17: =VLOOKUP(D17,'50库存'!$C$2:$D$313,2,0) -> 50US-MaoCiBabyBall001 | F17: =VLOOKUP(E17,'50库存'!$D$2:$U$313,18,0) -> 19.99 | G17: =COUNTIF('50库存'!$C$2:$C$313,D17) -> 1 | H17: =VLOOKUP(D17,'50库存'!$C$2:$U$313,19,0) -> 19.99 | I17: Percent | J17: =CEILING($J$13*B17/H17,1) -> 26 | K17: 3 | L17: =CEILING($L$13*B17/H17,1) -> 36 | M17: 5 | N17: =CEILING($N$13*B17/H17,1) -> 61 | O17: 8
B18: =IFERROR(IF(OR(VLOOKUP(D18,Sheet4!$F$9:$G$245,2,0)="SS",VLOOKUP(D18,Sheet4!$F$9:$G$245,2,0)="S"),2,1),1) -> 1 | C18: =VLOOKUP(D18,Sheet4!$F$9:$G$245,2,0) -> #N/A | D18: B0C7G9L4GD | E18: =VLOOKUP(D18,'50库存'!$C$2:$D$313,2,0) -> 50US-MaoCiBabyBall002 | F18: =VLOOKUP(E18,'50库存'!$D$2:$U$313,18,0) -> 18.99 | G18: =COUNTIF('50库存'!$C$2:$C$313,D18) -> 1 | H18: =VLOOKUP(D18,'50库存'!$C$2:$U$313,19,0) -> 18.99 | I18: Percent | J18: =CEILING($J$13*B18/H18,1) -> 27 | K18: 3 | L18: =CEILING($L$13*B18/H18,1) -> 37 | M18: 5 | N18: =CEILING($N$13*B18/H18,1) -> 64 | O18: 8
B19: =IFERROR(IF(OR(VLOOKUP(D19,Sheet4!$F$9:$G$245,2,0)="SS",VLOOKUP(D19,Sheet4!$F$9:$G$245,2,0)="S"),2,1),1) -> 1 | C19: =VLOOKUP(D19,Sheet4!$F$9:$G$245,2,0) -> P | D19: B0CCJKDDLG | E19: 50Fengrenji-WhiteNEW01 | F19: =VLOOKUP(E19,'50库存'!$D$2:$U$313,18,0) -> 43.37 | G19: =COUNTIF('50库存'!$C$2:$C$313,D19) -> 3 | H19: =VLOOKUP(E19,'50库存'!$D$2:$U$313,18,0) -> 43.37 | I19: Percent | J19: =CEILING($J$13*B19/H19,1) -> 12 | K19: 3 | L19: =CEILING($L$13*B19/H19,1) -> 17 | M19: 5 | N19: =CEILING($N$13*B19/H19,1) -> 28 | O19: 8
B20: =IFERROR(IF(OR(VLOOKUP(D20,Sheet4!$F$9:$G$245,2,0)="SS",VLOOKUP(D20,Sheet4!$F$9:$G$245,2,0)="S"),2,1),1) -> 1 | C20: =VLOOKUP(D20,Sheet4!$F$9:$G$245,2,0) -> P | D20: B0CCJKDDLG | E20: 50US-FengRenJi202-new | F20: =VLOOKUP(E20,'50库存'!$D$2:$U$313,18,0) -> 43.39 | H20: =VLOOKUP(E20,'50库存'!$D$2:$U$313,18,0) -> 43.39 | I20: Percent | J20: =CEILING($J$13*B20/H20,1) -> 12 | K20: 3 | L20: =CEILING($L$13*B20/H20,1) -> 17 | M20: 5 | N20: =CEILING($N$13*B20/H20,1) -> 28 | O20: 8
B21: =IFERROR(IF(OR(VLOOKUP(D21,Sheet4!$F$9:$G$245,2,0)="SS",VLOOKUP(D21,Sheet4!$F$9:$G$245,2,0)="S"),2,1),1) -> 1 | C21: =VLOOKUP(D21,Sheet4!$F$9:$G$245,2,0) -> P | D21: B0CCJKDDLG | E21: FRenJ-White 002 | F21: =VLOOKUP(E21,'50库存'!$D$2:$U$313,18,0) -> 0 | H21: =VLOOKUP(E21,'50库存'!$D$2:$U$313,18,0) -> 0 | I21: Percent | J21: =CEILING($J$13*B21/H21,1) -> #DIV/0! | K21: 3 | L21: =CEILING($L$13*B21/H21,1) -> #DIV/0! | M21: 5 | N21: =CEILING($N$13*B21/H21,1) -> #DIV/0! | O21: 8
B22: =IFERROR(IF(OR(VLOOKUP(D22,Sheet4!$F$9:$G$245,2,0)="SS",VLOOKUP(D22,Sheet4!$F$9:$G$245,2,0)="S"),2,1),1) -> 1 | C22: =VLOOKUP(D22,Sheet4!$F$9:$G$245,2,0) -> #N/A | D22: B0CCJKFGGG | E22: WhiteFengrenjiNew02 | F22: =VLOOKUP(E22,'50库存'!$D$2:$U$313,18,0) -> 43.99 | G22: =COUNTIF('50库存'!$C$2:$C$313,D22) -> 2 | H22: =VLOOKUP(E22,'50库存'!$D$2:$U$313,18,0) -> 43.99 | I22: Percent | J22: =CEILING($J$13*B22/H22,1) -> 12 | K22: 3 | L22: =CEILING($L$13*B22/H22,1) -> 16 | M22: 5 | N22: =CEILING($N$13*B22/H22,1) -> 28 | O22: 8
B23: =IFERROR(IF(OR(VLOOKUP(D23,Sheet4!$F$9:$G$245,2,0)="SS",VLOOKUP(D23,Sheet4!$F$9:$G$245,2,0)="S"),2,1),1) -> 1 | C23: =VLOOKUP(D23,Sheet4!$F$9:$G$245,2,0) -> #N/A | D23: B0CCJKFGGG | E23: FRenJ-White 004 | F23: =VLOOKUP(E23,'50库存'!$D$2:$U$313,18,0) -> 0 | H23: =VLOOKUP(E23,'50库存'!$D$2:$U$313,18,0) -> 0 | I23: Percent | J23: =CEILING($J$13*B23/H23,1) -> #DIV/0! | K23: 3 | L23: =CEILING($L$13*B23/H23,1) -> #DIV/0! | M23: 5 | N23: =CEILING($N$13*B23/H23,1) -> #DIV/0! | O23: 8
B24: =IFERROR(IF(OR(VLOOKUP(D24,Sheet4!$F$9:$G$245,2,0)="SS",VLOOKUP(D24,Sheet4!$F$9:$G$245,2,0)="S"),2,1),1) -> 1 | C24: =VLOOKUP(D24,Sheet4!$F$9:$G$245,2,0) -> A | D24: B0DTTBGYWW | E24: =VLOOKUP(D24,'50库存'!$C$2:$D$313,2,0) -> 50US-GenSuiYa-003 | F24: =VLOOKUP(E24,'50库存'!$D$2:$U$313,18,0) -> 39.99 | G24: =COUNTIF('50库存'!$C$2:$C$313,D24) -> 1 | H24: =VLOOKUP(E24,'50库存'!$D$2:$U$313,18,0) -> 39.99 | I24: Percent | J24: =CEILING($J$13*B24/H24,1) -> 13 | K24: 3 | L24: =CEILING($L$13*B24/H24,1) -> 18 | M24: 5 | N24: =CEILING($N$13*B24/H24,1) -> 31 | O24: 8
B25: =IFERROR(IF(OR(VLOOKUP(D25,Sheet4!$F$9:$G$245,2,0)="SS",VLOOKUP(D25,Sheet4!$F$9:$G$245,2,0)="S"),2,1),1) -> 1 | C25: =VLOOKUP(D25,Sheet4!$F$9:$G$245,2,0) -> A | D25: B0DTT3NTLG | E25: =VLOOKUP(D25,'50库存'!$C$2:$D$313,2,0) -> 50US-GenSuiYa-004 | F25: =VLOOKUP(E25,'50库存'!$D$2:$U$313,18,0) -> 39.99 | G25: =COUNTIF('50库存'!$C$2:$C$313,D25) -> 1 | H25: =VLOOKUP(E25,'50库存'!$D$2:$U$313,18,0) -> 39.99 | I25: Percent | J25: =CEILING($J$13*B25/H25,1) -> 13 | K25: 3 | L25: =CEILING($L$13*B25/H25,1) -> 18 | M25: 5 | N25: =CEILING($N$13*B25/H25,1) -> 31 | O25: 8
B26: =IFERROR(IF(OR(VLOOKUP(D26,Sheet4!$F$9:$G$245,2,0)="SS",VLOOKUP(D26,Sheet4!$F$9:$G$245,2,0)="S"),2,1),1) -> 1 | C26: =VLOOKUP(D26,Sheet4!$F$9:$G$245,2,0) -> A | D26: B0DTT4GNWW | E26: =VLOOKUP(D26,'50库存'!$C$2:$D$313,2,0) -> 50US-GenSuiYa-005 | F26: =VLOOKUP(E26,'50库存'!$D$2:$U$313,18,0) -> 36.99 | G26: =COUNTIF('50库存'!$C$2:$C$313,D26) -> 1 | H26: =VLOOKUP(E26,'50库存'!$D$2:$U$313,18,0) -> 36.99 | I26: Percent | J26: =CEILING($J$13*B26/H26,1) -> 14 | K26: 3 | L26: =CEILING($L$13*B26/H26,1) -> 19 | M26: 5 | N26: =CEILING($N$13*B26/H26,1) -> 33 | O26: 8
B27: =IFERROR(IF(OR(VLOOKUP(D27,Sheet4!$F$9:$G$245,2,0)="SS",VLOOKUP(D27,Sheet4!$F$9:$G$245,2,0)="S"),2,1),1) -> 1 | C27: =VLOOKUP(D27,Sheet4!$F$9:$G$245,2,0) -> A | D27: B0DTT8SK6H | E27: =VLOOKUP(D27,'50库存'!$C$2:$D$313,2,0) -> 50US-GenSuiYa-006 | F27: =VLOOKUP(E27,'50库存'!$D$2:$U$313,18,0) -> 35.99 | G27: =COUNTIF('50库存'!$C$2:$C$313,D27) -> 1 | H27: =VLOOKUP(E27,'50库存'!$D$2:$U$313,18,0) -> 35.99 | I27: Percent | J27: =CEILING($J$13*B27/H27,1) -> 14 | K27: 3 | L27: =CEILING($L$13*B27/H27,1) -> 20 | M27: 5 | N27: =CEILING($N$13*B27/H27,1) -> 34 | O27: 8
B28: =IFERROR(IF(OR(VLOOKUP(D28,Sheet4!$F$9:$G$245,2,0)="SS",VLOOKUP(D28,Sheet4!$F$9:$G$245,2,0)="S"),2,1),1) -> 1 | C28: =VLOOKUP(D28,Sheet4!$F$9:$G$245,2,0) -> A | D28: B0DYMGYWJ7 | E28: =VLOOKUP(D28,'50库存'!$C$2:$D$313,2,0) -> 50-3Ddongwupintu-Shizi1 | F28: =VLOOKUP(E28,'50库存'!$D$2:$U$313,18,0) -> 23.99 | G28: =COUNTIF('50库存'!$C$2:$C$313,D28) -> 1 | H28: =VLOOKUP(E28,'50库存'!$D$2:$U$313,18,0) -> 23.99 | I28: Percent | J28: =CEILING($J$13*B28/H28,1) -> 21 | K28: 3 | L28: =CEILING($L$13*B28/H28,1) -> 30 | M28: 5 | N28: =CEILING($N$13*B28/H28,1) -> 51 | O28: 8
B29: =IFERROR(IF(OR(VLOOKUP(D29,Sheet4!$F$9:$G$245,2,0)="SS",VLOOKUP(D29,Sheet4!$F$9:$G$245,2,0)="S"),2,1),1) -> 1 | C29: =VLOOKUP(D29,Sheet4!$F$9:$G$245,2,0) -> A | D29: B0DYN4HDJW | E29: =VLOOKUP(D29,'50库存'!$C$2:$D$313,2,0) -> 50-3Ddongwupintu-Lu1 | F29: =VLOOKUP(E29,'50库存'!$D$2:$U$313,18,0) -> 23.99 | G29: =COUNTIF('50库存'!$C$2:$C$313,D29) -> 1 | H29: =VLOOKUP(E29,'50库存'!$D$2:$U$313,18,0) -> 23.99 | I29: Percent | J29: =CEILING($J$13*B29/H29,1) -> 21 | K29: 3 | L29: =CEILING($L$13*B29/H29,1) -> 30 | M29: 5 | N29: =CEILING($N$13*B29/H29,1) -> 51 | O29: 8
B30: =IFERROR(IF(OR(VLOOKUP(D30,Sheet4!$F$9:$G$245,2,0)="SS",VLOOKUP(D30,Sheet4!$F$9:$G$245,2,0)="S"),2,1),1) -> 1 | C30: =VLOOKUP(D30,Sheet4!$F$9:$G$245,2,0) -> A | D30: B0FHH5Q86M | E30: =VLOOKUP(D30,'50库存'!$C$2:$D$313,2,0) -> G502GuYuKaChe001 | F30: =VLOOKUP(E30,'50库存'!$D$2:$U$313,18,0) -> 22.99 | G30: =COUNTIF('50库存'!$C$2:$C$313,D30) -> 1 | H30: =VLOOKUP(E30,'50库存'!$D$2:$U$313,18,0) -> 22.99 | I30: Percent | J30: =CEILING($J$13*B30/H30,1) -> 22 | K30: 3 | L30: =CEILING($L$13*B30/H30,1) -> 31 | M30: 5 | N30: =CEILING($N$13*B30/H30,1) -> 53 | O30: 8
B31: =IFERROR(IF(OR(VLOOKUP(D31,Sheet4!$F$9:$G$245,2,0)="SS",VLOOKUP(D31,Sheet4!$F$9:$G$245,2,0)="S"),2,1),1) -> 1 | C31: =VLOOKUP(D31,Sheet4!$F$9:$G$245,2,0) -> A | D31: B0FHHC21LG | E31: =VLOOKUP(D31,'50库存'!$C$2:$D$313,2,0) -> G502GuYuKaChe002 | F31: =VLOOKUP(E31,'50库存'!$D$2:$U$313,18,0) -> 22.99 | G31: =COUNTIF('50库存'!$C$2:$C$313,D31) -> 1 | H31: =VLOOKUP(E31,'50库存'!$D$2:$U$313,18,0) -> 22.99 | I31: Percent | J31: =CEILING($J$13*B31/H31,1) -> 22 | K31: 3 | L31: =CEILING($L$13*B31/H31,1) -> 31 | M31: 5 | N31: =CEILING($N$13*B31/H31,1) -> 53 | O31: 8
B32: =IFERROR(IF(OR(VLOOKUP(D32,Sheet4!$F$9:$G$245,2,0)="SS",VLOOKUP(D32,Sheet4!$F$9:$G$245,2,0)="S"),2,1),1) -> 1 | C32: =VLOOKUP(D32,Sheet4!$F$9:$G$245,2,0) -> A | D32: B0FHHC11GJ | E32: =VLOOKUP(D32,'50库存'!$C$2:$D$313,2,0) -> G503GuYuWaJueJi001 | F32: =VLOOKUP(E32,'50库存'!$D$2:$U$313,18,0) -> 23.99 | G32: =COUNTIF('50库存'!$C$2:$C$313,D32) -> 1 | H32: =VLOOKUP(E32,'50库存'!$D$2:$U$313,18,0) -> 23.99 | I32: Percent | J32: =CEILING($J$13*B32/H32,1) -> 21 | K32: 3 | L32: =CEILING($L$13*B32/H32,1) -> 30 | M32: 5 | N32: =CEILING($N$13*B32/H32,1) -> 51 | O32: 8
B33: =IFERROR(IF(OR(VLOOKUP(D33,Sheet4!$F$9:$G$245,2,0)="SS",VLOOKUP(D33,Sheet4!$F$9:$G$245,2,0)="S"),2,1),1) -> 1 | C33: =VLOOKUP(D33,Sheet4!$F$9:$G$245,2,0) -> A | D33: B0FHH5PQ4H | E33: =VLOOKUP(D33,'50库存'!$C$2:$D$313,2,0) -> G503GuYuWaJueJi002 | F33: =VLOOKUP(E33,'50库存'!$D$2:$U$313,18,0) -> 22.99 | G33: =COUNTIF('50库存'!$C$2:$C$313,D33) -> 1 | H33: =VLOOKUP(E33,'50库存'!$D$2:$U$313,18,0) -> 22.99 | I33: Percent | J33: =CEILING($J$13*B33/H33,1) -> 22 | K33: 3 | L33: =CEILING($L$13*B33/H33,1) -> 31 | M33: 5 | N33: =CEILING($N$13*B33/H33,1) -> 53 | O33: 8
B34: =IFERROR(IF(OR(VLOOKUP(D34,Sheet4!$F$9:$G$245,2,0)="SS",VLOOKUP(D34,Sheet4!$F$9:$G$245,2,0)="S"),2,1),1) -> 1 | C34: =VLOOKUP(D34,Sheet4!$F$9:$G$245,2,0) -> #N/A | D34: B0GCH6J851 | E34: G505Guyuhuoche | F34: =VLOOKUP(E34,'50库存'!$D$2:$U$313,18,0) -> 0 | G34: =COUNTIF('50库存'!$C$2:$C$313,D34) -> 2 | H34: =VLOOKUP(E34,'50库存'!$D$2:$U$313,18,0) -> 0 | I34: Percent | J34: =CEILING($J$13*B34/H34,1) -> #DIV/0! | K34: 3 | L34: =CEILING($L$13*B34/H34,1) -> #DIV/0! | M34: 5 | N34: =CEILING($N$13*B34/H34,1) -> #DIV/0! | O34: 8
B35: =IFERROR(IF(OR(VLOOKUP(D35,Sheet4!$F$9:$G$245,2,0)="SS",VLOOKUP(D35,Sheet4!$F$9:$G$245,2,0)="S"),2,1),1) -> 1 | C35: =VLOOKUP(D35,Sheet4!$F$9:$G$245,2,0) -> #N/A | D35: B0GCH6J851 | E35: 50US-G501GuYuHuoChe | F35: =VLOOKUP(E35,'50库存'!$D$2:$U$313,18,0) -> 19.99 | G35: =COUNTIF('50库存'!$C$2:$C$313,D35) -> 2 | H35: =VLOOKUP(E35,'50库存'!$D$2:$U$313,18,0) -> 19.99 | I35: Percent | J35: =CEILING($J$13*B35/H35,1) -> 26 | K35: 3 | L35: =CEILING($L$13*B35/H35,1) -> 36 | M35: 5 | N35: =CEILING($N$13*B35/H35,1) -> 61 | O35: 8
B36: =IFERROR(IF(OR(VLOOKUP(D36,Sheet4!$F$9:$G$245,2,0)="SS",VLOOKUP(D36,Sheet4!$F$9:$G$245,2,0)="S"),2,1),1) -> 1 | C36: =VLOOKUP(D36,Sheet4!$F$9:$G$245,2,0) -> #N/A | D36: B0GCHH67CH | E36: =VLOOKUP(D36,'50库存'!$C$2:$D$313,2,0) -> G504Guyuhuoche | F36: =VLOOKUP(E36,'50库存'!$D$2:$U$313,18,0) -> 20.99 | G36: =COUNTIF('50库存'!$C$2:$C$313,D36) -> 1 | H36: =VLOOKUP(E36,'50库存'!$D$2:$U$313,18,0) -> 20.99 | I36: Percent | J36: =CEILING($J$13*B36/H36,1) -> 24 | K36: 3 | L36: =CEILING($L$13*B36/H36,1) -> 34 | M36: 5 | N36: =CEILING($N$13*B36/H36,1) -> 58 | O36: 8
B37: =IFERROR(IF(OR(VLOOKUP(D37,Sheet4!$F$9:$G$245,2,0)="SS",VLOOKUP(D37,Sheet4!$F$9:$G$245,2,0)="S"),2,1),1) -> 1 | C37: =VLOOKUP(D37,Sheet4!$F$9:$G$245,2,0) -> #N/A | D37: B0FHH5PNNZ | E37: 50US-G505GuYuZhiShengJi | F37: =VLOOKUP(E37,'50库存'!$D$2:$U$313,18,0) -> 0 | G37: =COUNTIF('50库存'!$C$2:$C$313,D37) -> 2 | H37: =VLOOKUP(E37,'50库存'!$D$2:$U$313,18,0) -> 0 | I37: Percent | J37: =CEILING($J$13*B37/H37,1) -> #DIV/0! | K37: 3 | L37: =CEILING($L$13*B37/H37,1) -> #DIV/0! | M37: 5 | N37: =CEILING($N$13*B37/H37,1) -> #DIV/0! | O37: 8
D38: B0FHH5PNNZ | E38: G501Guyuhuoche | F38: =VLOOKUP(E38,'50库存'!$D$2:$U$313,18,0) -> 0 | G38: =COUNTIF('50库存'!$C$2:$C$313,D38) -> 2 | H38: =VLOOKUP(E38,'50库存'!$D$2:$U$313,18,0) -> 0 | I38: Percent | J38: =CEILING($J$13*B38/H38,1) -> #DIV/0! | K38: 3 | L38: =CEILING($L$13*B38/H38,1) -> #DIV/0! | M38: 5 | N38: =CEILING($N$13*B38/H38,1) -> #DIV/0! | O38: 8
B39: =IFERROR(IF(OR(VLOOKUP(D39,Sheet4!$F$9:$G$245,2,0)="SS",VLOOKUP(D39,Sheet4!$F$9:$G$245,2,0)="S"),2,1),1) -> 1 | C39: =VLOOKUP(D39,Sheet4!$F$9:$G$245,2,0) -> A | D39: B0FG6W44P5 | E39: =VLOOKUP(D39,'50库存'!$C$2:$D$313,2,0) -> 50US-HanBaoJi-002 | F39: =VLOOKUP(E39,'50库存'!$D$2:$U$313,18,0) -> 36.99 | G39: =COUNTIF('50库存'!$C$2:$C$313,D39) -> 1 | H39: =VLOOKUP(E39,'50库存'!$D$2:$U$313,18,0) -> 36.99 | I39: Percent | J39: =CEILING($J$13*B39/H39,1) -> 14 | K39: 3 | L39: =CEILING($L$13*B39/H39,1) -> 19 | M39: 5 | N39: =CEILING($N$13*B39/H39,1) -> 33 | O39: 8
B40: =IFERROR(IF(OR(VLOOKUP(D40,Sheet4!$F$9:$G$245,2,0)="SS",VLOOKUP(D40,Sheet4!$F$9:$G$245,2,0)="S"),2,1),1) -> 1 | C40: =VLOOKUP(D40,Sheet4!$F$9:$G$245,2,0) -> A | D40: B0FG73GKBG | E40: =VLOOKUP(D40,'50库存'!$C$2:$D$313,2,0) -> 50US-HanBaoJi-003 | F40: =VLOOKUP(E40,'50库存'!$D$2:$U$313,18,0) -> 38.99 | G40: =COUNTIF('50库存'!$C$2:$C$313,D40) -> 1 | H40: =VLOOKUP(E40,'50库存'!$D$2:$U$313,18,0) -> 38.99 | I40: Percent | J40: =CEILING($J$13*B40/H40,1) -> 13 | K40: 3 | L40: =CEILING($L$13*B40/H40,1) -> 18 | M40: 5 | N40: =CEILING($N$13*B40/H40,1) -> 31 | O40: 8
B41: =IFERROR(IF(OR(VLOOKUP(D41,Sheet4!$F$9:$G$245,2,0)="SS",VLOOKUP(D41,Sheet4!$F$9:$G$245,2,0)="S"),2,1),1) -> 1 | C41: =VLOOKUP(D41,Sheet4!$F$9:$G$245,2,0) -> P | D41: B0FHKLCG68 | E41: =VLOOKUP(D41,'50库存'!$C$2:$D$313,2,0) -> YinErTanSheTouLanJi-0001 | F41: =VLOOKUP(E41,'50库存'!$D$2:$U$313,18,0) -> 29.99 | G41: =COUNTIF('50库存'!$C$2:$C$313,D41) -> 1 | H41: =VLOOKUP(E41,'50库存'!$D$2:$U$313,18,0) -> 29.99 | I41: Percent | J41: =CEILING($J$13*B41/H41,1) -> 17 | K41: 3 | L41: =CEILING($L$13*B41/H41,1) -> 24 | M41: 5 | N41: =CEILING($N$13*B41/H41,1) -> 41 | O41: 8
B42: =IFERROR(IF(OR(VLOOKUP(D42,Sheet4!$F$9:$G$245,2,0)="SS",VLOOKUP(D42,Sheet4!$F$9:$G$245,2,0)="S"),2,1),1) -> 1 | C42: =VLOOKUP(D42,Sheet4!$F$9:$G$245,2,0) -> #N/A | D42: B0F13S45L4 | E42: =VLOOKUP(D42,'50库存'!$C$2:$D$313,2,0) -> 50US-DuiDieKongLong-003 | F42: =VLOOKUP(E42,'50库存'!$D$2:$U$313,18,0) -> 0 | G42: =COUNTIF('50库存'!$C$2:$C$313,D42) -> 1 | H42: =VLOOKUP(E42,'50库存'!$D$2:$U$313,18,0) -> 0 | I42: Percent | J42: =CEILING($J$13*B42/H42,1) -> #DIV/0! | K42: 3 | L42: =CEILING($L$13*B42/H42,1) -> #DIV/0! | M42: 5 | N42: =CEILING($N$13*B42/H42,1) -> #DIV/0! | O42: 8
B43: =IFERROR(IF(OR(VLOOKUP(D43,Sheet4!$F$9:$G$245,2,0)="SS",VLOOKUP(D43,Sheet4!$F$9:$G$245,2,0)="S"),2,1),1) -> 1 | C43: =VLOOKUP(D43,Sheet4!$F$9:$G$245,2,0) -> #N/A | D43: B0FMXV3JBC | E43: =VLOOKUP(D43,'50库存'!$C$2:$D$313,2,0) -> 50US-DuiDieKongLong-007 | F43: =VLOOKUP(E43,'50库存'!$D$2:$U$313,18,0) -> 36.99 | G43: =COUNTIF('50库存'!$C$2:$C$313,D43) -> 1 | H43: =VLOOKUP(E43,'50库存'!$D$2:$U$313,18,0) -> 36.99 | I43: Percent | J43: =CEILING($J$13*B43/H43,1) -> 14 | K43: 3 | L43: =CEILING($L$13*B43/H43,1) -> 19 | M43: 5 | N43: =CEILING($N$13*B43/H43,1) -> 33 | O43: 8
B44: =IFERROR(IF(OR(VLOOKUP(D44,Sheet4!$F$9:$G$245,2,0)="SS",VLOOKUP(D44,Sheet4!$F$9:$G$245,2,0)="S"),2,1),1) -> 1 | C44: =VLOOKUP(D44,Sheet4!$F$9:$G$245,2,0) -> #N/A | D44: B0GJWXPW57，50US-RuanDanTankFaSheTou-01 | F44: 39.99 | G44: =COUNTIF('50库存'!$C$2:$C$313,D44) -> 0 | H44: 39.99 | I44: Percent | J44: =CEILING($J$13*B44/H44,1) -> 13 | K44: 3 | L44: =CEILING($L$13*B44/H44,1) -> 18 | M44: 5 | N44: =CEILING($N$13*B44/H44,1) -> 31 | O44: 8
D48: only-value
D49: B0DTP8B4FZ | E49: 50US-MaiGanYaZi-013 | F49: 25.74 | G49: 1 | H49: 25.74 | I49: Percent | J49: 20 | K49: 3 | L49: 28 | M49: 5 | N49: 47 | O49: 8
D50: B0DTP4VV5V | E50: 50US-MaiGanYaZi-005 | F50: 29.99 | G50: 1 | H50: 29.99 | I50: Percent | J50: 17 | K50: 3 | L50: 24 | M50: 5 | N50: 41 | O50: 8
D51: B0C7G7W43V | E51: 50US-MaoCiBabyBall001 | F51: 19.99 | G51: 1 | H51: 19.99 | I51: Percent | J51: 26 | K51: 3 | L51: 36 | M51: 5 | N51: 61 | O51: 8
D52: B0C7G9L4GD | E52: 50US-MaoCiBabyBall002 | F52: 18.99 | G52: 1 | H52: 18.99 | I52: Percent | J52: 27 | K52: 3 | L52: 37 | M52: 5 | N52: 64 | O52: 8
D53: B0CCJKDDLG | E53: 50Fengrenji-WhiteNEW01 | F53: 43.37 | G53: 3 | H53: 43.37 | I53: Percent | J53: 12 | K53: 3 | L53: 17 | M53: 5 | N53: 28 | O53: 8
D54: B0CCJKDDLG | E54: 50US-FengRenJi202-new | F54: 43.39 | H54: 43.39 | I54: Percent | J54: 12 | K54: 3 | L54: 17 | M54: 5 | N54: 28 | O54: 8
D55: B0CCJKDDLG | E55: FRenJ-White 002 | F55: 0 | H55: 0 | I55: Percent | J55: #DIV/0! | K55: 3 | L55: #DIV/0! | M55: 5 | N55: #DIV/0! | O55: 8
D56: B0CCJKFGGG | E56: WhiteFengrenjiNew02 | F56: 43.99 | G56: 2 | H56: 43.99 | I56: Percent | J56: 12 | K56: 3 | L56: 16 | M56: 5 | N56: 28 | O56: 8
D57: B0CCJKFGGG | E57: FRenJ-White 004 | F57: 0 | H57: 0 | I57: Percent | J57: #DIV/0! | K57: 3 | L57: #DIV/0! | M57: 5 | N57: #DIV/0! | O57: 8
D58: B0DTTBGYWW | E58: 50US-GenSuiYa-003 | F58: 39.99 | G58: 1 | H58: 39.99 | I58: Percent | J58: 13 | K58: 3 | L58: 18 | M58: 5 | N58: 31 | O58: 8
D59: B0DTT3NTLG | E59: 50US-GenSuiYa-004 | F59: 39.99 | G59: 1 | H59: 39.99 | I59: Percent | J59: 13 | K59: 3 | L59: 18 | M59: 5 | N59: 31 | O59: 8
D60: B0DTT4GNWW | E60: 50US-GenSuiYa-005 | F60: 36.99 | G60: 1 | H60: 36.99 | I60: Percent | J60: 14 | K60: 3 | L60: 19 | M60: 5 | N60: 33 | O60: 8
D61: B0DTT8SK6H | E61: 50US-GenSuiYa-006 | F61: 35.99 | G61: 1 | H61: 35.99 | I61: Percent | J61: 14 | K61: 3 | L61: 20 | M61: 5 | N61: 34 | O61: 8
D62: B0DYMGYWJ7 | E62: 50-3Ddongwupintu-Shizi1 | F62: 23.99 | G62: 1 | H62: 23.99 | I62: Percent | J62: 21 | K62: 3 | L62: 30 | M62: 5 | N62: 51 | O62: 8
D63: B0DYN4HDJW | E63: 50-3Ddongwupintu-Lu1 | F63: 23.99 | G63: 1 | H63: 23.99 | I63: Percent | J63: 21 | K63: 3 | L63: 30 | M63: 5 | N63: 51 | O63: 8
D64: B0FHH5Q86M | E64: G502GuYuKaChe001 | F64: 22.99 | G64: 1 | H64: 22.99 | I64: Percent | J64: 22 | K64: 3 | L64: 31 | M64: 5 | N64: 53 | O64: 8
D65: B0FHHC21LG | E65: G502GuYuKaChe002 | F65: 22.99 | G65: 1 | H65: 22.99 | I65: Percent | J65: 22 | K65: 3 | L65: 31 | M65: 5 | N65: 53 | O65: 8
D66: B0FHHC11GJ | E66: G503GuYuWaJueJi001 | F66: 23.99 | G66: 1 | H66: 23.99 | I66: Percent | J66: 21 | K66: 3 | L66: 30 | M66: 5 | N66: 51 | O66: 8
D67: B0FHH5PQ4H | E67: G503GuYuWaJueJi002 | F67: 22.99 | G67: 1 | H67: 22.99 | I67: Percent | J67: 22 | K67: 3 | L67: 31 | M67: 5 | N67: 53 | O67: 8
D68: B0GCH6J851 | E68: G505Guyuhuoche | F68: 0 | G68: 2 | H68: 0 | I68: Percent | J68: #DIV/0! | K68: 3 | L68: #DIV/0! | M68: 5 | N68: #DIV/0! | O68: 8
D69: B0GCH6J851 | E69: 50US-G501GuYuHuoChe | F69: 19.99 | G69: 2 | H69: 19.99 | I69: Percent | J69: 26 | K69: 3 | L69: 36 | M69: 5 | N69: 61 | O69: 8
D70: B0GCHH67CH | E70: G504Guyuhuoche | F70: 20.99 | G70: 1 | H70: 20.99 | I70: Percent | J70: 24 | K70: 3 | L70: 34 | M70: 5 | N70: 58 | O70: 8
D71: B0FHH5PNNZ | E71: 50US-G505GuYuZhiShengJi | F71: 0 | G71: 2 | H71: 0 | I71: Percent | J71: #DIV/0! | K71: 3 | L71: #DIV/0! | M71: 5 | N71: #DIV/0! | O71: 8
D72: B0FG6W44P5 | E72: 50US-HanBaoJi-002 | F72: 36.99 | G72: 1 | H72: 36.99 | I72: Percent | J72: 14 | K72: 3 | L72: 19 | M72: 5 | N72: 33 | O72: 8
D73: B0FG73GKBG | E73: 50US-HanBaoJi-003 | F73: 38.99 | G73: 1 | H73: 38.99 | I73: Percent | J73: 13 | K73: 3 | L73: 18 | M73: 5 | N73: 31 | O73: 8
D74: B0FHKLCG68 | E74: YinErTanSheTouLanJi-0001 | F74: 29.99 | G74: 1 | H74: 29.99 | I74: Percent | J74: 17 | K74: 3 | L74: 24 | M74: 5 | N74: 41 | O74: 8
D75: B0F13S45L4 | E75: 50US-DuiDieKongLong-003 | F75: 0 | G75: 1 | H75: 0 | I75: Percent | J75: #DIV/0! | K75: 3 | L75: #DIV/0! | M75: 5 | N75: #DIV/0! | O75: 8
D76: B0FMXV3JBC | E76: 50US-DuiDieKongLong-007 | F76: 36.99 | G76: 1 | H76: 36.99 | I76: Percent | J76: 14 | K76: 3 | L76: 19 | M76: 5 | N76: 33 | O76: 8
D87: 149
D89: B0CT5J8GCW
D90: B0CT5GKHRM
D91: B0FHPSR92X
D92: B0FHP2GN29
D93: B0FPC6D218
D94: B0F1Y6LC4H
D95: B0DD7HPPGX
D96: B0FMK6R2HS
A102: 2 | B102: =IF(OR(C102="SS",C102="S"),2,1) -> 1 | C102: =VLOOKUP(D102,Sheet4!$K$9:$L$110,2,0) -> A | D102: B0CT5J8GCW | E102: =VLOOKUP(D102,'149库存'!$C$2:$U$199,2,0) -> 149US-8JianTaoBingXiangChiLun | F102: =VLOOKUP(E102,'149库存'!$D$2:$U$313,18,0) -> 34.99 | G102: =COUNTIF('149库存'!$C$2:$C$199,D102) -> 1 | H102: =VLOOKUP(D102,'149库存'!$C$2:$U$313,19,0) -> 34.99 | I102: Percent | J102: =CEILING($J$13*B102/H102,1) -> 15 | K102: 3 | L102: =CEILING($L$13*B102/H102,1) -> 21 | M102: 5 | N102: =CEILING($N$13*B102/H102,1) -> 35 | O102: 8
A103: 1 | B103: =IF(OR(C103="SS",C103="S"),2,1) -> 1 | C103: =VLOOKUP(D103,Sheet4!$K$9:$L$110,2,0) -> A | D103: B0CT5GKHRM | E103: =VLOOKUP(D103,'149库存'!$C$2:$U$199,2,0) -> 149US-XiaoHaoBingXiangChiLun | F103: =VLOOKUP(E103,'149库存'!$D$2:$U$313,18,0) -> 35.99 | G103: =COUNTIF('149库存'!$C$2:$C$199,D103) -> 1 | H103: =VLOOKUP(D103,'149库存'!$C$2:$U$313,19,0) -> 35.99 | I103: Percent | J103: =CEILING($J$13*B103/H103,1) -> 14 | K103: 3 | L103: =CEILING($L$13*B103/H103,1) -> 20 | M103: 5 | N103: =CEILING($N$13*B103/H103,1) -> 34 | O103: 8
B104: =IF(OR(C104="SS",C104="S"),2,1) -> 1 | C104: =VLOOKUP(D104,Sheet4!$K$9:$L$110,2,0) -> A | D104: B0FHPSR92X | E104: =VLOOKUP(D104,'149库存'!$C$2:$U$199,2,0) -> 149US-SoftCiLiGuan26P-007 | F104: =VLOOKUP(E104,'149库存'!$D$2:$U$313,18,0) -> 33.99 | G104: =COUNTIF('149库存'!$C$2:$C$199,D104) -> 1 | H104: =VLOOKUP(D104,'149库存'!$C$2:$U$313,19,0) -> 33.99 | I104: Percent | J104: =CEILING($J$13*B104/H104,1) -> 15 | K104: 3 | L104: =CEILING($L$13*B104/H104,1) -> 21 | M104: 5 | N104: =CEILING($N$13*B104/H104,1) -> 36 | O104: 8
B105: =IFERROR(IF(OR(C105="SS",C105="S"),2,1),1) -> 1 | C105: =VLOOKUP(D105,Sheet4!$K$9:$L$110,2,0) -> #N/A | D105: B0FHP2GN29 | E105: =VLOOKUP(D105,'149库存'!$C$2:$U$199,2,0) -> 149US-SoftCiLiGuan66PCS | F105: =VLOOKUP(E105,'149库存'!$D$2:$U$313,18,0) -> 38.99 | G105: =COUNTIF('149库存'!$C$2:$C$199,D105) -> 1 | H105: =VLOOKUP(D105,'149库存'!$C$2:$U$313,19,0) -> 38.99 | I105: Percent | J105: =CEILING($J$13*B105/H105,1) -> 13 | K105: 3 | L105: =CEILING($L$13*B105/H105,1) -> 18 | M105: 5 | N105: =CEILING($N$13*B105/H105,1) -> 31 | O105: 8
B106: =IFERROR(IF(OR(C106="SS",C106="S"),2,1),1) -> 2 | C106: =VLOOKUP(D106,Sheet4!$K$9:$L$110,2,0) -> S | D106: B0FPC6D218 | E106: =VLOOKUP(D106,'149库存'!$C$2:$U$199,2,0) -> 149US-PinkNiuDanClaw | F106: =VLOOKUP(E106,'149库存'!$D$2:$U$313,18,0) -> 97.99 | G106: =COUNTIF('149库存'!$C$2:$C$199,D106) -> 1 | H106: =VLOOKUP(D106,'149库存'!$C$2:$U$313,19,0) -> 97.99 | I106: Percent | J106: =CEILING($J$13*B106/H106,1) -> 11 | K106: 3 | L106: =CEILING($L$13*B106/H106,1) -> 15 | M106: 5 | N106: =CEILING($N$13*B106/H106,1) -> 25 | O106: 8
B107: =IFERROR(IF(OR(C107="SS",C107="S"),2,1),1) -> 2 | C107: =VLOOKUP(D107,Sheet4!$K$9:$L$110,2,0) -> S | D107: B0F1Y6LC4H | E107: =VLOOKUP(D107,'149库存'!$C$2:$U$199,2,0) -> 149-GuDianniwaA20 | F107: =VLOOKUP(E107,'149库存'!$D$2:$U$313,18,0) -> 49.99 | G107: =COUNTIF('149库存'!$C$2:$C$199,D107) -> 1 | H107: =VLOOKUP(D107,'149库存'!$C$2:$U$313,19,0) -> 49.99 | I107: Percent | J107: =CEILING($J$13*B107/H107,1) -> 21 | K107: 3 | L107: =CEILING($L$13*B107/H107,1) -> 29 | M107: 5 | N107: =CEILING($N$13*B107/H107,1) -> 49 | O107: 8
B108: =IFERROR(IF(OR(C108="SS",C108="S"),2,1),1) -> 1 | C108: =VLOOKUP(D108,Sheet4!$K$9:$L$110,2,0) -> #N/A | D108: B0DD7HPPGX | E108: =VLOOKUP(D108,'149库存'!$C$2:$U$199,2,0) -> 149US-QiQiuChe | F108: =VLOOKUP(E108,'149库存'!$D$2:$U$313,18,0) -> 39.99 | G108: =COUNTIF('149库存'!$C$2:$C$199,D108) -> 1 | H108: =VLOOKUP(D108,'149库存'!$C$2:$U$313,19,0) -> 39.99 | I108: Percent | J108: =CEILING($J$13*B108/H108,1) -> 13 | K108: 3 | L108: =CEILING($L$13*B108/H108,1) -> 18 | M108: 5 | N108: =CEILING($N$13*B108/H108,1) -> 31 | O108: 8
B109: =IFERROR(IF(OR(C109="SS",C109="S"),2,1),1) -> 1 | C109: =VLOOKUP(D109,Sheet4!$K$9:$L$110,2,0) -> A | D109: B0FMK6R2HS | E109: =VLOOKUP(D109,'149库存'!$C$2:$U$199,2,0) -> ZiMuYouXi-0003 | F109: =VLOOKUP(E109,'149库存'!$D$2:$U$313,18,0) -> 39.99 | G109: =COUNTIF('149库存'!$C$2:$C$199,D109) -> 1 | H109: =VLOOKUP(D109,'149库存'!$C$2:$U$313,19,0) -> 39.99 | I109: Percent | J109: =CEILING($J$13*B109/H109,1) -> 13 | K109: 3 | L109: =CEILING($L$13*B109/H109,1) -> 18 | M109: 5 | N109: =CEILING($N$13*B109/H109,1) -> 31 | O109: 8
A114: 2 | B114: 1 | C114: A | D114: B0CT5J8GCW | E114: 149US-8JianTaoBingXiangChiLun | F114: 34.99 | G114: 1 | H114: 34.99 | I114: Percent | J114: 15 | K114: 3 | L114: 21 | M114: 5 | N114: 35 | O114: 8
A115: 1 | B115: 1 | C115: A | D115: B0CT5GKHRM | E115: 149US-XiaoHaoBingXiangChiLun | F115: 35.99 | G115: 1 | H115: 35.99 | I115: Percent | J115: 14 | K115: 3 | L115: 20 | M115: 5 | N115: 34 | O115: 8
B116: 1 | C116: A | D116: B0FHPSR92X | E116: 149US-SoftCiLiGuan26P-007 | F116: 33.99 | G116: 1 | H116: 33.99 | I116: Percent | J116: 15 | K116: 3 | L116: 21 | M116: 5 | N116: 36 | O116: 8
B117: 1 | C117: #N/A | D117: B0FHP2GN29 | E117: 149US-SoftCiLiGuan66PCS | F117: 38.99 | G117: 1 | H117: 38.99 | I117: Percent | J117: 13 | K117: 3 | L117: 18 | M117: 5 | N117: 31 | O117: 8
B118: 2 | C118: S | D118: B0FPC6D218 | E118: 149US-PinkNiuDanClaw | F118: 97.99 | G118: 1 | H118: 97.99 | I118: Percent | J118: 11 | K118: 3 | L118: 15 | M118: 5 | N118: 25 | O118: 8
B119: 2 | C119: S | D119: B0F1Y6LC4H | E119: 149-GuDianniwaA20 | F119: 49.99 | G119: 1 | H119: 49.99 | I119: Percent | J119: 21 | K119: 3 | L119: 29 | M119: 5 | N119: 49 | O119: 8
B120: 1 | C120: #N/A | D120: B0DD7HPPGX | E120: 149US-QiQiuChe | F120: 39.99 | G120: 1 | H120: 39.99 | I120: Percent | J120: 13 | K120: 3 | L120: 18 | M120: 5 | N120: 31 | O120: 8
B121: 1 | C121: A | D121: B0FMK6R2HS | E121: ZiMuYouXi-0003 | F121: 39.99 | G121: 1 | H121: 39.99 | I121: Percent | J121: 13 | K121: 3 | L121: 18 | M121: 5 | N121: 31 | O121: 8
D127: 48
D129: B0F26NHK7M
D130: B0FH2FXX7B
D131: B0FH2J7RM6
D132: B0FH2GQ7CM
D133: B0FH2DS2FR
D134: B0FH2FYH2Y
A136: 2 | B136: =IFERROR(IF(OR(C136="SS",C136="S"),2,1),1) -> 1 | C136: =VLOOKUP(D136,Sheet4!$K$9:$L$110,2,0) -> #N/A | D136: B0F26NHK7M | E136: =VLOOKUP(D136,'48库存'!$C$2:$U$199,2,0) -> 48US-YinYueHuiGangQingJiMu | F136: =VLOOKUP(E136,'48库存'!$D$2:$U$313,18,0) -> 43.99 | G136: =COUNTIF('48库存'!$C$2:$C$199,D136) -> 1 | H136: =VLOOKUP(D136,'48库存'!$C$2:$U$313,19,0) -> 43.99 | I136: Percent | J136: =CEILING($J$13*B136/H136,1) -> 12 | K136: 3 | L136: =CEILING($L$13*B136/H136,1) -> 16 | M136: 5 | N136: =CEILING($N$13*B136/H136,1) -> 28 | O136: 8
A137: 1 | B137: =IFERROR(IF(OR(C137="SS",C137="S"),2,1),1) -> 1 | C137: =VLOOKUP(D137,Sheet4!$K$9:$L$110,2,0) -> #N/A | D137: B0FH2FXX7B | E137: =VLOOKUP(D137,'48库存'!$C$2:$U$199,2,0) -> 48US-JuanZhiShouLian-001 | F137: =VLOOKUP(E137,'48库存'!$D$2:$U$313,18,0) -> 29.99 | G137: =COUNTIF('48库存'!$C$2:$C$199,D137) -> 1 | H137: =VLOOKUP(D137,'48库存'!$C$2:$U$313,19,0) -> 29.99 | I137: Percent | J137: =CEILING($J$13*B137/H137,1) -> 17 | K137: 3 | L137: =CEILING($L$13*B137/H137,1) -> 24 | M137: 5 | N137: =CEILING($N$13*B137/H137,1) -> 41 | O137: 8
B138: =IFERROR(IF(OR(C138="SS",C138="S"),2,1),1) -> 1 | C138: =VLOOKUP(D138,Sheet4!$K$9:$L$110,2,0) -> #N/A | D138: B0FH2J7RM6 | E138: =VLOOKUP(D138,'48库存'!$C$2:$U$199,2,0) -> 48US-JuanZhiShouLian-002 | F138: =VLOOKUP(E138,'48库存'!$D$2:$U$313,18,0) -> 18.99 | G138: =COUNTIF('48库存'!$C$2:$C$199,D138) -> 1 | H138: =VLOOKUP(D138,'48库存'!$C$2:$U$313,19,0) -> 18.99 | I138: Percent | J138: =CEILING($J$13*B138/H138,1) -> 27 | K138: 3 | L138: =CEILING($L$13*B138/H138,1) -> 37 | M138: 5 | N138: =CEILING($N$13*B138/H138,1) -> 64 | O138: 8
B139: =IFERROR(IF(OR(C139="SS",C139="S"),2,1),1) -> 1 | C139: =VLOOKUP(D139,Sheet4!$K$9:$L$110,2,0) -> #N/A | D139: B0FH2GQ7CM | E139: =VLOOKUP(D139,'48库存'!$C$2:$U$199,2,0) -> 48US-MiddleShouLian001 | F139: =VLOOKUP(E139,'48库存'!$D$2:$U$313,18,0) -> 17.99 | G139: =COUNTIF('48库存'!$C$2:$C$199,D139) -> 1 | H139: =VLOOKUP(D139,'48库存'!$C$2:$U$313,19,0) -> 17.99 | I139: Percent | J139: =CEILING($J$13*B139/H139,1) -> 28 | K139: 3 | L139: =CEILING($L$13*B139/H139,1) -> 39 | M139: 5 | N139: =CEILING($N$13*B139/H139,1) -> 67 | O139: 8
B140: =IFERROR(IF(OR(C140="SS",C140="S"),2,1),1) -> 1 | C140: =VLOOKUP(D140,Sheet4!$K$9:$L$110,2,0) -> #N/A | D140: B0FH2DS2FR | E140: =VLOOKUP(D140,'48库存'!$C$2:$U$199,2,0) -> 48US-SmallShouLian001 | F140: =VLOOKUP(E140,'48库存'!$D$2:$U$313,18,0) -> 19.99 | G140: =COUNTIF('48库存'!$C$2:$C$199,D140) -> 1 | H140: =VLOOKUP(D140,'48库存'!$C$2:$U$313,19,0) -> 19.99 | I140: Percent | J140: =CEILING($J$13*B140/H140,1) -> 26 | K140: 3 | L140: =CEILING($L$13*B140/H140,1) -> 36 | M140: 5 | N140: =CEILING($N$13*B140/H140,1) -> 61 | O140: 8
B141: =IFERROR(IF(OR(C141="SS",C141="S"),2,1),1) -> 1 | C141: =VLOOKUP(D141,Sheet4!$K$9:$L$110,2,0) -> #N/A | D141: B0FH2FYH2Y | E141: =VLOOKUP(D141,'48库存'!$C$2:$U$199,2,0) -> 48US-SmallShouLian002 | F141: =VLOOKUP(E141,'48库存'!$D$2:$U$313,18,0) -> 19.99 | G141: =COUNTIF('48库存'!$C$2:$C$199,D141) -> 1 | H141: =VLOOKUP(D141,'48库存'!$C$2:$U$313,19,0) -> 19.99 | I141: Percent | J141: =CEILING($J$13*B141/H141,1) -> 26 | K141: 3 | L141: =CEILING($L$13*B141/H141,1) -> 36 | M141: 5 | N141: =CEILING($N$13*B141/H141,1) -> 61 | O141: 8
A145: 2 | B145: 1 | C145: #N/A | D145: B0F26NHK7M | E145: 48US-YinYueHuiGangQingJiMu | F145: 43.99 | G145: 1 | H145: 43.99 | I145: Percent | J145: 12 | K145: 3 | L145: 16 | M145: 5 | N145: 28 | O145: 8
...

Sheet 50库存
A1: snapshot-date | B1: fnsku | C1: asin | D1: sku | E1: product-name | F1: condition | G1: available | H1: pending-removal-quantity | I1: inv-age-0-to-90-days | J1: inv-age-91-to-180-days | K1: inv-age-181-to-270-days | L1: inv-age-271-to-365-days | M1: inv-age-366-to-455-days | N1: inv-age-456-plus-days | O1: currency | P1: units-shipped-t7 | Q1: units-shipped-t30 | R1: units-shipped-t60 | S1: units-shipped-t90 | T1: alert | U1: your-price | V1: sales-price | W1: lowest-price-new-plus-shipping | X1: lowest-price-used | Y1: recommended-action | Z1: DEPRECATED healthy-inventory-level | AA1: recommended-sales-price | AB1: recommended-sale-duration-days | AC1: recommended-removal-quantity | AD1: estimated-cost-savings-of-recommended-actions | AE1: sell-through | AF1: item-volume | AG1: volume-unit-measurement | AH1: storage-type | AI1: storage-volume | AJ1: marketplace | AK1: product-group | AL1: sales-rank | AM1: days-of-supply | AN1: estimated-excess-quantity | AO1: weeks-of-cover-t30 | AP1: weeks-of-cover-t90 | AQ1: featuredoffer-price | AR1: sales-shipped-last-7-days | AS1: sales-shipped-last-30-days | AT1: sales-shipped-last-60-days | AU1: sales-shipped-last-90-days | AV1: inv-age-0-to-30-days | AW1: inv-age-31-to-60-days | AX1: inv-age-61-to-90-days | AY1: inv-age-181-to-330-days | AZ1: inv-age-331-to-365-days | BA1: estimated-storage-cost-next-month | BB1: inbound-quantity | BC1: inbound-working | BD1: inbound-shipped | BE1: inbound-received | BF1: no-sale-last-6-months | BG1: Total Reserved Quantity | BH1: unfulfillable-quantity | BI1: quantity-to-be-charged-ais-181-210-days | BJ1: estimated-ais-181-210-days | BK1: quantity-to-be-charged-ais-211-240-days | BL1: estimated-ais-211-240-days | BM1: quantity-to-be-charged-ais-241-270-days | BN1: estimated-ais-241-270-days | BO1: quantity-to-be-charged-ais-271-300-days | BP1: estimated-ais-271-300-days | BQ1: quantity-to-be-charged-ais-301-330-days | BR1: estimated-ais-301-330-days | BS1: quantity-to-be-charged-ais-331-365-days | BT1: estimated-ais-331-365-days | BU1: quantity-to-be-charged-ais-366-455-days | BV1: estimated-ais-366-455-days | BW1: quantity-to-be-charged-ais-456-plus-days | BX1: estimated-ais-456-plus-days | BY1: historical-days-of-supply | BZ1: fba-minimum-inventory-level | CA1: fba-inventory-level-health-status | CB1: Recommended ship-in quantity | CC1: Recommended ship-in date | CD1: Last updated date for Historical Days of Supply | CE1: Exempted from Low-Inventory-Level fee? | CF1: Low-Inventory-Level fee applied in current week? | CG1: Short term historical days of supply | CH1: Long term historical days of supply | CI1: Inventory age snapshot date | CJ1: Inventory Supply at FBA | CK1: Reserved FC Transfer | CL1: Reserved FC Processing | CM1: Reserved Customer Order | CN1: Reserved Staging | CO1: Total Days of Supply (including units from open shipments) | CP1: supplier | CQ1: is-seasonal-in-next-3-months | CR1: season-name | CS1: season-start-date | CT1: season-end-date
A2: 46188 | B2: X0042YZRY5 | C2: B0CQXJ37CQ | D2: NewSewingMachinePink 0001 | E2: Portable Sewing Machine for Beginners, Mini Electric Sewing Machine 12 Built-in Stitch Patterns, Light, 2 Speed with Foot Pedal & Sewing Kit, Household máquinas de coser for Kids Ages 8-12 | F2: New | G2: 33 | H2: 0 | I2: 20 | J2: 14 | K2: 0 | L2: 0 | M2: 0 | N2: 0 | O2: USD | P2: 3 | Q2: 10 | R2: 15 | S2: 22 | U2: 79.99 | V2: 49.99 | W2: 49.99 | X2: 0 | Y2: NoExcessInventory | AA2: 0 | AB2: 0 | AC2: 0 | AD2: 0 | AE2: 0.65 | AF2: 0.744874 | AG2: cubic feet | AH2: Standard | AI2: 24.580842 | AJ2: US | AK2: gl_home | AL2: 32209 | AM2: 100 | AN2: 0 | AO2: 14 | AP2: 21 | AQ2: 49.99 | AR2: 149.97 | AS2: 522.4 | AT2: 759.85 | AU2: 1097.28 | AV2: 18 | AW2: 2 | AX2: 0 | AY2: 0 | AZ2: 0 | BA2: 16.21 | BB2: 3 | BC2: 0 | BD2: 0 | BE2: 3 | BG2: 1 | BH2: 0 | BY2: 137.5 | BZ2: 38 | CA2: Low stock | CB2: 24 | CC2: 46193 | CD2: 46188 | CE2: Yes | CF2: No | CG2: 115.7 | CH2: 137.5 | CI2: 46186 | CJ2: 36 | CK2: 0 | CL2: 1 | CM2: 0 | CN2: 0 | CO2: 102 | CP2: unassigned | CQ2: N
A3: 46188 | B3: X004T1CKOB | C3: B0FHH5PQ4H | D3: G503GuYuWaJueJi002 | E3: ROHSCE Push and Go Friction Powered Toy Cars for Toddlers 1-3, Musical Cartoon Excavator Construction Vehicles, Baby Engineering Trucks for 1 2 3 Year Old Boys Girls, Birthday | F3: New | G3: 32 | H3: 0 | I3: 0 | J3: 32 | K3: 0 | L3: 0 | M3: 0 | N3: 0 | O3: USD | P3: 0 | Q3: 1 | R3: 2 | S3: 4 | T3: Low traffic | U3: 22.99 | V3: 15.49 | W3: 15.49 | X3: 0 | Y3: Create Outlet deal | AA3: 10.84 | AB3: 2 | AC3: 0 | AD3: 448.27 | AE3: 0.12 | AF3: 0.054246 | AG3: cubic feet | AH3: Standard | AI3: 1.735872 | AJ3: US | AK3: gl_toy | AL3: 598598 | AM3: 366 | AN3: 32 | AO3: 128 | AP3: 104 | AQ3: 15.49 | AR3: 0 | AS3: 15.49 | AT3: 31.81 | AU3: 63.53 | AV3: 0 | AW3: 0 | AX3: 0 | AY3: 0 | AZ3: 0 | BA3: 1.24 | BB3: 0 | BC3: 0 | BD3: 0 | BE3: 0 | BG3: 0 | BH3: 0 | BY3: 976 | BZ3: 3 | CA3: Excess | CD3: 46188 | CE3: Yes | CF3: No | CG3: 976 | CH3: 758 | CI3: 46186 | CJ3: 32 | CK3: 0 | CL3: 0 | CM3: 0 | CN3: 0 | CO3: 366 | CP3: unassigned | CQ3: N
A4: 46188 | B4: X0042Z3XE5 | C4: B0CQX71441 | D4: NewSewingMachineBlack 0002 | E4: Flying Banana Mini Sewing Machine for Beginners, Portable Electric Small Mending Machine with 12 Stitches, Foot Pedal, LED Light, 2 Speeds, Kids Sewing Kit for Boys & Girls 6-12 Years Old - White | F4: New | G4: 17 | H4: 0 | I4: 20 | J4: 3 | K4: 0 | L4: 0 | M4: 0 | N4: 0 | O4: USD | P4: 2 | Q4: 5 | R4: 14 | S4: 20 | U4: 89.99 | V4: 64.99 | W4: 64.99 | X4: 0 | Y4: NoRestockExcessActionRequired | AA4: 0 | AB4: 0 | AC4: 0 | AD4: 0 | AE4: 1.03 | AF4: 0.734919 | AG4: cubic feet | AH4: Standard | AI4: 12.493623 | AJ4: US | AK4: gl_home | AL4: 32209 | AM4: 185 | AN4: 0 | AO4: 47 | AP4: 38 | AQ4: 64.99 | AR4: 129.98 | AS4: 324.95 | AT4: 900.86 | AU4: 1320.8 | AV4: 19 | AW4: 0 | AX4: 1 | AY4: 0 | AZ4: 0 | BA4: 32.42 | BB4: 42 | BC4: 0 | BD4: 42 | BE4: 0 | BG4: 6 | BH4: 0 | BY4: 117 | BZ4: 14 | CA4: Healthy | CD4: 46188 | CE4: Yes | CF4: No | CG4: 117 | CH4: 75.1 | CI4: 46186 | CJ4: 59 | CK4: 0 | CL4: 0 | CM4: 0 | CN4: 6 | CO4: 189 | CP4: unassigned | CQ4: N
A5: 46188 | B5: X002LTO7VR | C5: B07SRSJZSL | D5: 6JianQiuUs-5001 | E5: ROHSCE Sensory Balls for Baby Sensory Baby Toys 6 to 12 Months for Toddlers 1-3, Bright Color Textured Multi Soft Ball Gift Sets, Montessori Toys for Babies 6-12 Months Infant Toys (6 Pack) | F5: New | G5: 3462 | H5: 0 | I5: 5400 | J5: 0 | K5: 0 | L5: 0 | M5: 0 | N5: 0 | O5: USD | P5: 495 | Q5: 1928 | R5: 3671 | S5: 5598 | U5: 15.99 | V5: 0 | W5: 15.99 | X5: 0 | Y5: NoRestockExcessActionRequired | AA5: 0 | AB5: 0 | AC5: 0 | AD5: 0 | AE5: 1.89 | AF5: 0.08017 | AG5: cubic feet | AH5: Standard | AI5: 277.54854 | AJ5: US | AK5: gl_toy | AL5: 2409 | AM5: 95 | AN5: 0 | AO5: 22 | AP5: 24 | AQ5: 15.99 | AR5: 7910.57 | AS5: 30884.24 | AT5: 58227.21 | AU5: 88067.54 | AV5: 5400 | AW5: 0 | AX5: 0 | AY5: 0 | AZ5: 0 | BA5: 296.7 | BB5: 7301 | BC5: 3744 | BD5: 3216 | BE5: 341 | BG5: 1418 | BH5: 5 | BY5: 59.4 | BZ5: 3707 | CA5: Healthy | CD5: 46188 | CE5: No | CF5: No | CG5: 59.4 | CH5: 41.1 | CI5: 46185 | CJ5: 11575 | CK5: 812 | CL5: 156 | CM5: 13 | CN5: 1249 | CO5: 170 | CQ5: N
A6: 46188 | B6: X0046NX1NV | C6: B0C6T332PH | D6: 50-huangsepenshuihuojian-2PH | E6: ROHSCE Water Rocket Sprinkler for Kids, Outdoor Sprinkler Rocket Launcher Toy for Backyard, Summer Water Toys for Kids Ages 3-12, Fun Water Powered Rocket Toy (Yellow-1) | G6: 0 | H6: -1 | O6: USD | U6: 0 | V6: 0 | W6: 0 | X6: 0 | Y6: NoRestockExcessActionRequired | AB6: 0 | AC6: 0 | AE6: -1 | AH6: Standard | AJ6: US | AK6: gl_toy | AM6: 0 | AN6: 0 | AQ6: 26.99 | AY6: 0 | BB6: 0 | BC6: 0 | BD6: 0 | BE6: 0 | BG6: 0 | BH6: 0 | CJ6: 0 | CK6: 0 | CL6: 0 | CM6: 0 | CN6: 0 | CO6: 0 | CP6: unassigned | CQ6: N
A7: 46188 | B7: X005554ZWP | C7: B0GTL46L4V | D7: 50US-trainmangluban | E7: ROHSCE Baby Activity Cube Toys 12-18 Months, Montessori Musical Train with Lights & Sounds, Shape Sorter Busy Cube, Multifunctional Learning Toys for Toddlers 1-3 Boys Girls | F7: New | G7: 0 | H7: -1 | O7: USD | U7: 65.99 | V7: 0 | W7: 0 | X7: 0 | Y7: Edit listing | AB7: 0 | AC7: 0 | AE7: -1 | AH7: Standard | AJ7: US | AK7: gl_toy | AN7: 0 | AY7: 0 | BB7: 15 | BC7: 15 | BD7: 0 | BE7: 0 | BG7: 0 | BH7: 0 | CJ7: 15 | CK7: 0 | CL7: 0 | CM7: 0 | CN7: 0 | CP7: unassigned | CQ7: N
A8: 46188 | B8: X004ML2I7R | C8: B0F192Z9C9 | D8: 50US-YingErYongQuan-003 | E8: Baby Pool Float with Removable Canopy Baby Float,Friendly Material Swim Trainer for Toddler Boys Girls,Babies Toy | G8: 0 | H8: -1 | O8: USD | U8: 0 | V8: 0 | W8: 0 | X8: 0 | Y8: NoRestockExcessActionRequired | AB8: 0 | AC8: 0 | AE8: -1 | AH8: Other | AJ8: US | AK8: gl_outdoors | AN8: 0 | AY8: 0 | BB8: 0 | BG8: 0 | BH8: 0 | CJ8: 0 | CK8: 0 | CL8: 0 | CM8: 0 | CN8: 0 | CP8: unassigned | CQ8: N
A9: 46188 | B9: X0051COV53 | C9: B0GSPQCM17 | D9: 50US-BallsBlocks26PCS-01 | E9: ROHSCE 26PCS Textured Sensory Balls & Soft Silicone Building Blocks, Montessori Stacking Toy for Babies 6-12 Months, BPA-Free Infant Sensory Toys for Grasping & Early Learning | G9: 0 | H9: -1 | O9: USD | U9: 0 | V9: 0 | W9: 0 | X9: 0 | Y9: NoRestockExcessActionRequired | AB9: 0 | AC9: 0 | AE9: -1 | AH9: Other | AJ9: US | AK9: gl_toy | AN9: 0 | AY9: 0 | BB9: 0 | BG9: 0 | BH9: 0 | CJ9: 0 | CK9: 0 | CL9: 0 | CM9: 0 | CN9: 0 | CP9: unassigned | CQ9: N
A10: 46188 | B10: X002UKDWNB | C10: B0915H7J7Q | D10: FBA-YuLian- parent-0001 | E10: ROHSCE No Hooks Waffle Weave Mildew Resistant Shower Curtain with Snap in Removable Liner for Bathroom-Hotel Grade,Mesh Top Window, Machine Washable-72x72inch | G10: 0 | H10: -1 | O10: USD | U10: 0 | V10: 0 | W10: 0 | X10: 0 | Y10: NoRestockExcessActionRequired | AB10: 0 | AC10: 0 | AE10: -1 | AJ10: US | AK10: gl_home | AN10: 0 | AY10: 0 | BB10: 0 | BG10: 0 | BH10: 0 | CJ10: 0 | CK10: 0 | CL10: 0 | CM10: 0 | CN10: 0 | CP10: unassigned | CQ10: N
A11: 46188 | B11: X004MN5Z89 | C11: B0DTP55X8K | D11: 50US-MaiGanYaZi-004 | E11: ROHSCE Baby Bath Toys 6-12 Months, 9 Pcs Wheat Straw Sensory Balls & Ducks, No Hole Floating Toddler Bath Toys, for Boys & Girls 1-3, Textured Squeeze Stress Relief Montessori Set | F11: New | G11: 9 | H11: 0 | I11: 0 | J11: 0 | K11: 0 | L11: 0 | M11: 9 | N11: 0 | O11: USD | P11: 0 | Q11: 0 | R11: 0 | S11: 0 | T11: Low traffic | U11: 26.99 | V11: 0 | W11: 21.59 | X11: 0 | Y11: Lower price | AA11: 0 | AB11: 0 | AC11: 0 | AD11: 323.05 | AE11: 0 | AF11: 0.112375 | AG11: cubic feet | AH11: Standard | AI11: 1.011375 | AJ11: US | AK11: gl_toy | AL11: 238733 | AM11: 366 | AN11: 9 | AQ11: 21.59 | AR11: 0 | AS11: 0 | AT11: 0 | AU11: 0 | AV11: 0 | AW11: 0 | AX11: 0 | AY11: 0 | AZ11: 0 | BA11: 7.64 | BB11: 0 | BC11: 0 | BD11: 0 | BE11: 0 | BG11: 0 | BH11: 0 | BI11: 0 | BJ11: 0 | BK11: 0 | BL11: 0 | BM11: 0 | BN11: 0 | BO11: 0 | BP11: 0 | BQ11: 0 | BR11: 0 | BS11: 0 | BT11: 0 | BU11: 9 | BV11: 6.99 | BW11: 0 | BX11: 0 | BZ11: 1 | CA11: Excess | CI11: 46185 | CJ11: 9 | CK11: 0 | CL11: 0 | CM11: 0 | CN11: 0 | CO11: 366 | CP11: unassigned | CQ11: N
A12: 46188 | B12: X003HYQYM5 | C12: B0BLHYTV6G | D12: SoftBuildingBlock-114 | E12: Soft Building Block Sets for Kids Aged 36 Months to 6 Years Old Top STEM Building Blocks for Preschool Large Construction Block Toys for Toddler to Improve Imagination Creativity Hands-on Ability | G12: 0 | H12: -1 | O12: USD | U12: 0 | V12: 0 | W12: 0 | X12: 0 | Y12: NoRestockExcessActionRequired | AB12: 0 | AC12: 0 | AE12: -1 | AJ12: US | AK12: gl_toy | AN12: 0 | AY12: 0 | BB12: 0 | BG12: 0 | BH12: 0 | CJ12: 0 | CK12: 0 | CL12: 0 | CM12: 0 | CN12: 0 | CP12: unassigned | CQ12: N
A13: 46188 | B13: X0050OVSSP | C13: B0CGCM7TXL | D13: 50US-PangXieBubbleMachine | E13: Crab Bubble Bath Maker for The Bathtub,Blows Bubbles and Plays 12 Children’s Songs,Sing-Along Bath Bubble Machine Baby, Toddler Kids Toys Makes Great Gifts for 3 Years Girl Boy | G13: 0 | H13: -1 | O13: USD | U13: 0 | V13: 0 | W13: 0 | X13: 0 | Y13: NoRestockExcessActionRequired | AB13: 0 | AC13: 0 | AE13: -1 | AH13: Standard | AJ13: US | AK13: gl_toy | AM13: 0 | AN13: 0 | AQ13: 13.8 | AY13: 0 | BB13: 0 | BG13: 0 | BH13: 0 | CJ13: 0 | CK13: 0 | CL13: 0 | CM13: 0 | CN13: 0 | CO13: 0 | CP13: unassigned | CQ13: N
A14: 46188 | B14: X003RGLZ45 | C14: B0BYVGS56Z | D14: YaoKongQi Teether11 | E14: ROHSCE Silicone Baby Teether Toys, Cell Phone Teething Toys for Babies 6-12 Months Soft Molar Teether Infant Baby Chew Toys Sensory Remote Teether BPA-Free Gifts, Black+Green | G14: 0 | H14: -1 | O14: USD | U14: 0 | V14: 0 | W14: 0 | X14: 0 | Y14: NoRestockExcessActionRequired | AB14: 0 | AC14: 0 | AE14: -1 | AH14: Standard | AJ14: US | AK14: gl_baby_product | AM14: 0 | AN14: 0 | AQ14: 5.99 | AY14: 0 | BB14: 0 | BC14: 0 | BD14: 0 | BE14: 0 | BG14: 0 | BH14: 0 | CJ14: 0 | CK14: 0 | CL14: 0 | CM14: 0 | CN14: 0 | CO14: 0 | CP14: unassigned | CQ14: N
A15: 46188 | B15: X004YXYQ5F | C15: B0CT5SFK7T | D15: 50US-LiHeRuanCiBall6 | E15: ROHSCE Baby Sensory Balls, 6PCS Soft Textured Spiky Bath Toys 6M+ | F15: New | G15: 23 | H15: 0 | I15: 0 | J15: 23 | K15: 0 | L15: 0 | M15: 0 | N15: 0 | O15: USD | P15: 0 | Q15: 0 | R15: 0 | S15: 1 | T15: Low conversion | U15: 40.99 | V15: 0 | W15: 31.99 | X15: 0 | Y15: Lower price | AB15: 0 | AC15: 0 | AE15: 0.32 | AF15: 0.266389 | AG15: cubic feet | AH15: Standard | AI15: 6.126947 | AJ15: US | AK15: gl_toy | AL15: 2409 | AM15: 87 | AN15: 0 | AP15: 299 | AQ15: 31.99 | AR15: 0 | AS15: 0 | AT15: 0 | AU15: 40.99 | AV15: 0 | AW15: 0 | AX15: 0 | AY15: 0 | AZ15: 0 | BB15: 0 | BC15: 0 | BD15: 0 | BE15: 0 | BG15: 0 | BH15: 0 | BZ15: 1 | CA15: Healthy | CH15: 2080 | CI15: 46186 | CJ15: 23 | CK15: 0 | CL15: 0 | CM15: 0 | CN15: 0 | CO15: 87 | CP15: unassigned | CQ15: N
A16: 46188 | B16: X0046NX0JB | C16: B0BLHZLLK6 | D16: 50-ruantijimu-LK6 | E16: ROHSCE Soft Building Blocks for Toddler, Blocks for Kids 6 Months and up, Large Creative Stacking Blocks 20 PCS STEM Toddler Toys Gifts, Educational Baby Blocks Colorful Soft Block Sets | G16: 0 | H16: -1 | O16: USD | U16: 0 | V16: 0 | W16: 0 | X16: 0 | Y16: NoRestockExcessActionRequired | AB16: 0 | AC16: 0 | AE16: -1 | AJ16: US | AK16: gl_toy | AL16: 26497 | AM16: 0 | AN16: 0 | AQ16: 19.99 | AY16: 0 | BB16: 0 | BG16: 0 | BH16: 0 | CJ16: 0 | CK16: 0 | CL16: 0 | CM16: 0 | CN16: 0 | CO16: 0 | CQ16: N
A17: 46188 | B17: X002LYPVNF | C17: B08FDP4WNK | D17: GameGuaTanZsUs-5001 | E17: Flying Banana Gamer Play & Win Purple Gamepad Tapestry, Cool Colorful Gaming Wall Hanging Tapestry For Men,Bedroom Aesthetic,College Dorm Room Decor(78.7 x 59in) | G17: 0 | H17: -1 | O17: USD | U17: 0 | V17: 0 | W17: 0 | X17: 0 | Y17: NoRestockExcessActionRequired | AB17: 0 | AC17: 0 | AE17: -1 | AH17: Standard | AJ17: US | AK17: gl_home | AM17: 0 | AN17: 0 | AQ17: 18.85 | AY17: 0 | BB17: 0 | BC17: 0 | BD17: 0 | BE17: 0 | BG17: 0 | BH17: 0 | CJ17: 0 | CK17: 0 | CL17: 0 | CM17: 0 | CN17: 0 | CO17: 0 | CP17: unassigned | CQ17: N
A18: 46188 | B18: X0051RPOUT | C18: B0GJXPV9Q1 | D18: 50US-TankYaoKongQi-002 | E18: ROHSCE RC Tank Accessories Controller Set, Replacement 2.4GHz Remote Transmitter and Gesture Sensing Watch Control for Compatible Battle Vehicle Toy Spare Parts | G18: 0 | H18: 0 | I18: 19 | J18: 0 | K18: 0 | L18: 0 | M18: 0 | N18: 0 | O18: USD | U18: 0 | V18: 0 | W18: 0 | X18: 0 | Y18: NoRestockExcessActionRequired | AB18: 0 | AC18: 0 | AE18: 0 | AF18: 0.038098 | AG18: cubic feet | AH18: Standard | AI18: 0 | AJ18: US | AK18: gl_toy | AM18: 0 | AN18: 0 | AQ18: 22.99 | AV18: 0 | AW18: 19 | AX18: 0 | AY18: 0 | AZ18: 0 | BB18: 0 | BC18: 0 | BD18: 0 | BE18: 0 | BG18: 19 | BH18: 0 | CI18: 46186 | CJ18: 0 | CK18: 0 | CL18: 0 | CM18: 0 | CN18: 19 | CO18: 85 | CP18: unassigned | CQ18: N
A19: 46188 | B19: X004ETS49X | C19: B0CRDL2HD6 | D19: 50-PinkGuiDaoClaw-HD6 | E19: ROHSCE Claw Machine for Kids, Mini Vending Machine Toys for Girls, Arcade Game Toy for Ages 8-13, Electronic Claw Game Machine for Party with Lights Sound, Birthday Gifts for Ages 4+ | G19: 0 | H19: -1 | O19: USD | P19: 0 | Q19: 0 | R19: 0 | S19: 0 | U19: 0 | V19: 0 | W19: 0 | X19: 0 | Y19: NoRestockExcessActionRequired | AB19: 0 | AC19: 0 | AE19: -1 | AH19: Oversize | AJ19: US | AK19: gl_toy | AL19: 192027 | AN19: 0 | AQ19: 79.99 | AR19: 0 | AS19: 0 | AT19: 0 | AU19: 0 | AY19: 0 | BB19: 0 | BC19: 0 | BD19: 0 | BE19: 0 | BG19: 0 | BH19: 0 | CJ19: 0 | CK19: 0 | CL19: 0 | CM19: 0 | CN19: 0 | CP19: unassigned | CQ19: N
A20: 46188 | B20: X004QU0Y93 | C20: B0DTTVCDCG | D20: 50US-GenSuiYa-001 | E20: ROHSCE Duck Tummy Time Toys for Baby, Musical Toys for Toddlers, Baby Crawling Baby Toys for Boys Girls, Early Learning Education, Christmas Birthday Gifts for Babies 18 Months | G20: 0 | H20: -1 | O20: USD | P20: 0 | Q20: 0 | R20: 0 | S20: 0 | U20: 0 | V20: 0 | W20: 0 | X20: 0 | Y20: NoRestockExcessActionRequired | AB20: 0 | AC20: 0 | AE20: -1 | AH20: Standard | AJ20: US | AK20: gl_toy | AM20: 0 | AN20: 0 | AQ20: 22.49 | AR20: 0 | AS20: 0 | AT20: 0 | AU20: 0 | AY20: 0 | BB20: 0 | BC20: 0 | BD20: 0 | BE20: 0 | BG20: 0 | BH20: 0 | BZ20: 1 | CA20: Out of stock | CJ20: 0 | CK20: 0 | CL20: 0 | CM20: 0 | CN20: 0 | CO20: 0 | CP20: unassigned | CQ20: N
A21: 46188 | B21: X0051RXUQ9 | C21: B0GJYDMJ8D | D21: 50US-TankTiHuanJiShen-03 | E21: ROHSCE Green RC Tank Accessories Replacement Body Shell, Plastic Hull Cover for Remote Control Tank Model, Repair Spare Part Upgrade Kit for RC Hobby Tracked Vehicle | F21: New | G21: 20 | H21: 0 | I21: 20 | J21: 0 | K21: 0 | L21: 0 | M21: 0 | N21: 0 | O21: USD | T21: Low conversion | U21: 41.99 | V21: 0 | W21: 29.99 | X21: 0 | Y21: Lower price | AA21: 0 | AB21: 0 | AC21: 0 | AD21: 0 | AE21: 0 | AF21: 0.091635 | AG21: cubic feet | AH21: Standard | AI21: 1.8327 | AJ21: US | AK21: gl_toy | AL21: 206385 | AM21: 28 | AN21: 0 | AQ21: 29.99 | AV21: 0 | AW21: 20 | AX21: 0 | AY21: 0 | AZ21: 0 | BA21: 1.31 | BB21: 0 | BC21: 0 | BD21: 0 | BE21: 0 | BG21: 0 | BH21: 0 | CI21: 46186 | CJ21: 20 | CK21: 0 | CL21: 0 | CM21: 0 | CN21: 0 | CO21: 28 | CP21: unassigned | CQ21: N
A22: 46188 | B22: B08F3GFQYJ | C22: B08F3GFQYJ | D22: JIaJieMao12taozhuang-0012 | E22: Yayalovehomee Magnetic Eyelashes and Magnetic Eyeliner Kit, 12 Pairs of Different Styles Reusable Magnetic Eyelashes with 2 Special Magnetic Eyeliners and Tweezers, Easy to Apply with Natural Look | G22: 0 | H22: -1 | O22: USD | U22: 0 | V22: 0 | W22: 0 | X22: 0 | Y22: NoRestockExcessActionRequired | AB22: 0 | AC22: 0 | AE22: -1 | AJ22: US | AK22: gl_beauty | AN22: 0 | AY22: 0 | BB22: 0 | BG22: 0 | BH22: 0 | CJ22: 0 | CK22: 0 | CL22: 0 | CM22: 0 | CN22: 0 | CP22: unassigned | CQ22: N
A23: 46188 | B23: X003F87X73 | C23: B0BHF5ZBS6 | D23: TuMaMaBalls | E23: ROHSCE Montessori Sensory Balls for Babies 6 to 12 Months, Soft Textured Multi Sensory Toys, BPA Free - Gift Set Includes: Toddler Ball, Bath Toys | G23: 0 | H23: -1 | O23: USD | U23: 0 | V23: 0 | W23: 0 | X23: 0 | Y23: NoRestockExcessActionRequired | AB23: 0 | AC23: 0 | AE23: -1 | AH23: Standard | AJ23: US | AK23: gl_toy | AM23: 0 | AN23: 0 | AQ23: 15.99 | AY23: 0 | BB23: 0 | BC23: 0 | BD23: 0 | BE23: 0 | BG23: 0 | BH23: 0 | CJ23: 0 | CK23: 0 | CL23: 0 | CM23: 0 | CN23: 0 | CO23: 0 | CP23: unassigned | CQ23: N
A24: 46188 | B24: B09GVMZLSF | C24: B09GVMZLSF | D24: JIMU9JIAN | E24: Flying Banana Building Blocks Baby Toys for 3 Months and up, Soft Squeeze Sensory Colorful Teething Chewing Educational Stacking Blocks with 3D Embossed Patterns | G24: 0 | H24: -1 | O24: USD | U24: 0 | V24: 0 | W24: 0 | X24: 0 | Y24: NoRestockExcessActionRequired | AB24: 0 | AC24: 0 | AE24: -1 | AH24: Standard | AJ24: US | AK24: gl_toy | AM24: 0 | AN24: 0 | AQ24: 9.99 | AY24: 0 | BB24: 0 | BC24: 0 | BD24: 0 | BE24: 0 | BG24: 0 | BH24: 0 | CJ24: 0 | CK24: 0 | CL24: 0 | CM24: 0 | CN24: 0 | CO24: 0 | CP24: unassigned | CQ24: N
A25: 46188 | B25: X003EOK7TJ | C25: B0BGBWZY8G | D25: BubbleGun-Blue-2 | E25: Automatic Bubble Machine for Kids, Kids Bubble Makers Bubble Machine Gun with Light, Automatic Gatling Bubble Gun for Adult & Kids, Rechargeable Bubble Machine for Party, Large Bubble Blower | G25: 0 | H25: -1 | O25: USD | U25: 0 | V25: 0 | W25: 0 | X25: 0 | Y25: NoRestockExcessActionRequired | AB25: 0 | AC25: 0 | AE25: -1 | AH25: Standard | AJ25: US | AK25: gl_toy | AM25: 0 | AN25: 0 | AQ25: 29.99 | AY25: 0 | BB25: 0 | BC25: 0 | BD25: 0 | BE25: 0 | BG25: 0 | BH25: 0 | CJ25: 0 | CK25: 0 | CL25: 0 | CM25: 0 | CN25: 0 | CO25: 0 | CP25: unassigned | CQ25: N
A26: 46188 | B26: X00554YAPD | C26: B0GXNYXWXP | D26: 50US-yinyueguPINK-003 | E26: ROHSCE Infant Musical Drum Toy – Colorful Interactive Drum Playset with Lights and Sounds, Perfect for Enhancing Sensory Awareness, Motor Skills, and Early Cognitive Development | F26: New | G26: 0 | H26: -1 | O26: USD | U26: 55.99 | V26: 0 | W26: 0 | X26: 0 | Y26: Edit listing | AB26: 0 | AC26: 0 | AE26: -1 | AH26: Standard | AJ26: US | AK26: gl_toy | AN26: 0 | AY26: 0 | BB26: 20 | BC26: 20 | BD26: 0 | BE26: 0 | BG26: 0 | BH26: 0 | CJ26: 20 | CK26: 0 | CL26: 0 | CM26: 0 | CN26: 0 | CP26: unassigned | CQ26: N
A27: 46188 | B27: X004YIAEBZ | C27: B0DSZRWS75 | D27: 50US-TankRuanDanLanTou | E27: ROHSCE Blue Foam Dart Launcher Attachment for RC Toy Vehicle, Soft Foam Dart Shooter Replacement Module for Remote Control Stunt Car Toy, Kids RC Toy Accessory Spare Part | F27: New | G27: 20 | H27: 0 | I27: 0 | J27: 20 | K27: 0 | L27: 0 | M27: 0 | N27: 0 | O27: USD | T27: Low conversion | U27: 28.49 | V27: 0 | W27: 22.79 | X27: 0 | Y27: Lower price | AA27: 0 | AB27: 0 | AC27: 0 | AD27: 67.83 | AE27: 0 | AF27: 0.15428 | AG27: cubic feet | AH27: Standard | AI27: 3.0856 | AJ27: US | AK27: gl_toy | AL27: 206385 | AN27: 6 | AQ27: 22.79 | AV27: 0 | AW27: 0 | AX27: 0 | AY27: 0 | AZ27: 0 | BA27: 2.21 | BB27: 0 | BC27: 0 | BD27: 0 | BE27: 0 | BG27: 0 | BH27: 0 | CA27: Excess | CI27: 46186 | CJ27: 20 | CK27: 0 | CL27: 0 | CM27: 0 | CN27: 0 | CP27: unassigned | CQ27: N
A28: 46188 | B28: X004SQ5VN9 | C28: B0FGC9SZ4D | D28: HuocheMaoRongChe002 | E28: ROHSCE Plush Remote Control Train for Toddlers, Soft RC Car with 2.4GHz Two-Button Remote, Washable Soft Cover, for Boys & Girls Ages 18 Months+ | G28: 0 | H28: -1 | O28: USD | P28: 0 | Q28: 0 | R28: 0 | S28: 0 | U28: 0 | V28: 0 | W28: 0 | X28: 0 | Y28: NoRestockExcessActionRequired | AB28: 0 | AC28: 0 | AE28: -1 | AH28: Standard | AJ28: US | AK28: gl_toy | AM28: 0 | AN28: 0 | AQ28: 35.99 | AR28: 0 | AS28: 0 | AT28: 0 | AU28: 0 | AY28: 0 | BB28: 0 | BC28: 0 | BD28: 0 | BE28: 0 | BG28: 0 | BH28: 1 | BZ28: 1 | CA28: Out of stock | CJ28: 0 | CK28: 0 | CL28: 0 | CM28: 0 | CN28: 0 | CO28: 0 | CP28: unassigned | CQ28: N
A29: 46188 | B29: X003DY3UUN | C29: B0BDFBXDHP | D29: SZQchuxuGuan-03 | E29: ROHSCE Sensory Balls Montessori Toys for Babies 6-12 Months, Baby Sensory Toys Turtle Toys Bright Color Textured Multi Soft Balls, BPA Free Ball for Toddlers 1-3 Teething Gifts | G29: 49 | H29: -1 | O29: USD | P29: 0 | Q29: 10 | R29: 19 | S29: 43 | W29: -1 | X29: -1 | Y29: CreateShippingPlan | AA29: 0 | AB29: 0 | AC29: 0 | AD29: 0 | AE29: -1 | AH29: Standard | AJ29: US | AK29: gl_sports | AL29: 9437 | AM29: 65 | AN29: 0 | AO29: 19 | AP29: 14 | AQ29: 29.99 | AR29: 0 | AS29: 249.9 | AT29: 462.42 | AU29: 1046.18 | AY29: 0 | BA29: 6.17 | BB29: 0 | BC29: 0 | BD29: 0 | BE29: 0 | BG29: 0 | BH29: 1 | BY29: 126.4 | BZ29: 48 | CA29: Healthy | CB29: 54 | CC29: 46195 | CD29: 46188 | CE29: Yes | CF29: No | CG29: 126.4 | CH29: 77.7 | CJ29: 50 | CK29: 1 | CL29: 0 | CM29: 0 | CN29: 0 | CO29: 65 | CP29: unassigned | CQ29: N
A30: 46188 | B30: X004957WDB | C30: B0CJ5B2DXY | D30: 50busyboard-0001 | E30: ROHSCE Montessori Busy Board Sensory Toys for Toddlers 1-3, Activity Music & LED Light Up Montessori Toys for 2+ Year Old, Travel Toys for 2 Year Old Boys & Girls, 2025 | F30: New | G30: 39 | H30: 0 | I30: 11 | J30: 40 | K30: 0 | L30: 0 | M30: 0 | N30: 0 | O30: USD | P30: 4 | Q30: 9 | R30: 22 | S30: 32 | U30: 39.99 | V30: 0 | W30: 39.99 | X30: 0 | Y30: NoExcessInventory | AA30: 0 | AB30: 0 | AC30: 0 | AD30: 0 | AE30: 0.49 | AF30: 0.300229 | AG30: cubic feet | AH30: Standard | AI30: 11.708931 | AJ30: US | AK30: gl_toy | AL30: 203254 | AM30: 64 | AN30: 0 | AO30: 17 | AP30: 15 | AQ30: 29.99 | AR30: 131.06 | AS30: 299.51 | AT30: 729.18 | AU30: 1122.78 | AV30: 11 | AW30: 0 | AX30: 0 | AY30: 0 | AZ30: 0 | BA30: 9.49 | BB30: 0 | BC30: 0 | BD30: 0 | BE30: 0 | BG30: 8 | BH30: 4 | BY30: 159.9 | BZ30: 39 | CA30: Healthy | CB30: 13 | CC30: 46194 | CD30: 46188 | CE30: Yes | CF30: No | CG30: 144.8 | CH30: 159.9 | CI30: 46186 | CJ30: 43 | CK30: 4 | CL30: 0 | CM30: 0 | CN30: 8 | CO30: 77 | CP30: unassigned | CQ30: N
A31: 46188 | B31: X004JMVLFJ | C31: B0GG4GS8FZ | D31: 50-WuziMangLuBan | E31: ROHSCE Baby Busy Board for 1 Year Old, Musical Montessori House Busy Board with Light & Music, Toddler Activity Toy for Boys Girls 12-18 Months, 1 Year Old Birthday Gift | F31: New | G31: 5 | H31: -1 | O31: USD | P31: 1 | Q31: 10 | R31: 16 | S31: 30 | U31: 27.99 | V31: 0 | W31: 0 | X31: 0 | Y31: CreateShippingPlan | AB31: 0 | AC31: 0 | AE31: -1 | AH31: Standard | AJ31: US | AK31: gl_toy | AL31: 203254 | AM31: 18 | AN31: 0 | AO31: 2 | AP31: 2 | AQ31: 27.99 | AR31: 27.99 | AS31: 279.9 | AT31: 447.84 | AU31: 831.7 | AY31: 0 | BB31: 0 | BC31: 0 | BD31: 0 | BE31: 0 | BG31: 1 | BH31: 0 | BY31: 20.7 | BZ31: 24 | CA31: Low stock | CB31: 42 | CC31: 46187 | CD31: 46188 | CE31: Yes | CF31: No | CG31: 12.6 | CH31: 20.7 | CJ31: 9 | CK31: 4 | CL31: 0 | CM31: 1 | CN31: 0 | CO31: 20 | CP31: unassigned | CQ31: N
A32: 46188 | B32: X003EOGQWL | C32: B0BGBXHL7T | D32: BubbleGun-Blue-1 | E32: ROHSCE Automatic Bubble Machine for Kids, Kids Bubble Makers Bubble Machine Gun with Light, Automatic Gatling Bubble Gun for Kids, Rechargeable Bubble Machine Bubble Blower for Party, Blue | G32: 0 | H32: -1 | O32: USD | U32: 0 | V32: 0 | W32: 0 | X32: 0 | Y32: NoRestockExcessActionRequired | AB32: 0 | AC32: 0 | AE32: -1 | AH32: Standard | AJ32: US | AK32: gl_toy | AN32: 0 | AQ32: 63.99 | AY32: 0 | BB32: 0 | BC32: 0 | BD32: 0 | BE32: 0 | BG32: 0 | BH32: 0 | CJ32: 0 | CK32: 0 | CL32: 0 | CM32: 0 | CN32: 0 | CP32: unassigned | CQ32: N
A33: 46188 | B33: X003RGBQ1R | C33: B0BYVFS9H1 | D33: YaoKongQi Teether06 | E33: ROHSCE Silicone Baby Teether Toys, Mobile Phone Shape Teething Toys for Babies 6-12 Months Soft Molar Teether Infant Baby Chew Toys Sensory Phone Teether for Baby BPA-Free Gifts, Yellow | G33: 0 | H33: -1 | O33: USD | U33: 0 | V33: 0 | W33: 0 | X33: 0 | Y33: NoRestockExcessActionRequired | AB33: 0 | AC33: 0 | AE33: -1 | AH33: Standard | AJ33: US | AK33: gl_baby_product | AM33: 0 | AN33: 0 | AQ33: 3.49 | AY33: 0 | BB33: 0 | BC33: 0 | BD33: 0 | BE33: 0 | BG33: 0 | BH33: 0 | CJ33: 0 | CK33: 0 | CL33: 0 | CM33: 0 | CN33: 0 | CO33: 0 | CP33: unassigned | CQ33: N
A34: 46188 | B34: X003E7KZCZ | C34: B0BFDXJ925 | D34: shouchifengrenji | E34: Mini Handheld Electric Sewing Machine for Kids & Sewing Beginners, Portable Sewing Machine with Sewing Kit for Household Sewing | G34: 0 | H34: -1 | O34: USD | U34: 0 | V34: 0 | W34: 0 | X34: 0 | Y34: NoRestockExcessActionRequired | AB34: 0 | AC34: 0 | AE34: -1 | AJ34: US | AK34: gl_home | AN34: 0 | AY34: 0 | BB34: 0 | BG34: 0 | BH34: 0 | CJ34: 0 | CK34: 0 | CL34: 0 | CM34: 0 | CN34: 0 | CP34: unassigned | CQ34: N
A35: 46188 | B35: X00335CKC1 | C35: B09MK2ZTK1 | D35: 50-FB-bluepuzzle-001 | E35: Flying Banana Wooden Face Changing Cube Matching Game Puzzle, Expressions Matching Block Puzzles Building Cubes Game Educational Social Toys for Kids Ages 3 Years and Up | G35: 0 | H35: -1 | O35: USD | U35: 0 | V35: 0 | W35: 0 | X35: 0 | Y35: NoRestockExcessActionRequired | AB35: 0 | AC35: 0 | AE35: -1 | AJ35: US | AK35: gl_toy | AN35: 0 | AY35: 0 | BB35: 0 | BG35: 0 | BH35: 0 | CJ35: 0 | CK35: 0 | CL35: 0 | CM35: 0 | CN35: 0 | CP35: unassigned | CQ35: N
A36: 46188 | B36: X003WOREFL | C36: B0BLKBV7T2 | D36: YaokongYueyeche-006 | E36: ROHSCE RC Tank that Shoots Gesture Sensing RC Tank, 2.4GHz Battle Soft Bullets Hand Control Car Drift Remote Control Trucks for Boys & Girls 8-12, Remote Control Tank with Light Music | G36: 0 | H36: -1 | O36: USD | U36: 0 | V36: 0 | W36: 0 | X36: 0 | Y36: NoRestockExcessActionRequired | AB36: 0 | AC36: 0 | AE36: -1 | AJ36: US | AK36: gl_toy | AL36: 206385 | AM36: 0 | AN36: 0 | AQ36: 69.99 | AY36: 0 | BB36: 0 | BG36: 0 | BH36: 0 | CB36: 56 | CC36: 46187 | CJ36: 0 | CK36: 0 | CL36: 0 | CM36: 0 | CN36: 0 | CO36: 0 | CP36: unassigned | CQ36: N
A37: 46188 | B37: X004MPM67P | C37: B0C7G9L4GD | D37: 50US-MaoCiBabyBall002 | E37: ROHSCE Baby Sensory Balls 6–12 Months, Soft Spiky Textured Teething Toys for Infants Montessori Grasping & Learning Balls for Tactile Development & Play | F37: New | G37: 12 | H37: 0 | I37: 1 | J37: 11 | K37: 0 | L37: 0 | M37: 0 | N37: 0 | O37: USD | P37: 2 | Q37: 6 | R37: 9 | S37: 13 | T37: Low traffic | U37: 18.99 | V37: 15.99 | W37: 15.99 | X37: 0 | Y37: Create Outlet deal | AA37: 11.19 | AB37: 2 | AC37: 0 | AD37: 238.72 | AE37: 0.74 | AF37: 0.0649 | AG37: cubic feet | AH37: Standard | AI37: 0.7788 | AJ37: US | AK37: gl_sports | AL37: 329212 | AM37: 114 | AN37: 12 | AO37: 14 | AP37: 22 | AQ37: 15.99 | AR37: 31.98 | AS37: 95.94 | AT37: 149.91 | AU37: 225.87 | AV37: 0 | AW37: 0 | AX37: 1 | AY37: 0 | AZ37: 0 | BA37: 0.56 | BB37: 10 | BC37: 10 | BD37: 0 | BE37: 0 | BG37: 0 | BH37: 0 | BY37: 120.9 | BZ37: 7 | CA37: Excess | CD37: 46188 | CE37: Yes | CF37: No | CG37: 63.3 | CH37: 120.9 | CI37: 46186 | CJ37: 22 | CK37: 0 | CL37: 0 | CM37: 0 | CN37: 0 | CO37: 192 | CP37: unassigned | CQ37: N
A38: 46188 | B38: X004SHE0FN | C38: B08FM4LMWR | D38: 50US-NEWp-Sewing Machine White020 | E38: Mini Sewing Machine for Beginners-Maquina de Coser, Easy Automatic Sewing Machine with Extension Table, Household Electric Portable Sewing Tool with Sewing Kit, Small, for All Age, Kids or Adults | G38: 0 | H38: -1 | O38: USD | P38: 0 | Q38: 0 | R38: 0 | S38: 0 | U38: 0 | V38: 0 | W38: 0 | X38: 0 | Y38: NoRestockExcessActionRequired | AB38: 0 | AC38: 0 | AE38: -1 | AH38: Standard | AJ38: US | AK38: gl_home | AL38: 32209 | AM38: 0 | AN38: 0 | AQ38: 34.99 | AR38: 0 | AS38: 0 | AT38: 0 | AU38: 0 | AY38: 0 | BB38: 0 | BC38: 0 | BD38: 0 | BE38: 0 | BG38: 0 | BH38: 0 | BZ38: 1 | CA38: Out of stock | CB38: 231 | CC38: 46188 | CJ38: 0 | CK38: 0 | CL38: 0 | CM38: 0 | CN38: 0 | CO38: 0 | CP38: unassigned | CQ38: N
A39: 46188 | B39: X003RGBNZL | C39: B0BYVFTT4X | D39: YaoKongQi Teether09 | E39: ROHSCE Silicone Baby Teether Toys, Remote Game Control Teething Toys for Babies 6-12 Months Soft Molar Teether Infant Baby Chew Toys Sensory Remote Teether BPA-Free Gifts, Black+Dark Blue | G39: 0 | H39: -1 | O39: USD | U39: 0 | V39: 0 | W39: 0 | X39: 0 | Y39: NoRestockExcessActionRequired | AB39: 0 | AC39: 0 | AE39: -1 | AH39: Standard | AJ39: US | AK39: gl_baby_product | AM39: 0 | AN39: 0 | AQ39: 3.99 | AY39: 0 | BB39: 0 | BC39: 0 | BD39: 0 | BE39: 0 | BG39: 0 | BH39: 0 | CJ39: 0 | CK39: 0 | CL39: 0 | CM39: 0 | CN39: 0 | CO39: 0 | CP39: unassigned | CQ39: N
A40: 46188 | B40: X003G49PO5 | C40: B09GVMZLSF | D40: SoftBuildingBlock-9 | E40: Flying Banana Building Blocks Baby Toys for 3 Months and up, Soft Squeeze Sensory Colorful Teething Chewing Educational Stacking Blocks with 3D Embossed Patterns | G40: 0 | H40: -1 | O40: USD | U40: 0 | V40: 0 | W40: 0 | X40: 0 | Y40: NoRestockExcessActionRequired | AB40: 0 | AC40: 0 | AE40: -1 | AH40: Standard | AJ40: US | AK40: gl_toy | AM40: 0 | AN40: 0 | AQ40: 9.99 | AY40: 0 | BB40: 0 | BC40: 0 | BD40: 0 | BE40: 0 | BG40: 0 | BH40: 0 | CJ40: 0 | CK40: 0 | CL40: 0 | CM40: 0 | CN40: 0 | CO40: 0 | CP40: unassigned | CQ40: N
A41: 46188 | B41: X004MKHF03 | C41: B0F18Z6W15 | D41: 50US-YingErYongQuan-005 | E41: Baby Pool Float with Removable Sun Canopy,Infant Swim Float with Anti-Flip Tail Design Baby Toy | G41: 0 | H41: -1 | O41: USD | U41: 0 | V41: 0 | W41: 0 | X41: 0 | Y41: NoRestockExcessActionRequired | AB41: 0 | AC41: 0 | AE41: -1 | AH41: Other | AJ41: US | AK41: gl_outdoors | AN41: 0 | AY41: 0 | BB41: 0 | BG41: 0 | BH41: 0 | CJ41: 0 | CK41: 0 | CL41: 0 | CM41: 0 | CN41: 0 | CP41: unassigned | CQ41: N
A42: 46188 | B42: X0046MF699 | C42: B0CFZM7ZMN | D42: 50-lansexiaoshuiqiang-MN | E42: ROHSCE Electric Water Gun Pistol, Rechargeable Automatic Squirt Guns Up to 26 FT Range, One-Button Powerful Squirt Guns for Kids & Adults Summer Swimming Pool Party Beach Outdoor Activity, Blue | G42: 0 | H42: -1 | O42: USD | U42: 0 | V42: 0 | W42: 0 | X42: 0 | Y42: NoRestockExcessActionRequired | AB42: 0 | AC42: 0 | AE42: -1 | AH42: Standard | AJ42: US | AK42: gl_toy | AM42: 0 | AN42: 0 | AQ42: 9.99 | AY42: 0 | BB42: 0 | BC42: 0 | BD42: 0 | BE42: 0 | BG42: 0 | BH42: 0 | CJ42: 0 | CK42: 0 | CL42: 0 | CM42: 0 | CN42: 0 | CO42: 0 | CP42: unassigned | CQ42: N
A43: 46188 | B43: X004MKYNOJ | C43: B0F192ZFBS | D43: 50US-YingErYongQuan-002 | E43: ROHSCE Baby Beach Float with Canopy 1 Year Old Pool Float 6 Month Pool Float 12 Month Swim Float for Infants & Toddlers Infant Swim Float | F43: New | G43: 4 | H43: 0 | I43: 0 | J43: 0 | K43: 0 | L43: 0 | M43: 4 | N43: 0 | O43: USD | P43: 0 | Q43: 0 | R43: 0 | S43: 0 | T43: Low traffic | U43: 109.99 | V43: 104.49 | W43: 104.49 | X43: 0 | Y43: Create removal order | AA43: 0 | AB43: 0 | AC43: 0 | AD43: 909.48 | AE43: 0 | AF43: 0.791667 | AG43: cubic feet | AH43: Oversize | AI43: 3.166668 | AJ43: US | AK43: gl_sports | AL43: 1371949 | AM43: 366 | AN43: 4 | AQ43: 104.49 | AR43: 0 | AS43: 0 | AT43: 0 | AU43: 0 | AV43: 0 | AW43: 0 | AX43: 0 | AY43: 0 | AZ43: 0 | BA43: 23.27 | BB43: 0 | BC43: 0 | BD43: 0 | BE43: 0 | BG43: 0 | BH43: 0 | BI43: 0 | BJ43: 0 | BK43: 0 | BL43: 0 | BM43: 0 | BN43: 0 | BO43: 0 | BP43: 0 | BQ43: 0 | BR43: 0 | BS43: 0 | BT43: 0 | BU43: 4 | BV43: 21.85 | BW43: 0 | BX43: 0 | BZ43: 1 | CA43: Excess | CI43: 46186 | CJ43: 4 | CK43: 0 | CL43: 0 | CM43: 0 | CN43: 0 | CO43: 366 | CP43: unassigned | CQ43: N
A44: 46188 | B44: X003FOM7BJ | C44: B0BJBDJRTB | D44: Teether-HongLan | E44: Silicone Baby Teether Toys, Silicone Baby Teething Toys, BPA Free Teething Relief Baby Toys, Soft Textured Toddler Molar Toy, Silicone Teethers for Babies - 2 Pack… | G44: 0 | H44: -1 | O44: USD | U44: 0 | V44: 0 | W44: 0 | X44: 0 | Y44: NoRestockExcessActionRequired | AB44: 0 | AC44: 0 | AE44: -1 | AJ44: US | AK44: gl_baby_product | AN44: 0 | AY44: 0 | BB44: 0 | BG44: 0 | BH44: 0 | CJ44: 0 | CK44: 0 | CL44: 0 | CM44: 0 | CN44: 0 | CP44: unassigned | CQ44: N
A45: 46188 | B45: X0051KLQX5 | C45: B0GJYW6Z2F | D45: 50US-TankYaoKongQi-001 | E45: ROHSCE 2-in-1 RC Tank Remote Controller Set, Replacement Handheld Controller and Gesture Sensing Watch Remote for Compatible Stunt Battle Tank Toy, RC Tank Spare Accessories | F45: New | G45: 19 | H45: 0 | I45: 19 | J45: 0 | K45: 0 | L45: 0 | M45: 0 | N45: 0 | O45: USD | P45: 1 | Q45: 1 | R45: 1 | S45: 1 | T45: Low conversion | U45: 41.99 | V45: 0 | W45: 21.99 | X45: 0 | Y45: Lower price | AA45: 0 | AB45: 0 | AC45: 0 | AD45: 0 | AE45: 0.08 | AF45: 0.038098 | AG45: cubic feet | AH45: Standard | AI45: 0.723862 | AJ45: US | AK45: gl_toy | AL45: 206385 | AM45: 64 | AN45: 0 | AO45: 76 | AP45: 247 | AQ45: 21.99 | AR45: 0 | AS45: 0 | AT45: 0 | AU45: 0 | AV45: 0 | AW45: 19 | AX45: 0 | AY45: 0 | AZ45: 0 | BA45: 0.52 | BB45: 0 | BC45: 0 | BD45: 0 | BE45: 0 | BG45: 0 | BH45: 0 | BY45: 936 | BZ45: 11 | CA45: Healthy | CB45: 1 | CC45: 46195 | CD45: 46188 | CE45: Yes | CF45: No | CG45: 596 | CH45: 936 | CI45: 46186 | CJ45: 19 | CK45: 0 | CL45: 0 | CM45: 0 | CN45: 0 | CO45: 64 | CP45: unassigned | CQ45: N
A46: 46188 | B46: X0046MLIKF | C46: B0CDLWPTCN | D46: 50-xiaohaohongseshuqiang-TCN | E46: ROHSCE Electric Water Gun Pistol, Automatic Adult Water Pistol, Powerful Squirt Guns Long Range, Backyard Beach Party Toy, Pistolas De Agua Holiday Deals for Kids | G46: 0 | H46: -1 | O46: USD | U46: 0 | V46: 0 | W46: 0 | X46: 0 | Y46: NoRestockExcessActionRequired | AB46: 0 | AC46: 0 | AE46: -1 | AH46: Standard | AJ46: US | AK46: gl_toy | AM46: 0 | AN46: 0 | AQ46: 9.99 | AY46: 0 | BB46: 0 | BC46: 0 | BD46: 0 | BE46: 0 | BG46: 0 | BH46: 0 | CJ46: 0 | CK46: 0 | CL46: 0 | CM46: 0 | CN46: 0 | CO46: 0 | CP46: unassigned | CQ46: N
A47: 46188 | B47: X003IXZ8FJ | C47: B0BMXGWYJ8 | D47: diediele-01 | E47: ROHSCE Baby Sensory Stacking Rings - Montessori Educational Developmental Learning Infant Toys - Soft Building Blocks Toddlers - Baby Toys Newborn for 6 9 12 18 Month 1 One Year Old Girls Boys Gifts | G47: 0 | H47: -1 | O47: USD | U47: 0 | V47: 0 | W47: 0 | X47: 0 | Y47: NoRestockExcessActionRequired | AB47: 0 | AC47: 0 | AE47: -1 | AH47: Standard | AJ47: US | AK47: gl_toy | AN47: 0 | AQ47: 5.99 | AY47: 0 | BB47: 0 | BC47: 0 | BD47: 0 | BE47: 0 | BG47: 0 | BH47: 0 | CJ47: 0 | CK47: 0 | CL47: 0 | CM47: 0 | CN47: 0 | CP47: unassigned | CQ47: N
A48: 46188 | B48: X003799QHF | C48: B09W29MZHD | D48: 2yaojiao | E48: Silicone Baby Teether Toys, BPA Free Teething Relief, Soft Textured Toddler Molar Teethers for Babies - 2 Pack | G48: 0 | H48: -1 | O48: USD | U48: 0 | V48: 0 | W48: 0 | X48: 0 | Y48: NoRestockExcessActionRequired | AB48: 0 | AC48: 0 | AE48: -1 | AH48: Standard | AJ48: US | AK48: gl_baby_product | AM48: 0 | AN48: 0 | AQ48: 9.99 | AY48: 0 | BB48: 0 | BC48: 0 | BD48: 0 | BE48: 0 | BG48: 0 | BH48: 0 | CJ48: 0 | CK48: 0 | CL48: 0 | CM48: 0 | CN48: 0 | CO48: 0 | CP48: unassigned | CQ48: N
A49: 46188 | B49: X003RGLZ3V | C49: B0BYVCWKJD | D49: YaoKongQi Teether08 | E49: ROHSCE 2 Pcs Silicone Baby Teether Toys, Remote Game Control Teething Toys for Babies 6-12 Months Soft Molar Teether Infant Baby Chew Toys Sensory Remote Teether BPA-Free Gifts, Pink | G49: 0 | H49: -1 | O49: USD | U49: 0 | V49: 0 | W49: 0 | X49: 0 | Y49: NoRestockExcessActionRequired | AB49: 0 | AC49: 0 | AE49: -1 | AH49: Standard | AJ49: US | AK49: gl_baby_product | AM49: 0 | AN49: 0 | AQ49: 9.49 | AY49: 0 | BB49: 0 | BC49: 0 | BD49: 0 | BE49: 0 | BG49: 0 | BH49: 0 | CJ49: 0 | CK49: 0 | CL49: 0 | CM49: 0 | CN49: 0 | CO49: 0 | CP49: unassigned | CQ49: N
A50: 46188 | B50: X005522ABV | C50: B0H38PBQSJ | D50: 50US-yuer003 | G50: 0 | H50: -1 | O50: USD | U50: 0 | V50: 0 | W50: 0 | X50: 0 | Y50: NoRestockExcessActionRequired | AB50: 0 | AC50: 0 | AE50: -1 | AJ50: US | AN50: 0 | AY50: 0 | BB50: 0 | BG50: 0 | BH50: 0 | CJ50: 0 | CK50: 0 | CL50: 0 | CM50: 0 | CN50: 0 | CP50: unassigned | CQ50: N
A51: 46188 | B51: X004QM4UD7 | C51: B0DYN23PHP | D51: 50-3Ddongwupintu-Shizi2 | E51: ROHSCE 3D Puzzles for Kids Ages 3-8 - 6 Pack Animal Models (Lion, Dino, Elephant) - DIY EVA Foam Jigsaw Puzzle Toy - STEM Educational Building Kit Arts & Crafts Gift for Boys & Girls | F51: New | G51: 18 | H51: 0 | I51: 19 | J51: 0 | K51: 0 | L51: 0 | M51: 0 | N51: 0 | O51: USD | P51: 1 | Q51: 9 | R51: 12 | S51: 15 | T51: Low traffic | U51: 23.59 | V51: 18.99 | W51: 18.99 | X51: 0 | Y51: NoExcessInventory | AA51: 9.49 | AB51: 2 | AC51: 0 | AD51: 36.93 | AE51: 2 | AF51: 0.098612 | AG51: cubic feet | AH51: Standard | AI51: 1.775016 | AJ51: US | AK51: gl_toy | AL51: 409152 | AM51: 73 | AN51: 0 | AO51: 8 | AP51: 15 | AQ51: 18.99 | AR51: 18.99 | AS51: 180.11 | AT51: 250.88 | AU51: 302.84 | AV51: 19 | AW51: 0 | AX51: 0 | AY51: 0 | AZ51: 0 | BA51: 1.17 | BB51: 0 | BC51: 0 | BD51: 0 | BE51: 0 | BG51: 0 | BH51: 1 | BY51: 60.5 | BZ51: 14 | CA51: Healthy | CB51: 4 | CC51: 46194 | CD51: 46188 | CE51: Yes | CF51: No | CG51: 60.5 | CH51: 47.1 | CI51: 46186 | CJ51: 18 | CK51: 0 | CL51: 0 | CM51: 0 | CN51: 0 | CO51: 73 | CP51: unassigned | CQ51: N
A52: 46188 | B52: X002O7Y9LT | C52: B08KT79KJG | D52: FBA-10JianTaoShouZhuaQiu-BeiZi | E52: Sensory Balls for Baby, Infant Toys 6-12 Months, Textured Multi Balls for Toddlers 1-3 Colorful Soft Squeezy Bath Toy with Stacking Cups Montessori Toys for Babies Juguetes Para Bebes de 0 a 6 Meses | G52: 0 | H52: -1 | O52: USD | U52: 0 | V52: 0 | W52: 0 | X52: 0 | Y52: NoRestockExcessActionRequired | AB52: 0 | AC52: 0 | AE52: -1 | AH52: Standard | AJ52: US | AK52: gl_toy | AM52: 0 | AN52: 0 | AQ52: 25.99 | AY52: 0 | BB52: 0 | BC52: 0 | BD52: 0 | BE52: 0 | BG52: 0 | BH52: 0 | BZ52: 1 | CA52: Out of stock | CJ52: 0 | CK52: 0 | CL52: 0 | CM52: 0 | CN52: 0 | CO52: 0 | CP52: unassigned | CQ52: N
A53: 46188 | B53: X004SQMZBP | C53: B0FGCFD9FS | D53: XiaocheMaoRongChe001 | E53: ROHSCE Plush Remote Control Bus for Toddlers, 2.4GHz Soft Body RC Car with Music Universal Brick-Compatible Roof, Easy 2-Button Controller, Durable Wheels, Gift Toy for Boys & Girls Ages 2–5 | G53: 0 | H53: -1 | O53: USD | P53: 0 | Q53: 0 | R53: 0 | S53: 0 | U53: 0 | V53: 0 | W53: 0 | X53: 0 | Y53: NoRestockExcessActionRequired | AB53: 0 | AC53: 0 | AE53: -1 | AH53: Standard | AJ53: US | AK53: gl_toy | AM53: 0 | AN53: 0 | AQ53: 35.99 | AR53: 0 | AS53: 0 | AT53: 0 | AU53: 0 | AY53: 0 | BB53: 0 | BC53: 0 | BD53: 0 | BE53: 0 | BG53: 0 | BH53: 0 | BZ53: 1 | CA53: Out of stock | CJ53: 0 | CK53: 0 | CL53: 0 | CM53: 0 | CN53: 0 | CO53: 0 | CP53: unassigned | CQ53: N
A54: 46188 | B54: X002QT71KV | C54: B08J3MZQ2M | D54: New4JianTaoQiu-02 | E54: ROHSCE Montessori Toys for Babies 3 Months+, Baby Balls 3 to 12 Month for Babies & Toddlers 3M+, Textured Multi Ball Set Colorful & Soft Squeezy Sensory Toys. Stress Relief Balls for Infant (4 Pack) | F54: New | G54: 289 | H54: 0 | I54: 309 | J54: 0 | K54: 0 | L54: 0 | M54: 0 | N54: 0 | O54: USD | P54: 25 | Q54: 123 | R54: 283 | S54: 524 | U54: 18.99 | V54: 0 | W54: 18.99 | X54: 0 | Y54: NoRestockExcessActionRequired | AA54: 0 | AB54: 0 | AC54: 0 | AD54: 0 | AE54: 2.17 | AF54: 0.064997 | AG54: cubic feet | AH54: Standard | AI54: 18.784133 | AJ54: US | AK54: gl_toy | AL54: 2409 | AM54: 74 | AN54: 0 | AO54: 17 | AP54: 13 | AQ54: 14.24 | AR54: 370.25 | AS54: 1770.52 | AT54: 4022.32 | AU54: 7382.1 | AV54: 299 | AW54: 10 | AX54: 0 | AY54: 0 | AZ54: 0 | BA54: 15.08 | BB54: 240 | BC54: 0 | BD54: 240 | BE54: 0 | BG54: 14 | BH54: 0 | BY54: 71.8 | BZ54: 372 | CA54: Low stock | CB54: 345 | CC54: 46195 | CD54: 46188 | CE54: No | CF54: No | CG54: 71.8 | CH54: 36 | CI54: 46186 | CJ54: 539 | CK54: 10 | CL54: 13 | CM54: 1 | CN54: 0 | CO54: 77 | CP54: unassigned | CQ54: N
A55: 46188 | B55: X00554QX3F | C55: B0H3FCR75C | D55: 50US-yinyueguBlue-001 | E55: ROHSCE Musical Drum Toy with Sound Effects, Colorful Baby Music Toy with Double Drum Pads, Buttons, Lights and Melodies, Interactive Early Learning Musical Toy Gift for Toddlers Boys Girls | F55: New | G55: 0 | H55: -1 | O55: USD | U55: 55.99 | V55: 0 | W55: 0 | X55: 0 | Y55: Edit listing | AB55: 0 | AC55: 0 | AE55: -1 | AH55: Standard | AJ55: US | AK55: gl_baby_product | AN55: 0 | AQ55: 55.99 | AY55: 0 | BB55: 20 | BC55: 20 | BD55: 0 | BE55: 0 | BG55: 0 | BH55: 0 | CJ55: 20 | CK55: 0 | CL55: 0 | CM55: 0 | CN55: 0 | CP55: unassigned | CQ55: N
A56: 46188 | B56: X0046ME5HX | C56: B0CDLW2X17 | D56: 50-dahongseshuiqiang-X17 | E56: ROHSCE Electric Water Gun, Powerful Automatic Water Gun, Long Range Classic Big Electronic Watergun, Summer Outdoor Beach and Pool Party Toy, Holiday Deals Water Blaster Toy for Kids Adults, Red | G56: 0 | H56: -1 | O56: USD | U56: 0 | V56: 0 | W56: 0 | X56: 0 | Y56: NoRestockExcessActionRequired | AB56: 0 | AC56: 0 | AE56: -1 | AJ56: US | AK56: gl_toy | AM56: 0 | AN56: 0 | AQ56: 9.49 | AY56: 0 | BB56: 0 | BG56: 0 | BH56: 0 | CJ56: 0 | CK56: 0 | CL56: 0 | CM56: 0 | CN56: 0 | CO56: 0 | CP56: unassigned | CQ56: N
A57: 46188 | B57: X003DYNUKD | C57: B0BDFBYHNQ | D57: SZQchuxuGuan-02 | E57: ROHSCE Balls for Toddlers 1-3 Baby Sensory Toys, Montessori Toys for Babies 6-12 Months Baby Toys, Sensory Ball BPA Free Teething Gift Toddler Balls Bath Toys with Bright Color Multi Textured | F57: New | G57: 54 | H57: 0 | I57: 69 | J57: 0 | K57: 0 | L57: 0 | M57: 0 | N57: 0 | O57: USD | P57: 4 | Q57: 14 | R57: 26 | S57: 62 | U57: 29.99 | V57: 0 | W57: 28.49 | X57: 0 | Y57: CreateShippingPlan | AA57: 0 | AB57: 0 | AC57: 0 | AD57: 0 | AE57: 1.35 | AF57: 0.166667 | AG57: cubic feet | AH57: Standard | AI57: 9.000018 | AJ57: US | AK57: gl_toy | AL57: 9437 | AM57: 95 | AN57: 0 | AO57: 15 | AP57: 11 | AQ57: 24.99 | AR57: 99.96 | AS57: 350.08 | AT57: 659.57 | AU57: 1529.21 | AV57: 18 | AW57: 51 | AX57: 0 | AY57: 0 | AZ57: 0 | BA57: 7.21 | BB57: 0 | BC57: 0 | BD57: 0 | BE57: 0 | BG57: 0 | BH57: 0 | BY57: 100.3 | BZ57: 44 | CA57: Healthy | CB57: 19 | CC57: 46195 | CD57: 46181 | CE57: Yes | CF57: No | CG57: 100.3 | CH57: 47.9 | CI57: 46186 | CJ57: 67 | CK57: 13 | CL57: 0 | CM57: 0 | CN57: 0 | CO57: 95 | CP57: unassigned | CQ57: N
A58: 46188 | B58: X004T2YG3N | C58: B0F13S45L4 | D58: 50US-DuiDieKongLong-003 | E58: ROHSCE Rainbow Stacker Pull Along Toy for Toddlers 18-36 Months, Montessori 2 in 1 Stacking Toys Push & Pull Toys, Autism Sensory Learning Toy with 6 Nesting Arches, Baby Gifts for Christmas Birthday | G58: 21 | H58: 0 | I58: 0 | J58: 1 | K58: 20 | L58: 0 | M58: 0 | N58: 0 | O58: USD | P58: 0 | Q58: 1 | R58: 2 | S58: 5 | T58: Low traffic | W58: 39.99 | X58: -1 | Y58: Edit listing | AA58: 19.99 | AB58: 2 | AC58: 0 | AD58: 1188.86 | AE58: 0.21 | AF58: 0.200379 | AG58: cubic feet | AH58: Standard | AI58: 4.207959 | AJ58: US | AK58: gl_toy | AL58: 707040 | AM58: 351 | AN58: 21 | AO58: 84 | AP58: 54 | AQ58: 31.99 | AR58: 0 | AS58: 37.99 | AT58: 77.98 | AU58: 174.75 | AV58: 0 | AW58: 0 | AX58: 0 | AY58: 20 | AZ58: 0 | BA58: 24.64 | BB58: 0 | BC58: 0 | BD58: 0 | BE58: 0 | BG58: 1 | BH58: 0 | BI58: 0 | BJ58: 0 | BK58: 0 | BL58: 0 | BM58: 20 | BN58: 6.01 | BO58: 0 | BP58: 0 | BQ58: 0 | BR58: 0 | BS58: 0 | BT58: 0 | BU58: 0 | BV58: 0 | BW58: 0 | BX58: 0 | BY58: 673 | BZ58: 3 | CA58: Excess | CD58: 46188 | CE58: Yes | CF58: No | CG58: 673 | CH58: 423 | CI58: 46186 | CJ58: 21 | CK58: 0 | CL58: 1 | CM58: 0 | CN58: 0 | CO58: 366 | CP58: unassigned | CQ58: N
A59: 46188 | B59: X0051KLSBP | C59: B0GJZ76Q62 | D59: 50US-TankTiHuanJiShen-02 | E59: ROHSCE Green RC Tank Replacement Body, RC Tank Accessories Plastic Hull Shell Cover for Remote Control Tank Toy, Repair Upgrade Spare Parts for Hobby Model Vehicles | F59: New | G59: 20 | H59: 0 | I59: 20 | J59: 0 | K59: 0 | L59: 0 | M59: 0 | N59: 0 | O59: USD | T59: Low conversion | U59: 41.99 | V59: 0 | W59: 28.99 | X59: 0 | Y59: Lower price | AA59: 0 | AB59: 0 | AC59: 0 | AD59: 0 | AE59: 0 | AF59: 0.091635 | AG59: cubic feet | AH59: Standard | AI59: 1.8327 | AJ59: US | AK59: gl_toy | AL59: 206385 | AM59: 28 | AN59: 0 | AQ59: 28.99 | AV59: 0 | AW59: 20 | AX59: 0 | AY59: 0 | AZ59: 0 | BA59: 1.31 | BB59: 0 | BC59: 0 | BD59: 0 | BE59: 0 | BG59: 0 | BH59: 0 | CB59: 48 | CC59: 46193 | CI59: 46186 | CJ59: 20 | CK59: 0 | CL59: 0 | CM59: 0 | CN59: 0 | CO59: 28 | CP59: unassigned | CQ59: N
A60: 46188 | B60: X004RPXR2X | C60: B08G4MQP82 | D60: FengrenjiP82-NEWp | E60: Sewing Machine for Beginners with Extension Table, Adjustable 2-Speed 2-Thread Mini Sewing Machine, Portable Electric Maquina de Coser with Foot Pedal, Perfect for DIY, Ideal Gift for Kids and Adults | F60: New | G60: 31 | H60: 0 | I60: 39 | J60: 0 | K60: 0 | L60: 0 | M60: 0 | N60: 0 | O60: USD | P60: 16 | Q60: 23 | R60: 62 | S60: 93 | U60: 39.99 | V60: 0 | W60: 39.99 | X60: 0 | Y60: NoRestockExcessActionRequired | AA60: 0 | AB60: 0 | AC60: 0 | AD60: 0 | AE60: 2.09 | AF60: 0.292129 | AG60: cubic feet | AH60: Standard | AI60: 9.055999 | AJ60: US | AK60: gl_home | AL60: 32209 | AM60: 153 | AN60: 0 | AO60: 27 | AP60: 21 | AQ60: 39.99 | AR60: 591.84 | AS60: 842.27 | AT60: 2171.38 | AU60: 3234.57 | AV60: 39 | AW60: 0 | AX60: 0 | AY60: 0 | AZ60: 0 | BA60: 31.78 | BB60: 126 | BC60: 0 | BD60: 126 | BE60: 0 | BG60: 1 | BH60: 1 | BY60: 38.4 | BZ60: 29 | CA60: Healthy | CD60: 46188 | CE60: Yes | CF60: No | CG60: 38.4 | CH60: 37.7 | CI60: 46186 | CJ60: 163 | CK60: 6 | CL60: 1 | CM60: 0 | CN60: 0 | CO60: 154 | CP60: unassigned | CQ60: N
A61: 46188 | B61: B09M6DVNWX | C61: B09M6DVNWX | D61: NeiLian-BaiSe | E61: Snap-in Clear Shower Curtain Liner Replacement Hotel Qulity Premium Polyester Waterproof Fabric with Bottom Weighted Magnets to stable for Bathroom and Bathtub - Machine Washable 70 x 54 inch | G61: 0 | H61: -1 | O61: USD | U61: 0 | V61: 0 | W61: 0 | X61: 0 | Y61: NoRestockExcessActionRequired | AB61: 0 | AC61: 0 | AE61: -1 | AJ61: US | AK61: gl_home | AN61: 0 | AQ61: 19.99 | AY61: 0 | BB61: 0 | BG61: 0 | BH61: 0 | CJ61: 0 | CK61: 0 | CL61: 0 | CM61: 0 | CN61: 0 | CP61: unassigned | CQ61: N
A62: 46188 | B62: X004ETIY4N | C62: B0FP4VXQV9 | D62: 50-ErTongYuGang-LWL | E62: Small Fish Tank, Portable Betta Fish Tank for Kids with LED Light, Air Pump,Battery,Small Aquarium KIT - Perfect for Home Decor and Pet Care,Educational Science Gifts for Kids | F62: New | G62: 20 | H62: 0 | I62: 0 | J62: 20 | K62: 0 | L62: 0 | M62: 0 | N62: 0 | O62: USD | P62: 0 | Q62: 3 | R62: 4 | S62: 7 | T62: Low traffic | U62: 89.99 | V62: 64.99 | W62: 64.99 | X62: 0 | Y62: NoExcessInventory | AA62: 51.99 | AB62: 2 | AC62: 0 | AD62: 1877.13 | AE62: 0.3 | AF62: 0.765443 | AG62: cubic feet | AH62: Oversize | AI62: 15.30886 | AJ62: US | AK62: gl_pet_products | AL62: 216542 | AM62: 133 | AN62: 16 | AO62: 26 | AP62: 37 | AQ62: 64.99 | AR62: 0 | AS62: 194.97 | AT62: 259.96 | AU62: 479.93 | AV62: 0 | AW62: 0 | AX62: 0 | AY62: 0 | AZ62: 0 | BA62: 10.94 | BB62: 0 | BC62: 0 | BD62: 0 | BE62: 0 | BG62: 0 | BH62: 0 | BY62: 290.6 | BZ62: 6 | CA62: Excess | CD62: 46188 | CE62: Yes | CF62: No | CG62: 212.7 | CH62: 290.6 | CI62: 46186 | CJ62: 20 | CK62: 0 | CL62: 0 | CM62: 0 | CN62: 0 | CO62: 133 | CP62: unassigned | CQ62: N
A63: 46188 | B63: X002QADNUH | C63: B07SX1T3JQ | D63: FBA-ShouZhuaQiu-3JQ | E63: ROHSCE Sensory Balls for Baby, 6PCS Textured Sensory Toys for Toddlers 1-3 | F63: New | G63: 68 | H63: 0 | I63: 49 | J63: 19 | K63: 0 | L63: 0 | M63: 0 | N63: 0 | O63: USD | P63: 1 | Q63: 6 | R63: 10 | S63: 24 | T63: Low traffic | U63: 15.99 | V63: 0 | W63: 15.99 | X63: 0 | Y63: NoExcessInventory | AA63: 0 | AB63: 0 | AC63: 0 | AD63: 0 | AE63: 0.44 | AF63: 0.082718 | AG63: cubic feet | AH63: Standard | AI63: 5.624824 | AJ63: US | AK63: gl_toy | AL63: 243893 | AM63: 176 | AN63: 0 | AO63: 45 | AP63: 36 | AQ63: 15.99 | AR63: 15.99 | AS63: 95.94 | AT63: 159.9 | AU63: 383.76 | AV63: 0 | AW63: 49 | AX63: 0 | AY63: 0 | AZ63: 0 | BA63: 3.91 | BB63: 0 | BC63: 0 | BD63: 0 | BE63: 0 | BG63: 0 | BH63: 0 | BY63: 424.6 | BZ63: 26 | CA63: Healthy | CD63: 46188 | CE63: Yes | CF63: No | CG63: 424.6 | CH63: 193.8 | CI63: 46186 | CJ63: 68 | CK63: 0 | CL63: 0 | CM63: 0 | CN63: 0 | CO63: 176 | CP63: unassigned | CQ63: N
A64: 46188 | B64: X002LZJLYJ | C64: B08FDQBKW2 | D64: 10CunDengZsUs-5001 | E64: Flying Banana 10 inch Selfie Ring Light With Tripod Stand and Cell Phone Holder & Remote Control 3 Light Modes For YouTube Videos/Makeup Light/Live Streaming/Vlog Compatible For iPhone & Android Phone | G64: 0 | H64: -1 | O64: USD | U64: 0 | V64: 0 | W64: 0 | X64: 0 | Y64: NoRestockExcessActionRequired | AB64: 0 | AC64: 0 | AE64: -1 | AH64: Oversize | AJ64: US | AK64: gl_wireless | AN64: 0 | AQ64: 8.99 | AY64: 0 | BB64: 0 | BC64: 0 | BD64: 0 | BE64: 0 | BG64: 0 | BH64: 0 | CJ64: 0 | CK64: 0 | CL64: 0 | CM64: 0 | CN64: 0 | CP64: unassigned | CQ64: N
A65: 46188 | B65: X002M44UOZ | C65: B08FRGNGGZ | D65: YuLianZsUs3-5001 | E65: ROHSCE Hookless Shower Curtain Set with Snap-in Liner, 250GSM Waffle Weave Fabric, Hotel Grade, Mesh Window, Weighted Hem, 72x74 Inch - Black | G65: 0 | H65: -1 | O65: USD | U65: 0 | V65: 0 | W65: 0 | X65: 0 | Y65: NoRestockExcessActionRequired | AB65: 0 | AC65: 0 | AE65: -1 | AH65: Standard | AJ65: US | AK65: gl_home | AL65: 1351087 | AM65: 0 | AN65: 0 | AQ65: 33.99 | AY65: 0 | BB65: 0 | BC65: 0 | BD65: 0 | BE65: 0 | BG65: 0 | BH65: 0 | CB65: 39 | CC65: 46186 | CJ65: 0 | CK65: 0 | CL65: 0 | CM65: 0 | CN65: 0 | CO65: 0 | CP65: unassigned | CQ65: N
A66: 46188 | B66: X003HY2WML | C66: B0BLHZG8SC | D66: SoftBuildingBlock-112 | E66: ROHSCE Baby Blocks, 34PCS Soft Building Blocks for Babies 12M+ | F66: New | G66: 58 | H66: 0 | I66: 0 | J66: 75 | K66: 0 | L66: 0 | M66: 0 | N66: 0 | O66: USD | P66: 3 | Q66: 5 | R66: 6 | S66: 11 | U66: 29.99 | V66: 25.99 | W66: 25.99 | X66: 0 | Y66: NoRestockExcessActionRequired | AA66: 0 | AB66: 0 | AC66: 0 | AD66: 0 | AE66: 0.14 | AF66: 0.247108 | AG66: cubic feet | AH66: Standard | AI66: 14.332264 | AJ66: US | AK66: gl_toy | AL66: 26497 | AM66: 171 | AN66: 0 | AO66: 46 | AP66: 68 | AQ66: 25.99 | AR66: 77.97 | AS66: 129.95 | AT66: 155.44 | AU66: 276.89 | AV66: 0 | AW66: 0 | AX66: 0 | AY66: 0 | AZ66: 0 | BA66: 9.69 | BB66: 0 | BC66: 0 | BD66: 0 | BE66: 0 | BG66: 17 | BH66: 1 | BY66: 661.1 | BZ66: 18 | CA66: Healthy | CD66: 46188 | CE66: Yes | CF66: No | CG66: 471.8 | CH66: 661.1 | CI66: 46186 | CJ66: 58 | CK66: 0 | CL66: 1 | CM66: 0 | CN66: 16 | CO66: 182 | CP66: unassigned | CQ66: N
A67: 46188 | B67: X003IXQXAD | C67: B0BMXGYDTX | D67: diediele-07 | E67: ROHSCE Famure 6 Pieces Stacking Rings Stacking Blocks Montessori Toys Soft Stacking Blocks Ring Stacker Early Learning Toys for Babies | G67: 0 | H67: -1 | O67: USD | U67: 0 | V67: 0 | W67: 0 | X67: 0 | Y67: NoRestockExcessActionRequired | AB67: 0 | AC67: 0 | AE67: -1 | AH67: Standard | AJ67: US | AK67: gl_toy | AN67: 0 | AQ67: 16.99 | AY67: 0 | BB67: 0 | BC67: 0 | BD67: 0 | BE67: 0 | BG67: 0 | BH67: 0 | CJ67: 0 | CK67: 0 | CL67: 0 | CM67: 0 | CN67: 0 | CP67: unassigned | CQ67: N
A68: 46188 | B68: X002Y9PO5H | C68: B098WSPFTH | D68: YLSZQ-0708 | E68: Sensory Balls Baby Toys 6 to 12 Months Textured Multicolor 7 Pcs, Hand Catching Balls Rattle Sensory Toys for Toddlers 1-3 Sensory Developmental Newborn Baby Toys | G68: 0 | H68: -1 | O68: USD | U68: 0 | V68: 0 | W68: 0 | X68: 0 | Y68: NoRestockExcessActionRequired | AB68: 0 | AC68: 0 | AE68: -1 | AJ68: US | AK68: gl_sports | AN68: 0 | AY68: 0 | BB68: 0 | BG68: 0 | BH68: 0 | CJ68: 0 | CK68: 0 | CL68: 0 | CM68: 0 | CN68: 0 | CP68: unassigned | CQ68: N
A69: 46188 | B69: X004OTJ8S9 | C69: B0CCJKDDLG | D69: 50Fengrenji-WhiteNEW01 | E69: Flying Banana Portable Dual Speed Electric Sewing Kit for Beginners with Extension Table, Mini Sewing Machine with Light, Foot Pedal & Accessories for Household Travel DIY Crafts Repair, White | F69: New | G69: 14 | H69: 0 | I69: 0 | J69: 1 | K69: 0 | L69: 13 | M69: 0 | N69: 0 | O69: USD | P69: 0 | Q69: 0 | R69: 0 | S69: 0 | T69: Low traffic | U69: 43.37 | V69: 35.99 | W69: 35.99 | X69: 0 | Y69: Advertise listing | AA69: 0 | AB69: 0 | AC69: 0 | AD69: 821.51 | AE69: 0 | AF69: 0.270031 | AG69: cubic feet | AH69: Standard | AI69: 3.780434 | AJ69: US | AK69: gl_home | AL69: 680561 | AM69: 191 | AN69: 13 | AQ69: 35.99 | AR69: 0 | AS69: 0 | AT69: 0 | AU69: 0 | AV69: 0 | AW69: 0 | AX69: 0 | AY69: 0 | AZ69: 13 | BA69: 26.83 | BB69: 0 | BC69: 0 | BD69: 0 | BE69: 0 | BG69: 0 | BH69: 0 | BI69: 0 | BJ69: 0 | BK69: 0 | BL69: 0 | BM69: 0 | BN69: 0 | BO69: 0 | BP69: 0 | BQ69: 0 | BR69: 0 | BS69: 13 | BT69: 20.7 | BU69: 0 | BV69: 0 | BW69: 0 | BX69: 0 | BZ69: 2 | CA69: Excess | CI69: 46186 | CJ69: 14 | CK69: 0 | CL69: 0 | CM69: 0 | CN69: 0 | CO69: 191 | CP69: unassigned | CQ69: N
A70: 46188 | B70: X004MN5N2H | C70: B0DTNYLQ2G | D70: 50US-MaiGanYaZi-001 | E70: ROHSCE Sensory Balls for Babies, Ball for Toddlers 1-3, Wheat Straw Soft & Textured Multi Sensory Baby Toy 6-12 Months Squeeze, Infant Montessori Gift Set for Kids 5 Pack | G70: 0 | H70: -1 | O70: USD | P70: 0 | Q70: 0 | R70: 0 | S70: 0 | U70: 0 | V70: 0 | W70: 0 | X70: 0 | Y70: NoRestockExcessActionRequired | AB70: 0 | AC70: 0 | AE70: -1 | AH70: Standard | AJ70: US | AK70: gl_sports | AM70: 0 | AN70: 0 | AQ70: 19.99 | AR70: 0 | AS70: 0 | AT70: 0 | AU70: 0 | AY70: 0 | BB70: 0 | BC70: 0 | BD70: 0 | BE70: 0 | BG70: 0 | BH70: 0 | BZ70: 1 | CA70: Out of stock | CJ70: 0 | CK70: 0 | CL70: 0 | CM70: 0 | CN70: 0 | CO70: 0 | CP70: unassigned | CQ70: N
A71: 46188 | B71: X002M74JFR | C71: B08FT9HHFL | D71: FBAChunCaiGuanHunHe | E71: Flying Banana 10ml 20 PCS Squeeze Tubes for Lip Gloss,12 PCS Lip Gloss Tubes with Wand Empty, Containers for Lip Gloss Cosmetic with syringe sticker | G71: 0 | H71: -1 | O71: USD | U71: 0 | V71: 0 | W71: 0 | X71: 0 | Y71: NoRestockExcessActionRequired | AB71: 0 | AC71: 0 | AE71: -1 | AH71: Standard | AJ71: US | AK71: gl_beauty | AN71: 0 | AQ71: 16.99 | AY71: 0 | BB71: 0 | BC71: 0 | BD71: 0 | BE71: 0 | BG71: 0 | BH71: 0 | CJ71: 0 | CK71: 0 | CL71: 0 | CM71: 0 | CN71: 0 | CP71: unassigned | CQ71: N
A72: 46188 | B72: X003RGBQ21 | C72: B0BYVH9CX8 | D72: YaoKongQi Teether10 | E72: ROHSCE Silicone Baby Teether Toys, Remote Control Shape Teething Toys for Babies 6-12 Months Soft Molar Teether Infant Baby Chew Toys Sensory Remote Teether BPA-Free Gifts 2 Pack, Black+White | G72: 0 | H72: -1 | O72: USD | U72: 0 | V72: 0 | W72: 0 | X72: 0 | Y72: NoRestockExcessActionRequired | AB72: 0 | AC72: 0 | AE72: -1 | AH72: Standard | AJ72: US | AK72: gl_baby_product | AM72: 0 | AN72: 0 | AQ72: 4.99 | AY72: 0 | BB72: 0 | BC72: 0 | BD72: 0 | BE72: 0 | BG72: 0 | BH72: 0 | CJ72: 0 | CK72: 0 | CL72: 0 | CM72: 0 | CN72: 0 | CO72: 0 | CP72: unassigned | CQ72: N
A73: 46188 | B73: X003795G4H | C73: B09W3RZZQV | D73: 15yuer | E73: Soft Bionic Fishing Lure - 10 PCS Soft Plastic Swim Baits for Bass, Freshwater & Saltwater Top Water Fishing Lures | G73: 109 | H73: 0 | I73: 128 | J73: 0 | K73: 0 | L73: 0 | M73: 0 | N73: 0 | O73: USD | P73: 11 | Q73: 37 | R73: 72 | S73: 78 | T73: Low traffic | W73: 13.99 | X73: -1 | Y73: NoRestockExcessActionRequired | AA73: 0 | AB73: 0 | AC73: 0 | AD73: 0 | AE73: 1.17 | AF73: 0.01986 | AG73: cubic feet | AH73: Standard | AI73: 2.16474 | AJ73: US | AK73: gl_sports | AL73: 116372 | AM73: 96 | AN73: 0 | AO73: 18 | AP73: 29 | AQ73: 13.99 | AR73: 153.89 | AS73: 556.13 | AT73: 1220.78 | AU73: 1307.37 | AV73: 70 | AW73: 58 | AX73: 0 | AY73: 0 | AZ73: 0 | BA73: 1.51 | BB73: 65 | BC73: 60 | BD73: 0 | BE73: 5 | BG73: 13 | BH73: 0 | BY73: 109 | BZ73: 85 | CA73: Healthy | CD73: 46188 | CE73: Yes | CF73: No | CG73: 109 | CH73: 95.4 | CI73: 46186 | CJ73: 186 | CK73: 12 | CL73: 13 | CM73: 0 | CN73: 0 | CO73: 169 | CP73: unassigned | CQ73: N
A74: 46188 | B74: X0033OR1OT | C74: B09M6DVNWX | D74: Neilian-Bai-1214-FBA | E74: Snap-in Clear Shower Curtain Liner Replacement Hotel Qulity Premium Polyester Waterproof Fabric with Bottom Weighted Magnets to stable for Bathroom and Bathtub - Machine Washable 70 x 54 inch | G74: 0 | H74: -1 | O74: USD | U74: 0 | V74: 0 | W74: 0 | X74: 0 | Y74: NoRestockExcessActionRequired | AB74: 0 | AC74: 0 | AE74: -1 | AH74: Standard | AJ74: US | AK74: gl_home | AN74: 0 | AQ74: 19.99 | AY74: 0 | BB74: 0 | BC74: 0 | BD74: 0 | BE74: 0 | BG74: 0 | BH74: 0 | CJ74: 0 | CK74: 0 | CL74: 0 | CM74: 0 | CN74: 0 | CP74: unassigned | CQ74: N
A75: 46188 | B75: X002O92CVV | C75: B08FRGNGGZ | D75: YuLian-02-FBA | E75: ROHSCE Hookless Shower Curtain Set with Snap-in Liner, 250GSM Waffle Weave Fabric, Hotel Grade, Mesh Window, Weighted Hem, 72x74 Inch - Black | F75: New | G75: 7 | H75: -1 | O75: USD | P75: 2 | Q75: 9 | R75: 13 | S75: 22 | U75: 46.99 | V75: 33.99 | W75: 0 | X75: 0 | Y75: GoToRestock | AA75: 0 | AB75: 0 | AC75: 0 | AD75: 0 | AE75: -1 | AH75: Standard | AJ75: US | AK75: gl_home | AL75: 1351087 | AM75: 30 | AN75: 0 | AO75: 5 | AP75: 7 | AQ75: 33.99 | AR75: 67.98 | AS75: 305.91 | AT75: 425.87 | AU75: 693.91 | AY75: 0 | BA75: 0.7 | BB75: 5 | BC75: 5 | BD75: 0 | BE75: 0 | BG75: 1 | BH75: 0 | BY75: 68.6 | CD75: 46188 | CE75: Yes | CF75: No | CG75: 26.4 | CH75: 68.6 | CJ75: 12 | CK75: 0 | CL75: 1 | CM75: 0 | CN75: 0 | CO75: 53 | CQ75: N
A76: 46188 | B76: X004MN5N2R | C76: B0DTP4VV5V | D76: 50US-MaiGanYaZi-005 | E76: ROHSCE Baby Stacking Cups & Sensory Ball Set, Textured Sensory Toys for Babies, Soft Castle Nesting Blocks, Newborn Teether & Bath Toys 6-12 Months, 8 PCS Montessori Learning Gifts for Toddlers 1-3 | F76: New | G76: 18 | H76: 0 | I76: 0 | J76: 18 | K76: 0 | L76: 0 | M76: 0 | N76: 0 | O76: USD | P76: 2 | Q76: 3 | R76: 5 | S76: 9 | T76: Low traffic | U76: 29.99 | V76: 0 | W76: 29.99 | X76: 0 | Y76: NoExcessInventory | AA76: 0 | AB76: 0 | AC76: 0 | AD76: 190.88 | AE76: 0.4 | AF76: 0.06475 | AG76: cubic feet | AH76: Standard | AI76: 1.1655 | AJ76: US | AK76: gl_sports | AM76: 200 | AN76: 0 | AO76: 24 | AP76: 26 | AQ76: 20.39 | AR76: 39.59 | AS76: 59.98 | AT76: 100.76 | AU76: 195.52 | AV76: 0 | AW76: 0 | AX76: 0 | AY76: 0 | AZ76: 0 | BA76: 0.83 | BB76: 0 | BC76: 0 | BD76: 0 | BE76: 0 | BG76: 0 | BH76: 0 | BY76: 309 | BZ76: 7 | CA76: Healthy | CD76: 46188 | CE76: Yes | CF76: No | CG76: 309 | CH76: 251.9 | CI76: 46186 | CJ76: 18 | CK76: 0 | CL76: 0 | CM76: 0 | CN76: 0 | CO76: 200 | CP76: unassigned | CQ76: N
A77: 46188 | B77: X0053FICH1 | C77: B0GYNV85ZW | D77: 50US-LadybugR-05 | E77: Interactive Ladybug Rattle Toy for Babies – LED Lights & Music with Colorful Rings – Ideal for 3-24 Month Infants – Fine Motor Development Toy with Engaging Sounds | G77: 0 | H77: -1 | O77: USD | U77: 0 | V77: 0 | W77: 0 | X77: 0 | Y77: NoRestockExcessActionRequired | AB77: 0 | AC77: 0 | AE77: -1 | AH77: Standard | AJ77: US | AK77: gl_baby_product | AN77: 0 | AY77: 0 | BB77: 0 | BG77: 0 | BH77: 0 | CJ77: 0 | CK77: 0 | CL77: 0 | CM77: 0 | CN77: 0 | CP77: unassigned | CQ77: N
A78: 46188 | B78: X003345V8R | C78: B09MB4RN1R | D78: 50-SL-30Sshalou-002 | E78: Flying Banana 30 Seconds Sandglass Sand Clock Timers Time Saver Game Timer Toy Gift for Kids Random | G78: 0 | H78: -1 | O78: USD | U78: 0 | V78: 0 | W78: 0 | X78: 0 | Y78: NoRestockExcessActionRequired | AB78: 0 | AC78: 0 | AE78: -1 | AJ78: US | AK78: gl_toy | AN78: 0 | AY78: 0 | BB78: 0 | BG78: 0 | BH78: 0 | CJ78: 0 | CK78: 0 | CL78: 0 | CM78: 0 | CN78: 0 | CP78: unassigned | CQ78: N
A79: 46188 | B79: X00334A4Y3 | C79: B09MB24LCB | D79: 50-FCWH-whitepuzzle-002 | E79: Wooden Face Changing Cube Expressions Matching Block Game Puzzles Cute Building Blocks with Bell Social Board Games for 3+ Years Kids Christmas Birthday Gift | G79: 0 | H79: -1 | O79: USD | U79: 0 | V79: 0 | W79: 0 | X79: 0 | Y79: NoRestockExcessActionRequired | AB79: 0 | AC79: 0 | AE79: -1 | AJ79: US | AK79: gl_toy | AN79: 0 | AY79: 0 | BB79: 0 | BG79: 0 | BH79: 0 | CJ79: 0 | CK79: 0 | CL79: 0 | CM79: 0 | CN79: 0 | CP79: unassigned | CQ79: N
A80: 46188 | B80: X004R78I0R | C80: B0CDGKZK2K | D80: 50US-100SoftBuildingBlocks | E80: ROHSCE 100PCS Baby Blocks Set with Storage Bucket, Building Block Toys STEM Educational Toddler Gifts, Rubber Soft Blocks for Preschool, Sensory Stacking Toys to Improve Creativity | G80: 55 | H80: 0 | I80: 71 | J80: 0 | K80: 0 | L80: 0 | M80: 0 | N80: 0 | O80: USD | P80: 4 | Q80: 20 | R80: 41 | S80: 76 | W80: 51.99 | X80: -1 | Y80: NoRestockExcessActionRequired | AA80: 0 | AB80: 0 | AC80: 0 | AD80: 0 | AE80: 1.44 | AF80: 0.792969 | AG80: cubic feet | AH80: Oversize | AI80: 43.613295 | AJ80: US | AK80: gl_biss | AL80: 26497 | AM80: 56 | AN80: 0 | AO80: 15 | AP80: 13 | AQ80: 51.99 | AR80: 207.96 | AS80: 1057.8 | AT80: 2107.5 | AU80: 3857.04 | AV80: 71 | AW80: 0 | AX80: 0 | AY80: 0 | AZ80: 0 | BA80: 22.57 | BB80: 22 | BC80: 16 | BD80: 0 | BE80: 6 | BG80: 6 | BH80: 6 | BY80: 55 | BZ80: 51 | CA80: Healthy | CD80: 46188 | CE80: Yes | CF80: No | CG80: 55 | CH80: 42.2 | CI80: 46186 | CJ80: 85 | CK80: 8 | CL80: 6 | CM80: 0 | CN80: 0 | CO80: 75 | CP80: unassigned | CQ80: N
A81: 46188 | B81: X004FT1CDR | C81: B0CW9GKWSL | D81: 50GuiJiaoDieLe-Pink | E81: ROHSCE Silicone Stacking Toys for Babies, Rainbow Stacker, Montessori Nesting Blocks Soft Building Toys Large Sensory Stacking Toys for Creative Play & Learning, for Toddlers, 7CPS | G81: 23 | H81: -1 | O81: USD | P81: 6 | Q81: 13 | R81: 30 | S81: 46 | W81: -1 | X81: -1 | Y81: NoRestockExcessActionRequired | AA81: 0 | AB81: 0 | AC81: 0 | AD81: 0 | AE81: -1 | AH81: Standard | AJ81: US | AK81: gl_toy | AM81: 29 | AN81: 0 | AO81: 23 | AP81: 21 | AQ81: 12.99 | AR81: 86.74 | AS81: 197.87 | AT81: 473.7 | AU81: 751.94 | AY81: 0 | BA81: 0.23 | BB81: 53 | BC81: 53 | BD81: 0 | BE81: 0 | BG81: 3 | BH81: 0 | BY81: 78.3 | BZ81: 41 | CA81: Low stock | CB81: 5 | CC81: 46195 | CD81: 46188 | CE81: Yes | CF81: No | CG81: 78.3 | CH81: 63.1 | CJ81: 77 | CK81: 1 | CL81: 3 | CM81: 0 | CN81: 0 | CO81: 88 | CP81: unassigned | CQ81: N
A82: 46188 | B82: X0046NFKCV | C82: B0CDLWP5HK | D82: 50-cailansedashuiqiang-5HK | E82: ROHSCE Electric Water Gun for Kids, Automatic Squirt Guns 32FT Long Range, Powerful Auto Water Absorption, Modular High Battery Powered, Summer Pool Beach Outdoor Game Toys for Kids Age 8-12 | G82: 0 | H82: -1 | O82: USD | U82: 0 | V82: 0 | W82: 0 | X82: 0 | Y82: NoRestockExcessActionRequired | AB82: 0 | AC82: 0 | AE82: -1 | AH82: Standard | AJ82: US | AK82: gl_toy | AM82: 0 | AN82: 0 | AQ82: 38.99 | AY82: 0 | BB82: 0 | BC82: 0 | BD82: 0 | BE82: 0 | BG82: 0 | BH82: 0 | CJ82: 0 | CK82: 0 | CL82: 0 | CM82: 0 | CN82: 0 | CO82: 0 | CP82: unassigned | CQ82: N
A83: 46188 | B83: X003DYF9PH | C83: B0BDF7CTWP | D83: jimuSZQdiequan-01 | E83: Baby Toys 6 to 12 Months, Soft Building Blocks & Baby Sensory Balls & Stacking Rings, 3 in 1 Montessori Toys for 1 Year Old, Educational Infant Toys, Baby Sensory Toys for Toddler 1-3, Learning Toys | G83: 0 | H83: -1 | O83: USD | U83: 0 | V83: 0 | W83: 0 | X83: 0 | Y83: NoRestockExcessActionRequired | AB83: 0 | AC83: 0 | AE83: -1 | AH83: Standard | AJ83: US | AK83: gl_baby_product | AN83: 0 | AQ83: 27.99 | AY83: 0 | BB83: 0 | BC83: 0 | BD83: 0 | BE83: 0 | BG83: 0 | BH83: 0 | CJ83: 0 | CK83: 0 | CL83: 0 | CM83: 0 | CN83: 0 | CP83: unassigned | CQ83: N
A84: 46188 | B84: X004TC2W5H | C84: B0FMXV3JBC | D84: 50US-DuiDieKongLong-007 | E84: ROHSCE 2-in-1 Rainbow Stacker & Pull-Along Chameleon Toy for Toddlers 18-36 Months, Montessori-Inspired Nesting Arch Stacking Toy, Push & Pull Sensory Learning Toy, Christmas Birthday Gift | F84: New | G84: 22 | H84: 0 | I84: 0 | J84: 0 | K84: 22 | L84: 0 | M84: 0 | N84: 0 | O84: USD | T84: Low traffic | U84: 36.99 | V84: 0 | W84: 29.59 | X84: 12.05 | Y84: Create removal order | AA84: 0 | AB84: 0 | AC84: 0 | AD84: 1105.36 | AE84: 0 | AF84: 0.199302 | AG84: cubic feet | AH84: Standard | AI84: 4.384644 | AJ84: US | AK84: gl_toy | AN84: 22 | AQ84: 29.59 | AV84: 0 | AW84: 0 | AX84: 0 | AY84: 22 | AZ84: 0 | BA84: 24.65 | BB84: 0 | BC84: 0 | BD84: 0 | BE84: 0 | BF84: 22 | BG84: 1 | BH84: 0 | BI84: 0 | BJ84: 0 | BK84: 0 | BL84: 0 | BM84: 22 | BN84: 6.6 | BO84: 0 | BP84: 0 | BQ84: 0 | BR84: 0 | BS84: 0 | BT84: 0 | BU84: 0 | BV84: 0 | BW84: 0 | BX84: 0 | CA84: Excess | CI84: 46186 | CJ84: 22 | CK84: 0 | CL84: 1 | CM84: 0 | CN84: 0 | CP84: unassigned | CQ84: N
A85: 46188 | B85: X003HYWYY7 | C85: B0BLK8TLVM | D85: YaokongYueyeche-004 | E85: Remote Control Car, 2.4GHz All Terrain Off-Road RC Stunt Cars with Inflatable Wheels, Rechargeable Batteries for 1 Hour Play, Glow Up RC Truck Toys for Boys Kids Age 4-7 8-12 Birthday Charisma Gift | G85: 0 | H85: -1 | O85: USD | U85: 0 | V85: 0 | W85: 0 | X85: 0 | Y85: NoRestockExcessActionRequired | AB85: 0 | AC85: 0 | AE85: -1 | AH85: Standard | AJ85: US | AK85: gl_toy | AM85: 0 | AN85: 0 | AQ85: 32.9 | AY85: 0 | BB85: 0 | BC85: 0 | BD85: 0 | BE85: 0 | BG85: 0 | BH85: 0 | CJ85: 0 | CK85: 0 | CL85: 0 | CM85: 0 | CN85: 0 | CO85: 0 | CP85: unassigned | CQ85: N
A86: 46188 | B86: X003IXZ8FT | C86: B0BMXFZYLJ | D86: diediele-03 | E86: ROHSCE 6 Pcs Stacking Rings Soft Toys for Babies 6 Months and up Toddlers Sensory Educational Montessori Baby Blocks Developmental Teething Learning Stacker Girls Boys | G86: 0 | H86: -1 | O86: USD | U86: 0 | V86: 0 | W86: 0 | X86: 0 | Y86: NoRestockExcessActionRequired | AB86: 0 | AC86: 0 | AE86: -1 | AH86: Standard | AJ86: US | AK86: gl_toy | AN86: 0 | AQ86: 5.99 | AY86: 0 | BB86: 0 | BC86: 0 | BD86: 0 | BE86: 0 | BG86: 0 | BH86: 0 | CJ86: 0 | CK86: 0 | CL86: 0 | CM86: 0 | CN86: 0 | CP86: unassigned | CQ86: N
A87: 46188 | B87: X0046NXNL1 | C87: B0CDLW4ZCT | D87: 50-baisedahongseshuiqiang-ZCT | E87: ROHSCE Electric Water Gun, Powerful Automatic Squirt Guns, Long Range Classic Big Electronic Watergun, Electric Squirt Gun Water Blaster Toy for Kids Adults, Summer Pool Beach Outdoor Game Toys | G87: 0 | H87: -1 | O87: USD | U87: 0 | V87: 0 | W87: 0 | X87: 0 | Y87: NoRestockExcessActionRequired | AB87: 0 | AC87: 0 | AE87: -1 | AH87: Standard | AJ87: US | AK87: gl_toy | AM87: 0 | AN87: 0 | AQ87: 23.79 | AY87: 0 | BB87: 0 | BC87: 0 | BD87: 0 | BE87: 0 | BG87: 0 | BH87: 0 | CJ87: 0 | CK87: 0 | CL87: 0 | CM87: 0 | CN87: 0 | CO87: 0 | CP87: unassigned | CQ87: N
A88: 46188 | B88: X003F49WNP | C88: B0BGKRJGPZ | D88: HuoJian-Hei | E88: ROHSCE Rocket Launcher for Kids 8-12, Electric Powered Toy Launcher, Motorized Air Toys with Parachute Outdoor Toys for Kids Ages 6-8, Launch up to 250 ft Birthday Gift… | G88: 0 | H88: -1 | O88: USD | P88: 0 | Q88: 0 | R88: 0 | S88: 0 | U88: 0 | V88: 0 | W88: 0 | X88: 0 | Y88: NoRestockExcessActionRequired | AB88: 0 | AC88: 0 | AE88: -1 | AH88: Standard | AJ88: US | AK88: gl_toy | AM88: 0 | AN88: 0 | AQ88: 39.99 | AR88: 0 | AS88: 0 | AT88: 0 | AU88: 0 | AY88: 0 | BB88: 0 | BC88: 0 | BD88: 0 | BE88: 0 | BG88: 0 | BH88: 0 | BZ88: 1 | CA88: Out of stock | CB88: 1 | CC88: 46186 | CJ88: 0 | CK88: 0 | CL88: 0 | CM88: 0 | CN88: 0 | CO88: 0 | CP88: unassigned | CQ88: N
A89: 46188 | B89: X004JNA3J3 | C89: B0CCJLXS14 | D89: TouMingZiFengRen | E89: Flying Banana Mini Sewing Machine for Beginners Kids, Portable Electric Dual Speed Repairing Mending Tool with Light Foot Pedal, Household Travel DIY Kit, Transparent Purple | F89: New | G89: 18 | H89: 0 | I89: 0 | J89: 18 | K89: 0 | L89: 0 | M89: 0 | N89: 0 | O89: USD | P89: 0 | Q89: 0 | R89: 0 | S89: 0 | T89: Low traffic | U89: 55.54 | V89: 41.99 | W89: 41.99 | X89: 0 | Y89: Advertise listing | AA89: 0 | AB89: 0 | AC89: 0 | AD89: 1526.02 | AE89: 0 | AF89: 0.314972 | AG89: cubic feet | AH89: Standard | AI89: 5.669496 | AJ89: US | AK89: gl_home | AM89: 366 | AN89: 18 | AQ89: 41.99 | AR89: 0 | AS89: 0 | AT89: 0 | AU89: 0 | AV89: 0 | AW89: 0 | AX89: 0 | AY89: 0 | AZ89: 0 | BA89: 4.05 | BB89: 0 | BC89: 0 | BD89: 0 | BE89: 0 | BG89: 1 | BH89: 0 | CA89: Excess | CI89: 46186 | CJ89: 18 | CK89: 0 | CL89: 1 | CM89: 0 | CN89: 0 | CO89: 366 | CP89: unassigned | CQ89: N
A90: 46188 | B90: X0045PK07Z | C90: B0CT5SFK7T | D90: NewBabyBall 0007 | E90: ROHSCE Baby Sensory Balls, 6PCS Soft Textured Spiky Bath Toys 6M+ | F90: New | G90: 10 | H90: 0 | I90: 1 | J90: 9 | K90: 0 | L90: 0 | M90: 0 | N90: 0 | O90: USD | P90: 1 | Q90: 2 | R90: 3 | S90: 11 | U90: 39.99 | V90: 31.99 | W90: 31.99 | X90: 0 | Y90: CreateShippingPlan | AA90: 0 | AB90: 0 | AC90: 0 | AD90: 0 | AE90: 0.32 | AF90: 0.266389 | AG90: cubic feet | AH90: Standard | AI90: 2.66389 | AJ90: US | AK90: gl_toy | AL90: 2409 | AM90: 30 | AN90: 0 | AO90: 20 | AP90: 11 | AQ90: 31.99 | AR90: 31.99 | AS90: 63.48 | AT90: 95.47 | AU90: 383.39 | AV90: 0 | AW90: 0 | AX90: 1 | AY90: 0 | AZ90: 0 | BA90: 1.56 | BB90: 0 | BC90: 0 | BD90: 0 | BE90: 0 | BG90: 0 | BH90: 0 | BY90: 164.5 | BZ90: 11 | CA90: Low stock | CB90: 11 | CC90: 46193 | CD90: 46188 | CE90: Yes | CF90: No | CG90: 164.5 | CH90: 110.5 | CI90: 46186 | CJ90: 10 | CK90: 0 | CL90: 0 | CM90: 0 | CN90: 0 | CO90: 30 | CP90: unassigned | CQ90: N
A91: 46188 | B91: X0047HWYC5 | C91: B0CRDMC78Z | D91: 50DaHaoLanWaWaJi-78Z | E91: ROHSCE Mini Claw Machine for Kids | Electric Vending Machine Toy Arcade Game Toy with Mini Prizes, Candy Claw Machine Toys Adjustable Sound and Music, Birthday Gifts for Girls | G91: 0 | H91: -1 | O91: USD | U91: 0 | V91: 0 | W91: 0 | X91: 0 | Y91: NoRestockExcessActionRequired | AB91: 0 | AC91: 0 | AE91: -1 | AJ91: US | AK91: gl_toy | AL91: 804557 | AN91: 0 | AQ91: 81.69 | AY91: 0 | BB91: 0 | BG91: 0 | BH91: 0 | CJ91: 0 | CK91: 0 | CL91: 0 | CM91: 0 | CN91: 0 | CP91: unassigned | CQ91: N
A92: 46188 | B92: X004V6TWRH | C92: B0CN1BW4C7 | D92: NewHuoJian-200FT | E92: Rocket Launcher, 170 Feet of Flight Altitude, Model Rocket Kits with Launch Set, Rocket Toy, Kids Outdoor Toys, Gift for Kids Ages 8-12 Children's Day Gift | G92: 0 | H92: -1 | O92: USD | U92: 0 | V92: 0 | W92: 0 | X92: 0 | Y92: NoRestockExcessActionRequired | AB92: 0 | AC92: 0 | AE92: -1 | AH92: Standard | AJ92: US | AK92: gl_toy | AN92: 0 | AY92: 0 | BB92: 0 | BG92: 0 | BH92: 0 | CJ92: 0 | CK92: 0 | CL92: 0 | CM92: 0 | CN92: 0 | CP92: unassigned | CQ92: N
A93: 46188 | B93: X004QTLDU3 | C93: B0DTTJ2PNV | D93: 50US-GenSuiYa-002 | E93: ROHSCE Duck Tummy Time Toys Set, Crawling Baby Toy with Music and Light,Musical Toys for Toddlers 1-3, Duck Toy for Learning Crawl, Christmas Birthday Gift for Boys Girls | G93: 0 | H93: -1 | O93: USD | P93: 0 | Q93: 0 | R93: 0 | S93: 0 | U93: 0 | V93: 0 | W93: 0 | X93: 0 | Y93: NoRestockExcessActionRequired | AB93: 0 | AC93: 0 | AE93: -1 | AH93: Standard | AJ93: US | AK93: gl_toy | AM93: 0 | AN93: 0 | AQ93: 32.39 | AR93: 0 | AS93: 0 | AT93: 0 | AU93: 0 | AY93: 0 | BB93: 0 | BC93: 0 | BD93: 0 | BE93: 0 | BG93: 0 | BH93: 0 | BZ93: 1 | CA93: Out of stock | CJ93: 0 | CK93: 0 | CL93: 0 | CM93: 0 | CN93: 0 | CO93: 0 | CP93: unassigned | CQ93: N
A94: 46188 | B94: X003416GER | C94: B09P47QVR2 | D94: TaiYanGuaTan-2022 | E94: Flying Banana Sun and Moon Tapestry, Burning Sun with Stars Psychedelic Popular Mystic Wall Hanging Tapestry For Bedroom Aesthetic (78.7 x 59in) | G94: 0 | H94: -1 | O94: USD | U94: 0 | V94: 0 | W94: 0 | X94: 0 | Y94: NoRestockExcessActionRequired | AB94: 0 | AC94: 0 | AE94: -1 | AH94: Standard | AJ94: US | AK94: gl_home | AN94: 0 | AQ94: 14.99 | AY94: 0 | BB94: 0 | BC94: 0 | BD94: 0 | BE94: 0 | BG94: 0 | BH94: 0 | CJ94: 0 | CK94: 0 | CL94: 0 | CM94: 0 | CN94: 0 | CP94: unassigned | CQ94: N
A95: 46188 | B95: X002LYPIWJ | C95: B08FDP1X8N | D95: TaiYangGuaTanZsUs-5001 | E95: Sun and Moon Tapestry, Burning Sun with Stars Psychedelic Popular Mystic Wall Hanging Tapestry For Bedroom Aesthetic (78.7 x 59in) | G95: 0 | H95: -1 | O95: USD | U95: 0 | V95: 0 | W95: 0 | X95: 0 | Y95: NoRestockExcessActionRequired | AB95: 0 | AC95: 0 | AE95: -1 | AH95: Standard | AJ95: US | AK95: gl_home | AN95: 0 | AQ95: 8.29 | AY95: 0 | BB95: 0 | BC95: 0 | BD95: 0 | BE95: 0 | BG95: 0 | BH95: 0 | CJ95: 0 | CK95: 0 | CL95: 0 | CM95: 0 | CN95: 0 | CP95: unassigned | CQ95: N
A96: 46188 | B96: X0045P95Q7 | C96: B0BLHJ5G3N | D96: SZQchuxu-02 | E96: ROHSCE Sensory Balls for Toddlers 1-3, Montessori Toys for Babies 6-12 Months, Easter Baby Toys, Sensory Balls for Easter Basket, BPA Free Teething Gift, Toddler Bath Toys with Multi Textured | G96: 0 | H96: -1 | O96: USD | P96: 0 | Q96: 0 | R96: 0 | S96: 0 | U96: 0 | V96: 0 | W96: 0 | X96: 0 | Y96: NoRestockExcessActionRequired | AB96: 0 | AC96: 0 | AE96: -1 | AH96: Standard | AJ96: US | AK96: gl_toy | AM96: 0 | AN96: 0 | AQ96: 25.59 | AR96: 0 | AS96: 0 | AT96: 0 | AU96: 0 | AY96: 0 | BB96: 0 | BC96: 0 | BD96: 0 | BE96: 0 | BG96: 0 | BH96: 0 | BZ96: 1 | CA96: Out of stock | CJ96: 0 | CK96: 0 | CL96: 0 | CM96: 0 | CN96: 0 | CO96: 0 | CP96: unassigned | CQ96: N
A97: 46188 | B97: X003F4JGO5 | C97: B0BGKTVG8X | D97: HuoJian-Bai | E97: ROHSCE Rocket Launcher, 200 Feet of Flight Altitude, Model Rocket Kits with Launch Set, Rocket Toy with Parachute, Outdoor Toys for Kids Ages 4-8, Gifts for Kids Ages 8-12 | G97: 0 | H97: -1 | O97: USD | U97: 0 | V97: 0 | W97: 0 | X97: 0 | Y97: NoRestockExcessActionRequired | AB97: 0 | AC97: 0 | AE97: -1 | AH97: Standard | AJ97: US | AK97: gl_toy | AM97: 0 | AN97: 0 | AQ97: 20.99 | AY97: 0 | BB97: 0 | BC97: 0 | BD97: 0 | BE97: 0 | BG97: 0 | BH97: 0 | CJ97: 0 | CK97: 0 | CL97: 0 | CM97: 0 | CN97: 0 | CO97: 0 | CP97: unassigned | CQ97: N
A98: 46188 | B98: X0051KHYG3 | C98: B0GJYRXJJC | D98: 50US-4PCSTankLunZi-002 | E98: ROHSCE Black Set of 4 RC Stunt Car Replacement Wheels, Compatible Durable Spare Tire Kit for Kids Remote Control Toy Vehicle Repair, Easy-Install RC Car Accessories Parts | F98: New | G98: 20 | H98: 0 | I98: 20 | J98: 0 | K98: 0 | L98: 0 | M98: 0 | N98: 0 | O98: USD | T98: Low conversion | U98: 38.99 | V98: 0 | W98: 31.99 | X98: 0 | Y98: Lower price | AA98: 0 | AB98: 0 | AC98: 0 | AD98: 0 | AE98: 0 | AF98: 0.139028 | AG98: cubic feet | AH98: Standard | AI98: 2.78056 | AJ98: US | AK98: gl_toy | AL98: 206385 | AM98: 144 | AN98: 0 | AQ98: 31.99 | AV98: 0 | AW98: 20 | AX98: 0 | AY98: 0 | AZ98: 0 | BA98: 1.99 | BB98: 0 | BC98: 0 | BD98: 0 | BE98: 0 | BG98: 0 | BH98: 0 | CI98: 46186 | CJ98: 20 | CK98: 0 | CL98: 0 | CM98: 0 | CN98: 0 | CO98: 144 | CP98: unassigned | CQ98: N
A99: 46188 | B99: X0051RPOVD | C99: B0GJZ4Z1LY | D99: 50US-RuanDanTankFaSheTou-02 | E99: ROHSCE Green Foam Dart Launcher Attachment for RC Toy Vehicle, Soft Dart Shooter Replacement Module for Remote Control Stunt Car, Kids RC Car Accessory Spare Part | F99: New | G99: 20 | H99: 0 | I99: 20 | J99: 0 | K99: 0 | L99: 0 | M99: 0 | N99: 0 | O99: USD | T99: Low conversion | U99: 39.99 | V99: 0 | W99: 23.99 | X99: 0 | Y99: Lower price | AA99: 0 | AB99: 0 | AC99: 0 | AD99: 546.59 | AE99: 0 | AF99: 0.153854 | AG99: cubic feet | AH99: Standard | AI99: 3.07708 | AJ99: US | AK99: gl_toy | AL99: 206385 | AM99: 142 | AN99: 0 | AQ99: 23.99 | AV99: 0 | AW99: 20 | AX99: 0 | AY99: 0 | AZ99: 0 | BA99: 2.2 | BB99: 0 | BC99: 0 | BD99: 0 | BE99: 0 | BG99: 0 | BH99: 0 | CI99: 46186 | CJ99: 20 | CK99: 0 | CL99: 0 | CM99: 0 | CN99: 0 | CO99: 142 | CP99: unassigned | CQ99: N
A100: 46188 | B100: X004ETS4YX | C100: B0GFMRGFXW | D100: 50-LvHeGunZhu-PQ8 | E100: Glow in The Dark Marble Run 325 Piece Set Motorized Elevator STEM Maze Construction Blocks Kids Ages 3 Plus Easter Birthday Gift Boys Girls | F100: New | G100: 4 | H100: 0 | I100: 0 | J100: 0 | K100: 0 | L100: 4 | M100: 0 | N100: 0 | O100: USD | P100: 0 | Q100: 1 | R100: 1 | S100: 2 | T100: Low traffic | U100: 119.99 | V100: 0 | W100: 93.99 | X100: 0 | Y100: Lower price | AA100: 0 | AB100: 0 | AC100: 0 | AD100: 1059.44 | AE100: 0.4 | AF100: 0.872762 | AG100: cubic feet | AH100: Oversize | AI100: 3.491048 | AJ100: US | AK100: gl_toy | AL100: 792639 | AM100: 55 | AN100: 0 | AO100: 32 | AP100: 52 | AQ100: 93.99 | AR100: 0 | AS100: 93.99 | AT100: 93.99 | AU100: 187.98 | AV100: 0 | AW100: 0 | AX100: 0 | AY100: 4 | AZ100: 0 | BA100: 22.9 | BB100: 4 | BC100: 4 | BD100: 0 | BE100: 0 | BG100: 0 | BH100: 0 | BI100: 0 | BJ100: 0 | BK100: 0 | BL100: 0 | BM100: 0 | BN100: 0 | BO100: 0 | BP100: 0 | BQ100: 4 | BR100: 19.89 | BS100: 0 | BT100: 0 | BU100: 0 | BV100: 0 | BW100: 0 | BX100: 0 | BY100: 216.5 | BZ100: 10 | CA100: Low stock | CD100: 46188 | CE100: Yes | CF100: No | CG100: 128 | CH100: 216.5 | CI100: 46186 | CJ100: 8 | CK100: 0 | CL100: 0 | CM100: 0 | CN100: 0 | CO100: 113 | CP100: unassigned | CQ100: N
...

Sheet Sheet3
B8: 50等级 | G8: 149
B10: B07SRSJZSL | C10: B07SRSJZSL | D10: SS | G10: 149US-PinkNiuDanJi | H10: X004U9OXE7 | I10: B0CRDL2HD6 | J10: S
B11: B07SVYD7RV B07SX1K48R | C11: B07SVYD7RV | D11: SS | G11: 149US-SoftCiLiGuan26P-007 | H11: X004UB6DNT | I11: B0FHPSR92X | J11: A
B12: B08J3MZQ2M | C12: B08J3MZQ2M | D12: SS | G12: ZiMuYouXi-0002 | H12: X004UBDOYZ | I12: B0FMK6V5N6 | J12: A
B13: B0B9N5PX8H | C13: B0B9N5PX8H | D13: SS | G13: 149US-Chibang-devil | H13: X004UT0YYP | I13: B0F23T2MLJ
B14: B0BLHXCYWM B0DPSZLZNL | C14: B0BLHXCYWM | D14: SS
B15: B08FM4LMWR | C15: B08FM4LMWR | D15: SS | G15: 149-KeHuanWanJvQiang-001 | H15: X004TJJJ8X | I15: B0FHPVDGBQ | J15: P
B16: B0BLHZLLK6 B0DPSZLZNL | C16: B0BLHZLLK6 | D16: SS | G16: 149US-22TuZiMaoXianJi-NEW | H16: X004ZG26M1 | I16: B0GGR3FL2X | J16: A
G17: 149-xiaohaohudie-6J7 | H17: X004C26F2F | I17: B0CT8VF6J7 | J17: SS
B18: B0CW9NVMSZ | C18: B0CW9NVMSZ | D18: SS | G18: 149-ChiLunPinTu-GX6 | H18: X004FBT7HD | I18: B0CT5HKGX6 | J18: A
B19: B0CWH2F9MM B0DC3H9K53 | C19: B0CWH2F9MM | D19: SS | G19: 149-shishangnvhai-1GJ | H19: X004EGTBBV | I19: B0DCNWK1GJ | J19: S
B20: B0CJ6NHRQ2 | C20: B0CJ6NHRQ2 | D20: S | G20: 149-niwajiang-0002 | H20: X004EG8HB1 | I20: B0FP52CS55 | J20: S
B21: B0CT5R73WR | C21: B0CT5R73WR | D21: S | G21: 149US-PinkCaiHongWuClaw | H21: X004U9P0AN | I21: B0C5CWSDGX | J21: S
G22: 149US-PinkNiuDanClaw | H22: X004UEQAMP | I22: B0FPC6D218 | J22: S
B23: B0BLKBV7T2 | C23: B0BLKBV7T2 | D23: S
B24: B09W3RZZQV | C24: B09W3RZZQV | D24: A | G24: 149US-XiaoHaoTuZiMaoXianJi | H24: X004ZG6JRJ | I24: B0GGQDW816 | J24: A
B25: B0BDFBXDHP B0BDF8ZFC2 | C25: B0BDFBXDHP | D25: A | G25: 149-Reminxiangji-Pink | H25: X004SQHCWH | I25: B0FHHDCYFL | J25: A
B26: B0838NV866 | C26: B0838NV866 | D26: A | G26: 149HuaRongDaoYellow2 | H26: X004S25IZT | I26: B0F7H2HJ9K | J26: A
B27: B08G4MQP82 B0BW3SH2KR | C27: B08G4MQP82 | D27: SS | G27: HeJinLuoSiJiMu-0002 | H27: X004UBFH8L | I27: B0FK4FYRZJ | J27: A
B28: B0CJ6Q3PV7 | C28: B0CJ6Q3PV7 | D28: A | G28: 149-BlueNiuDanWaWaJi | H28: X004RPX36D | I28: B0CRDNDFLC | J28: SS
B29: B0BDFBYHNQ B0BDF8ZFC2 | C29: B0BDFBYHNQ | D29: A | G29: 149US-HongHeJiMu | H29: X004YTQB0H | I29: B09M8D5Z9S | J29: A
B30: B0CDGK13SD B0DPSZLZNL | C30: B0CDGK13SD | D30: A | G30: 149-YiCheHuaRongDao-1 | H30: X004S1P3E1 | I30: B0F7GZ1D8D | J30: A
B31: B07KD7NDK9 | C31: B07KD7NDK9 | D31: A | G31: ZiMuYouXi-0003 | H31: X004UBLE3D | I31: B0FMK6R2HS | J31: A
B32: B0CJ6P3P9F | C32: B0CJ6P3P9F | D32: A | G32: HeJinLuoSiJiMu-0008 | H32: X004UBFFD3 | I32: B0FK4GKPTM | J32: A
B33: B0BGKRJGPZ B0CRV273M2 | C33: B0BGKRJGPZ | D33: S | G33: 149US-DongWuChiLun | H33: X004MJ8UFN | I33: B0C65SQ3DV | J33: S
B34: B0CDGKTNS9 B0DPSZLZNL | C34: B0CDGKTNS9 | D34: S | G34: 149-qiuqianniwaA10 | H34: X004SJLWUR | I34: B0F1Y548MZ | J34: S
B35: B0CT5TKD1T | C35: B0CT5TKD1T | D35: A | G35: rideontrain 0007 | H35: X004DUX6HN | I35: B0DBZBTLVN | J35: S
... B38: B0CW9GKWSL | C38: B0CW9GKWSL | D38: A | G38: 149-XiShuizhuo-Blue | H38: X004P3IH13 | I38: B0F7FBDB45 | J38: P
B39: B07FR7N4M3 | C39: B07FR7N4M3 | D39: A | G39: 149-Reminxiangji-Blue | H39: X004SQEYNH | I39: B0FHHJXQ5S
B40: B0CDGKZK2K B0DPSZLZNL | C40: B0CDGKZK2K | D40: S | G40: 149-XiaoMaoXianJiGHY | H40: X004JP5I1T | I40: B0CYLWKGHY | J40: A
B41: B09NM5CQQQ | C41: B09NM5CQQQ | D41: P | G41: 149-ZiMuCiXiPinTu | H41: X004W3GUK1 | I41: B0DCNTP1H2 | J41: A
B42: B0BLHZG8SC B0C6Y1SM14 | C42: B0BLHZG8SC | D42: P | G42: ZiSeHuDieQun-1B | H42: X004OUF72J | I42: B0F23NNP4T | J42: S
B43: B0CQXJ37CQ | C43: B0CQXJ37CQ | D43: P | G43: 149US-8JianTaoBingXiangChiLun | H43: X004P3UUXV | I43: B0CT5J8GCW | J43: A
B44: B0CJ6NGP6S | C44: B0CJ6NGP6S | D44: A | G44: 149US-TaiKongChiLun | H44: X004MJ8MPB | I44: B0CT4YRY12 | J44: S
G45: 149BlueHuaZhuangBao-1 | H45: X004S5PNOH | I45: B0FDKRP2YL | J45: A
B46: B0CT5PL82Y | C46: B0CT5PL82Y | D46: P | G46: 149US-QiEMaoXianJi | H46: X004YLQ1KP | I46: B0FP53G22D | J46: A
B47: B0CW92T86K | C47: B0CW92T86K | D47: A | G47: 149-DaHaoWings-GM1 | H47: X004CW5O09 | I47: B0CT8SCGM1 | J47: S
B48: B0C5CBPHJS | C48: B0C5CBPHJS | D48: P | G48: 149-C-QiuQianWu | H48: X004J3H9ZT | I48: B0FPC7T521 | J48: ss
B49: B0CJ4MPLVD | C49: B0CJ4MPLVD | D49: P | G49: 149US-KongLongChiLUN | H49: X004MJD9JP | I49: B0CT5FS8YV | J49: S
B50: B0CJ5B2DXY B0CGTXZQWW | C50: B0CJ5B2DXY | D50: A | G50: 149-GuDianniwaA20 | H50: X004SJLFX1 | I50: B0F1Y6LC4H | J50: S
B51: B0C5BXVK9W | C51: B0C5BXVK9W | D51: P | G51: 149-ZhuangYuanNiWa-MMA02 | H51: X004SQL93P | I51: B0F1Y6TTSD | J51: ss
B52: B0DDHBTLWL | C52: B0DDHBTLWL | D52: A | G52: 149-BlueLuDengPaoPaoJi | H52: X004P3UFUJ | I52: B0D9M4GCQW | J52: A
B53: B0CTQDF5Q9 | C53: B0CTQDF5Q9 | D53: P | G53: 149-QiShiNiwajiang | H53: X004OF4L85 | I53: B0F1Y4DF87 | J53: S
G54: HeJinLuoSiJiMu-0007 | H54: X004UBJ2GT | I54: B0FK4GLJ7R | J54: A
B55: B07SX1T3JQ B0BQHP5PWH | C55: B07SX1T3JQ | D55: P | G55: 149-BiaoqingCixipintu | H55: X004PY9M07 | I55: B0DCNT2LNJ | J55: ss
B56: B0CWH32QZD B0DC3H9K53 | C56: B0CWH32QZD | D56: A | G56: 149US-ShouBiPaoPaoJi | H56: X004P3R61F | I56: B0CBWPNDQ6 | J56: S
B57: B0BLHJ5G3N | C57: B0BLHJ5G3N | D57: P | G57: 149-ZiSeHudiequn4B | H57: X004PABQXR | I57: B0F23RML5V | J57: S
B58: B0CQX71441 | C58: B0CQX71441 | D58: P | G58: 149-TaoYiJi-Pink | H58: X004Q1ODFD | I58: B0F29BGKS2 | J58: A
B59: B0BDDFFSG5 | C59: B0BDDFFSG5 | D59: P | G59: 149BlueHuaZhuangBao-2 | H59: X004S5TCC1 | I59: B0FDKPRJQ4 | J59: A
B60: B0CQ86MX8N B0F1FJ9NH2 | C60: B0CQ86MX8N | D60: P | G60: HeJinLuoSiJiMu-0001 | H60: X004UBJ0CZ | I60: B0FK4GLSNM | J60: A
B61: B0CTQG25QM B0D3129FS8 | C61: B0CTQG25QM | D61: P | G61: 149-Greentaoyiji | H61: X004Q9FOHL | I61: B0F299WYTQ | J61: A
B62: B08FRGNGGZ | C62: B08FRGNGGZ | D62: S | G62: 149-MaoXianJi-261 | H62: X004E6XMWP | I62: B0CYLVJ261 | J62: A
B63: B0CW14MNVM | C63: B0CW14MNVM | D63: A | I63: B0FPC7T521 | J63: S
B65: B0CW97PJZS | C65: B0CW97PJZS | D65: A
B66: B0CDGNFQMH B0DPSZLZNL | C66: B0CDGNFQMH | D66: S
B67: B0CVZVND5J B0D3LQPMM2 | C67: B0CVZVND5J | D67: A
B68: B0CT5SFK7T | C68: B0CT5SFK7T | D68: P
B69: B0BRQ62T5C B0BW3SH2KR | C69: B0BRQ62T5C | D69: P
B70: B0CT5R73WS B0DR5MLBCT | C70: B0CT5R73WS | D70: P
B71: B0CCDNZ6PR B0CJFCSM1F | C71: B0CCDNZ6PR | D71: S
B72: B07SX1T3JQ | C72: B07SX1T3JQ | D72: P
B74: B0CN19YZZ3 B0CRV273M2 | C74: B0CN19YZZ3 | D74: S
B75: B0CT57RMJT | C75: B0CT57RMJT | D75: P
B76: B0CQ7TDQCD | C76: B0CQ7TDQCD | D76: P
B78: B0CT59952T | C78: B0CT59952T | D78: P | H78: claw machine
B79: B0CCJL21G7 | C79: B0CCJL21G7 | D79: P | H79: claw machine for kid
B80: B091DL6GQ5 B0C32HHPFM | C80: B091DL6GQ5 | D80: P
B81: B0DHL1HN7W | C81: B0DHL1HN7W | D81: A
B83: B0D3KMVZKK | C83: B0D3KMVZKK | D83: A
B86: B08KT79KJG B0BW47WJ2K | C86: B08KT79KJG | D86: P
B87: B0F3CW7D6M | C87: B0F3CW7D6M | D87: P
B88: B0FHKLCG68 | C88: B0FHKLCG68 | D88: P
B89: B08Z3RTZ2G B0D9LTZKLW | C89: B08Z3RTZ2G | D89: A
B90: B0C5WJNC7H B0CGTXZQWW | C90: B0C5WJNC7H | D90: A
B91: B0FG72N63D | C91: B0FG72N63D | D91: S
B93: B07FQ4MGH6 | C93: B07FQ4MGH6 | D93: A
B95: B09BTMZYYD B0BW3SH2KR | C95: B09BTMZYYD | D95: P
B96: B0DYMGYWJ7 | C96: B0DYMGYWJ7 | D96: A
B97: B0DTPF5DMJ | C97: B0DTPF5DMJ
B99: B0CCJKDDLG | C99: B0CCJKDDLG | D99: P
B100: B0FG6QT1BT | C100: B0FG6QT1BT | D100: P
B101: B0DTP4VV5V | C101: B0DTP4VV5V | D101: P
B102: B0DTP8CJ82 | C102: B0DTP8CJ82 | D102: P
B103: B0C7G7W43V | C103: B0C7G7W43V | D103: P
B104: B0DTNYLQ2G | C104: B0DTNYLQ2G | D104: P
B105: B0DYN4HDJW | C105: B0DYN4HDJW | D105: A
B106: B0CT5RHX92 | C106: B0CT5RHX92 | D106: P
B107: B0FG6QPB1X | C107: B0FG6QPB1X | D107: P
B108: B0DTPHV3WP | C108: B0DTPHV3WP | D108: A
B109: 麦秆料无孔戏水数字鸭子 | C109: B0DTP8B4FZ | D109: P
B110: 麦秆料软胶手抓球 | C110: B0DTNYLQ2G | D110: A
... B117: 炫彩摇铃+手抓球球铃组合链接一 | C117: B0DTPHV3WP | D117: A
B118: 炫彩摇铃+手抓球球铃组合链接二 | C118: B0DTPF5DMJ
B119: NO.G502黄绿色卡车款谷雨小车链接一 | C119: B0FHH5Q86M | D119: A
B120: NO.G502黄绿色卡车款谷雨小车链接二 | C120: B0FHHC21LG | D120: A
B121: NO.G503黄绿色挖掘机款谷雨小车链接一 | C121: B0FHHC11GJ | D121: A
B122: NO.G503黄绿色挖掘机款谷雨小车链接二 | C122: B0FHH5PQ4H | D122: A
B123: 跟随鸭(白色）链接一 | C123: B0DTTBGYWW | D123: A
B124: 跟随鸭(白色）链接二 | C124: B0DTT3NTLG | D124: A
B125: 跟随鸭（黄绿紫）链接一 | C125: B0DTT4GNWW | D125: A
...

Sheet Sheet4
F7: 50asin等级 | K7: 149等级 | P7: 48等级
F9: B07SRSJZSL | G9: S | K9: X004U9OXE7 | L9: S
F10: B07SRSJZSL | G10: SS | K10: B0CRDL2HD6 | L10: S
F11: B07SVYD7RV | G11: S | K11: X004UB6DNT | L11: A
F12: B07SX1K48R | G12: S | K12: B0FHPSR92X | L12: A
F13: B07SVYD7RV | G13: SS | K13: X004UBDOYZ | L13: A
F14: B08J3MZQ2M | G14: S | K14: B0FMK6V5N6 | L14: A
F15: B08J3MZQ2M | G15: SS | K15: X004UT0YYP | L15: P
F16: B0B9N5PX8H | G16: S | K16: B0F23T2MLJ | L16: P
F17: B0B9N5PX8H | G17: SS | K17: X004TJJJ8X | L17: P
F18: B0BLHXCYWM | G18: S | K18: B0FHPVDGBQ | L18: P
F19: B0DPSZLZNL | G19: S | K19: X004ZG26M1 | L19: A
F20: B0BLHXCYWM | G20: SS | K20: B0GGR3FL2X | L20: A
... F110: B0DC3H9K53 | G110: A | K110: B0CYLVJ261 | L110: A
F111: B0CWH32QZD | G111: A
F112: B0BLHJ5G3N | G112: P
F113: B0BLHJ5G3N | G113: P
F114: B0CQX71441 | G114: P
F115: B0CQX71441 | G115: P
F116: B0BDDFFSG5 | G116: P
F117: B0BDDFFSG5 | G117: P
F118: B0CQ86MX8N | G118: P
F119: B0F1FJ9NH2 | G119: P
F120: B0CQ86MX8N | G120: P
F121: B0CTQG25QM | G121: P
F122: B0D3129FS8 | G122: P
... F220: B0DTPHV3WP | G220: A
F221: B0DTPF5DMJ
F222: B0FHH5Q86M | G222: A
F223: B0FHHC21LG | G223: A
F224: B0FHHC11GJ | G224: A
F225: B0FHH5PQ4H | G225: A
F226: B0DTTBGYWW | G226: A
F227: B0DTT3NTLG | G227: A
F228: B0DTT4GNWW | G228: A
F229: B0DTT8SK6H | G229: A
F230: B0FHKLCG68 | G230: A
F231: B0FG6W44P5 | G231: A
F232: B0FG73GKBG | G232: A
F233: B0CW9NVMSZ | G233: A
... F245: B0CT5RHX92 | G245: P

Sheet 149库存
A1: snapshot-date | B1: fnsku | C1: asin | D1: sku | E1: product-name | F1: condition | G1: available | H1: pending-removal-quantity | I1: inv-age-0-to-90-days | J1: inv-age-91-to-180-days | K1: inv-age-181-to-270-days | L1: inv-age-271-to-365-days | M1: inv-age-366-to-455-days | N1: inv-age-456-plus-days | O1: currency | P1: units-shipped-t7 | Q1: units-shipped-t30 | R1: units-shipped-t60 | S1: units-shipped-t90 | T1: alert | U1: your-price | V1: sales-price | W1: lowest-price-new-plus-shipping | X1: lowest-price-used | Y1: recommended-action | Z1: DEPRECATED healthy-inventory-level | AA1: recommended-sales-price | AB1: recommended-sale-duration-days | AC1: recommended-removal-quantity | AD1: estimated-cost-savings-of-recommended-actions | AE1: sell-through | AF1: item-volume | AG1: volume-unit-measurement | AH1: storage-type | AI1: storage-volume | AJ1: marketplace | AK1: product-group | AL1: sales-rank | AM1: days-of-supply | AN1: estimated-excess-quantity | AO1: weeks-of-cover-t30 | AP1: weeks-of-cover-t90 | AQ1: featuredoffer-price | AR1: sales-shipped-last-7-days | AS1: sales-shipped-last-30-days | AT1: sales-shipped-last-60-days | AU1: sales-shipped-last-90-days | AV1: inv-age-0-to-30-days | AW1: inv-age-31-to-60-days | AX1: inv-age-61-to-90-days | AY1: inv-age-181-to-330-days | AZ1: inv-age-331-to-365-days | BA1: estimated-storage-cost-next-month | BB1: inbound-quantity | BC1: inbound-working | BD1: inbound-shipped | BE1: inbound-received | BF1: no-sale-last-6-months | BG1: Total Reserved Quantity | BH1: unfulfillable-quantity | BI1: quantity-to-be-charged-ais-181-210-days | BJ1: estimated-ais-181-210-days | BK1: quantity-to-be-charged-ais-211-240-days | BL1: estimated-ais-211-240-days | BM1: quantity-to-be-charged-ais-241-270-days | BN1: estimated-ais-241-270-days | BO1: quantity-to-be-charged-ais-271-300-days | BP1: estimated-ais-271-300-days | BQ1: quantity-to-be-charged-ais-301-330-days | BR1: estimated-ais-301-330-days | BS1: quantity-to-be-charged-ais-331-365-days | BT1: estimated-ais-331-365-days | BU1: quantity-to-be-charged-ais-366-455-days | BV1: estimated-ais-366-455-days | BW1: quantity-to-be-charged-ais-456-plus-days | BX1: estimated-ais-456-plus-days | BY1: historical-days-of-supply | BZ1: fba-minimum-inventory-level | CA1: fba-inventory-level-health-status | CB1: Recommended ship-in quantity | CC1: Recommended ship-in date | CD1: Last updated date for Historical Days of Supply | CE1: Exempted from Low-Inventory-Level fee? | CF1: Low-Inventory-Level fee applied in current week? | CG1: Short term historical days of supply | CH1: Long term historical days of supply | CI1: Inventory age snapshot date | CJ1: Inventory Supply at FBA | CK1: Reserved FC Transfer | CL1: Reserved FC Processing | CM1: Reserved Customer Order | CN1: Reserved Staging | CO1: Total Days of Supply (including units from open shipments) | CP1: supplier | CQ1: is-seasonal-in-next-3-months | CR1: season-name | CS1: season-start-date | CT1: season-end-date
A2: 46189 | B2: B08G4MQP82 | C2: B08G4MQP82 | D2: 149-FengRenJi-P82 | E2: Sewing Machine for Beginners with Extension Table, Adjustable 2-Speed 2-Thread Mini Sewing Machine, Portable Electric Maquina de Coser with Foot Pedal, Perfect for DIY, Ideal Gift for Kids and Adults | G2: 0 | H2: -1 | O2: USD | U2: 0 | V2: 0 | W2: 0 | X2: 0 | Y2: NoRestockExcessActionRequired | AB2: 0 | AC2: 0 | AE2: -1 | AH2: Standard | AJ2: US | AK2: gl_home | AL2: 32209 | AN2: 0 | AQ2: 39.99 | AY2: 0 | BB2: 0 | BG2: 0 | BH2: 0 | CJ2: 0 | CK2: 0 | CL2: 0 | CM2: 0 | CN2: 0 | CP2: unassigned | CQ2: N
A3: 46189 | B3: X004U9OXE7 | C3: B0CRDL2HD6 | D3: 149US-PinkNiuDanJi | E3: ROHSCE Claw Machine for Kids, Mini Vending Machine Toys for Girls, Arcade Game Toy for Ages 8-13, Electronic Claw Game Machine for Party with Lights Sound, Birthday Gifts for Ages 4+ | F3: New | G3: 25 | H3: 0 | I3: 26 | J3: 0 | K3: 0 | L3: 0 | M3: 0 | N3: 0 | O3: USD | P3: 2 | Q3: 10 | R3: 18 | S3: 29 | U3: 97.99 | V3: 79.99 | W3: 79.99 | X3: 0 | Y3: NoRestockExcessActionRequired | AA3: 0 | AB3: 0 | AC3: 0 | AD3: 0 | AE3: 1.87 | AF3: 1.324074 | AG3: cubic feet | AH3: Oversize | AI3: 33.10185 | AJ3: US | AK3: gl_toy | AL3: 192027 | AM3: 102 | AN3: 0 | AO3: 22 | AP3: 25 | AQ3: 79.99 | AR3: 159.98 | AS3: 799.9 | AT3: 1439.82 | AU3: 2319.71 | AV3: 20 | AW3: 6 | AX3: 0 | AY3: 0 | AZ3: 0 | BA3: 19.79 | BB3: 32 | BC3: 26 | BD3: 6 | BE3: 0 | BG3: 0 | BH3: 0 | BY3: 57 | BZ3: 15 | CA3: Healthy | CD3: 46188 | CE3: Yes | CF3: No | CG3: 57 | CH3: 52.1 | CI3: 46186 | CJ3: 57 | CK3: 0 | CL3: 0 | CM3: 0 | CN3: 0 | CO3: 162 | CP3: unassigned | CQ3: N
A4: 46189 | B4: X004UB6DNT | C4: B0FHPSR92X | D4: 149US-SoftCiLiGuan26P-007 | E4: Magnetic Building Sticks Blocks for Toddlers 1-3 - Montessori Sensory Toys for 3 4 5 6 Year Old Boys & Girls, STEM Educational Construction Kit, Soft Flexible Magnets Gift Set for Kids Learning Games | F4: New | G4: 43 | H4: 0 | I4: 43 | J4: 0 | K4: 0 | L4: 0 | M4: 0 | N4: 0 | O4: USD | P4: 0 | Q4: 2 | R4: 14 | S4: 31 | T4: Low traffic | U4: 33.99 | V4: 19.99 | W4: 19.99 | X4: 0 | Y4: NoRestockExcessActionRequired | AA4: 0 | AB4: 0 | AC4: 0 | AD4: 0 | AE4: 0.79 | AF4: 0.140917 | AG4: cubic feet | AH4: Standard | AI4: 6.059431 | AJ4: US | AK4: gl_toy | AL4: 511375 | AM4: 185 | AN4: 0 | AO4: 86 | AP4: 18 | AQ4: 19.99 | AR4: 0 | AS4: 39.98 | AT4: 279.86 | AU4: 616.69 | AV4: 3 | AW4: 3 | AX4: 37 | AY4: 0 | AZ4: 0 | BA4: 5.63 | BB4: 0 | BC4: 0 | BD4: 0 | BE4: 0 | BG4: 0 | BH4: 0 | BY4: 430 | BZ4: 14 | CA4: Healthy | CD4: 46188 | CE4: Yes | CF4: No | CG4: 430 | CH4: 107.4 | CI4: 46186 | CJ4: 58 | CK4: 15 | CL4: 0 | CM4: 0 | CN4: 0 | CO4: 185 | CP4: unassigned | CQ4: N
A5: 46189 | B5: X004UBDOYZ | C5: B0FMK6V5N6 | D5: ZiMuYouXi-0002 | E5: ROHSCE Electronic Word Category Game, Durable Plastic Design, for Boys & Girls 6-12 Years Old, Fast-Paced Educational Vocabulary Toy for Family Party Night | F5: New | G5: 24 | H5: 0 | I5: 0 | J5: 25 | K5: 0 | L5: 0 | M5: 0 | N5: 0 | O5: USD | P5: 0 | Q5: 0 | R5: 5 | S5: 8 | T5: Low traffic | U5: 39.99 | V5: 19.99 | W5: 19.99 | X5: 0 | Y5: NoRestockExcessActionRequired | AA5: 0 | AB5: 0 | AC5: 0 | AD5: 432.19 | AE5: 0.32 | AF5: 0.114396 | AG5: cubic feet | AH5: Standard | AI5: 2.745504 | AJ5: US | AK5: gl_toy | AL5: 3278407 | AM5: 195 | AN5: 26 | AP5: 55 | AQ5: 19.99 | AR5: 0 | AS5: 0 | AT5: 99.95 | AU5: 159.53 | AV5: 0 | AW5: 0 | AX5: 0 | AY5: 0 | AZ5: 0 | BA5: 2.78 | BB5: 10 | BC5: 0 | BD5: 10 | BE5: 0 | BG5: 0 | BH5: 0 | BY5: 750 | BZ5: 5 | CA5: Excess | CD5: 46188 | CE5: Yes | CF5: No | CG5: 750 | CH5: 253.2 | CI5: 46186 | CJ5: 34 | CK5: 0 | CL5: 0 | CM5: 0 | CN5: 0 | CO5: 195 | CP5: unassigned | CQ5: N
A6: 46189 | B6: X004E7C2LB | C6: B0DD7HYVYM | D6: 149-qiqiuche-VYM | E6: ROHSCE Balloon Car Toy Pump Set, Balloon Race Car Kit for Kids Aged 3+, STEM Educational Balloon-Powered Cars for Boys Girls, Cool Toys for Autistic Kids with Rockets & Astronaut Figures | G6: 0 | H6: -1 | O6: USD | U6: 0 | V6: 0 | W6: 0 | X6: 0 | Y6: NoRestockExcessActionRequired | AB6: 0 | AC6: 0 | AE6: -1 | AJ6: US | AK6: gl_toy | AM6: 0 | AN6: 0 | AQ6: 26.24 | AY6: 0 | BB6: 0 | BG6: 0 | BH6: 0 | CJ6: 0 | CK6: 0 | CL6: 0 | CM6: 0 | CN6: 0 | CO6: 0 | CP6: unassigned | CQ6: N
A7: 46189 | B7: X004EG838N | C7: B0CT5R73WR | D7: 149-MaiGanLiuJian-3WR | E7: ROHSCE Sensory Balls for Babies - 6 Pack, Ball for Toddlers 1-3, Soft & Textured Montessori Baby Toys 6 to 12 Months, Wheat Straw Toddler Balls for Infant Development | G7: 0 | H7: -1 | O7: USD | U7: 0 | V7: 0 | W7: 0 | X7: 0 | Y7: NoRestockExcessActionRequired | AB7: 0 | AC7: 0 | AE7: -1 | AJ7: US | AK7: gl_toy | AL7: 2409 | AN7: 0 | AQ7: 18.99 | AY7: 0 | BB7: 0 | BG7: 0 | BH7: 0 | CJ7: 0 | CK7: 0 | CL7: 0 | CM7: 0 | CN7: 0 | CP7: unassigned | CQ7: N
A8: 46189 | B8: X004LVC1HF | C8: B0CD7RN2Q7 | D8: 149NewWhite-2Q7 | E8: ROHSCE Water Rocket Sprinkler for Kids, Outdoor Sprinkler Rocket Launcher Toy for Backyard, Summer Water Toys for Kids Ages 3-12, Fun Water Powered Rocket Toy (White-3) | G8: 0 | H8: -1 | O8: USD | U8: 0 | V8: 0 | W8: 0 | X8: 0 | Y8: NoRestockExcessActionRequired | AB8: 0 | AC8: 0 | AE8: -1 | AH8: Standard | AJ8: US | AK8: gl_toy | AM8: 0 | AN8: 0 | AQ8: 23.99 | AY8: 0 | BB8: 0 | BG8: 0 | BH8: 0 | CJ8: 0 | CK8: 0 | CL8: 0 | CM8: 0 | CN8: 0 | CO8: 0 | CP8: unassigned | CQ8: N
A9: 46189 | B9: X004YLNS65 | C9: B0DFFQV98K | D9: 149US-ShuangRenLanQiuJia | E9: ROHSCE 2-Player Basketball Arcade Game for Kids Ages 3-12, Indoor Outdoor Adjustable Dual Basketball Hoop with 6 Balls, Easy Assembly, Sport Toys Party Gifts for Boys & Girls Active Play | G9: 0 | H9: -1 | O9: USD | U9: 0 | V9: 0 | W9: 0 | X9: 0 | Y9: NoRestockExcessActionRequired | AB9: 0 | AC9: 0 | AE9: -1 | AH9: Oversize | AJ9: US | AK9: gl_toy | AM9: 0 | AN9: 0 | AQ9: 74.09 | AY9: 0 | BB9: 0 | BG9: 0 | BH9: 0 | CJ9: 0 | CK9: 0 | CL9: 0 | CM9: 0 | CN9: 0 | CO9: 0 | CP9: unassigned | CQ9: N
A10: 46189 | B10: X004M3GIXF | C10: B0CDLVX1T3 | D10: 149-CaiMeiHongQiang1T3 | E10: ROHSCE Electric Water Guns for Kids Age8-12, Squirt Guns Up to 32 FT Long Range, Automatic Water Absorption, Water Blaster Toy with Modular Battery, Summer Beach Pool Backyard Party Outdoor Toys | G10: 0 | H10: -1 | O10: USD | P10: 0 | Q10: 0 | R10: 0 | S10: 0 | U10: 0 | V10: 0 | W10: 0 | X10: 0 | Y10: NoRestockExcessActionRequired | AB10: 0 | AC10: 0 | AE10: -1 | AH10: Standard | AJ10: US | AK10: gl_toy | AM10: 0 | AN10: 0 | AQ10: 38.99 | AR10: 0 | AS10: 0 | AT10: 0 | AU10: 0 | AY10: 0 | BB10: 0 | BC10: 0 | BD10: 0 | BE10: 0 | BG10: 0 | BH10: 0 | BZ10: 1 | CA10: Out of stock | CJ10: 0 | CK10: 0 | CL10: 0 | CM10: 0 | CN10: 0 | CO10: 0 | CP10: unassigned | CQ10: N
A11: 46189 | B11: X00536XSEH | C11: B0GY4BZNQL | D11: radio-007 | E11: DIY Electronics Project Kit for Ages 10-14 - Wooden Radio Science Toy STEM Education Gift Physics Circuit Learning Assembly | G11: 0 | H11: -1 | O11: USD | U11: 0 | V11: 0 | W11: 0 | X11: 0 | Y11: NoRestockExcessActionRequired | AB11: 0 | AC11: 0 | AE11: -1 | AH11: Standard | AJ11: US | AK11: gl_toy | AN11: 0 | AY11: 0 | BB11: 0 | BG11: 0 | BH11: 0 | CJ11: 0 | CK11: 0 | CL11: 0 | CM11: 0 | CN11: 0 | CP11: unassigned | CQ11: N
A12: 46189 | B12: X004Q4ZCLT | C12: B0CGCKBSGT | D12: 149US-HuaSaMuYuPaoPaoJi | E12: Crab Bath Bubble Maker for Kids Bathtub Time. Blows Bubbles and Plays 24 Children’s Songs – Baby, Toddler Kids Bath Toys Makes Great Gifts for Toddlers – Sing-Along Bubble Machine Bath Toy | G12: 0 | H12: -1 | O12: USD | U12: 0 | V12: 0 | W12: 0 | X12: 0 | Y12: NoRestockExcessActionRequired | AB12: 0 | AC12: 0 | AE12: -1 | AH12: Other | AJ12: US | AK12: gl_toy | AN12: 0 | AY12: 0 | BB12: 0 | BG12: 0 | BH12: 0 | CJ12: 0 | CK12: 0 | CL12: 0 | CM12: 0 | CN12: 0 | CP12: unassigned | CQ12: N
A13: 46189 | B13: X004UT0YYP | C13: B0F23T2MLJ | D13: 149US-Chibang-devil | E13: ROHSCE Electric Devil Wings for Girls, Moving Light Up Bat Wings with LED Lights & Music, Adjustable Straps, Lightweight Costume Accessories for Kids 4-12, Halloween Birthday Christmas Party Gift | F13: New | G13: 28 | H13: 0 | I13: 0 | J13: 0 | K13: 28 | L13: 0 | M13: 0 | N13: 0 | O13: USD | P13: 0 | Q13: 0 | R13: 0 | S13: 1 | T13: Low traffic | U13: 49.99 | V13: 28.99 | W13: 28.99 | X13: 0 | Y13: Advertise listing | AB13: 0 | AC13: 0 | AE13: 0.04 | AF13: 0.224074 | AG13: cubic feet | AH13: Apparel | AI13: 6.274072 | AJ13: US | AK13: gl_apparel | AL13: 760704 | AM13: 366 | AN13: 0 | AP13: 364 | AQ13: 28.99 | AR13: 0 | AS13: 0 | AT13: 0 | AU13: 28.99 | AV13: 0 | AW13: 0 | AX13: 0 | AY13: 28 | AZ13: 0 | BB13: 0 | BC13: 0 | BD13: 0 | BE13: 0 | BG13: 0 | BH13: 0 | BZ13: 2 | CA13: Healthy | CH13: 2563 | CI13: 46186 | CJ13: 28 | CK13: 0 | CL13: 0 | CM13: 0 | CN13: 0 | CO13: 366 | CP13: unassigned | CQ13: N
A14: 46189 | B14: X004LV64XR | C14: B0C6T332PH | D14: 149-OYellowSprinkler2PH | E14: ROHSCE Water Rocket Sprinkler for Kids, Outdoor Sprinkler Rocket Launcher Toy for Backyard, Summer Water Toys for Kids Ages 3-12, Fun Water Powered Rocket Toy (Yellow-1) | G14: 0 | H14: -1 | O14: USD | U14: 0 | V14: 0 | W14: 0 | X14: 0 | Y14: NoRestockExcessActionRequired | AB14: 0 | AC14: 0 | AE14: -1 | AH14: Standard | AJ14: US | AK14: gl_toy | AM14: 0 | AN14: 0 | AQ14: 26.99 | AY14: 0 | BB14: 0 | BC14: 0 | BD14: 0 | BE14: 0 | BG14: 0 | BH14: 0 | CJ14: 0 | CK14: 0 | CL14: 0 | CM14: 0 | CN14: 0 | CO14: 0 | CP14: unassigned | CQ14: N
A15: 46189 | B15: X004JN99X9 | C15: B08Z3RTZ2G | D15: 149-BaiYuLian-Z2G | E15: ROHSCE Hookless Shower Curtain with Snap-in Liner, Waffle Weave Fabric, Hotel Grade, Clear Window, 72x74 Inch - White | G15: 0 | H15: -1 | O15: USD | P15: 0 | Q15: 0 | R15: 0 | S15: 0 | U15: 0 | V15: 0 | W15: 0 | X15: 0 | Y15: NoRestockExcessActionRequired | AB15: 0 | AC15: 0 | AE15: -1 | AH15: Standard | AJ15: US | AK15: gl_home | AL15: 1351087 | AM15: 0 | AN15: 0 | AQ15: 38.99 | AR15: 0 | AS15: 0 | AT15: 0 | AU15: 0 | AY15: 0 | BB15: 0 | BC15: 0 | BD15: 0 | BE15: 0 | BG15: 0 | BH15: 0 | BZ15: 1 | CA15: Out of stock | CJ15: 0 | CK15: 0 | CL15: 0 | CM15: 0 | CN15: 0 | CO15: 0 | CP15: unassigned | CQ15: N
A16: 46189 | B16: X004TJJJ8X | C16: B0FHPVDGBQ | D16: 149-KeHuanWanJvQiang-001 | E16: ROHSCE Flying Disc Launcher Toy for Kids Boys Girls 3-7 Year Old - Outdoor Rocket Shooter Game, Interactive Cat Dog Chase Toys, Indoor Activity Gifts for Toddlers Age 4-6 4-8 5-7 | F16: New | G16: 12 | H16: 0 | I16: 14 | J16: 0 | K16: 0 | L16: 0 | M16: 0 | N16: 0 | O16: USD | P16: 0 | Q16: 8 | R16: 21 | S16: 28 | T16: Low traffic | U16: 49.99 | V16: 29.99 | W16: 29.99 | X16: 0 | Y16: CreateShippingPlan | AA16: 0 | AB16: 0 | AC16: 0 | AD16: 0 | AE16: 1.62 | AF16: 0.225 | AG16: cubic feet | AH16: Standard | AI16: 2.7 | AJ16: US | AK16: gl_toy | AL16: 444729 | AM16: 54 | AN16: 0 | AO16: 6 | AP16: 5 | AQ16: 28.49 | AR16: 0 | AS16: 226.5 | AT16: 601.37 | AU16: 811.3 | AV16: 14 | AW16: 0 | AX16: 0 | AY16: 0 | AZ16: 0 | BA16: 1.99 | BB16: 0 | BC16: 0 | BD16: 0 | BE16: 0 | BG16: 0 | BH16: 1 | BY16: 50.4 | BZ16: 13 | CA16: Healthy | CB16: 7 | CC16: 46195 | CD16: 46188 | CE16: Yes | CF16: No | CG16: 44.5 | CH16: 50.4 | CI16: 46186 | CJ16: 15 | CK16: 3 | CL16: 0 | CM16: 0 | CN16: 0 | CO16: 54 | CP16: unassigned | CQ16: N
A17: 46189 | B17: X004EGUA3T | C17: B0D9XWDJ8F | D17: 149-GunQiuTuYa-J8F | E17: ROHSCE Marble Run for Kids, Vertical Magnetic Marble Maze Track with Doodle Board & Residue-Free Nano-Adhesive, STEM Explorers Brain Teaser Toy for Boys Girls Ages 3-12, Creative Thinking Games Gifts | G17: 0 | H17: -1 | O17: USD | U17: 0 | V17: 0 | W17: 0 | X17: 0 | Y17: NoRestockExcessActionRequired | AB17: 0 | AC17: 0 | AE17: -1 | AH17: Standard | AJ17: US | AK17: gl_toy | AL17: 190233 | AM17: 0 | AN17: 0 | AQ17: 29.99 | AY17: 0 | BB17: 0 | BC17: 0 | BD17: 0 | BE17: 0 | BG17: 0 | BH17: 0 | CB17: 5 | CC17: 46186 | CJ17: 0 | CK17: 0 | CL17: 0 | CM17: 0 | CN17: 0 | CO17: 0 | CP17: unassigned | CQ17: N
A18: 46189 | B18: X004ZG26M1 | C18: B0GGR3FL2X | D18: 149US-22TuZiMaoXianJi-NEW | E18: ROHSCE Sentro 22-Needle Circular Knitting Machine with Built-in Row Counter, Hand Crank Knitting Loom Machine for Beginners and Adults, DIY Hats, Scarves, Socks, and Crafts | F18: New | G18: 12 | H18: 0 | I18: 0 | J18: 12 | K18: 0 | L18: 0 | M18: 0 | N18: 0 | O18: USD | T18: Low traffic | U18: 49.99 | V18: 0 | W18: 38.99 | X18: 0 | Y18: Lower price | AA18: 0 | AB18: 0 | AC18: 0 | AD18: 995 | AE18: 0 | AF18: 0.361675 | AG18: cubic feet | AH18: Standard | AI18: 4.3401 | AJ18: US | AK18: gl_home | AL18: 215750 | AN18: 12 | AQ18: 38.99 | AV18: 0 | AW18: 0 | AX18: 0 | AY18: 0 | AZ18: 0 | BA18: 3.1 | BB18: 0 | BC18: 0 | BD18: 0 | BE18: 0 | BG18: 0 | BH18: 0 | CA18: Excess | CI18: 46186 | CJ18: 12 | CK18: 0 | CL18: 0 | CM18: 0 | CN18: 0 | CP18: unassigned | CQ18: N
A19: 46189 | B19: X004C26F2F | C19: B0CT8VF6J7 | D19: 149-xiaohaohudie-6J7 | E19: ROHSCE Electric Fairy Butterfly Wings Moving with LED Lights and Music, Light Up Butterfly Wings - Princess Fairy Costume Christmas Party Dress Up Gift for Girls 3 4 5 6 7 8 Year Old | F19: New | G19: 49 | H19: 0 | I19: 7 | J19: 44 | K19: 0 | L19: 0 | M19: 0 | N19: 0 | O19: USD | P19: 1 | Q19: 12 | R19: 26 | S19: 40 | U19: 39.89 | V19: 0 | W19: 39.89 | X19: 0 | Y19: NoRestockExcessActionRequired | AA19: 0 | AB19: 0 | AC19: 0 | AD19: 0.22 | AE19: 0.59 | AF19: 0.390973 | AG19: cubic feet | AH19: Standard | AI19: 19.157677 | AJ19: US | AK19: gl_toy | AL19: 760704 | AM19: 88 | AN19: 0 | AO19: 21 | AP19: 21 | AQ19: 32.99 | AR19: 34.99 | AS19: 419.88 | AT19: 909.74 | AU19: 1305.5 | AV19: 2 | AW19: 3 | AX19: 2 | AY19: 0 | AZ19: 0 | BA19: 18.27 | BB19: 16 | BC19: 16 | BD19: 0 | BE19: 0 | BG19: 1 | BH19: 0 | BY19: 153.5 | BZ19: 71 | CA19: Low stock | CB19: 126 | CC19: 46187 | CD19: 46188 | CE19: Yes | CF19: No | CG19: 153.5 | CH19: 147.2 | CI19: 46186 | CJ19: 66 | CK19: 1 | CL19: 0 | CM19: 1 | CN19: 0 | CO19: 127 | CP19: unassigned | CQ19: N
A20: 46189 | B20: X0053189TB | C20: B0GXTW8QC7 | D20: MatsPuzzlePads-007 | E20: Baby Play Mat Foam Tiles Interlocking Floor Mats for Crawling, Soft Thick EVA Puzzle Mat for Toddler Play Area, Waterproof Non-Toxic Foam Flooring for Nursery, Kids Room, Indoor Use | G20: 0 | H20: -1 | O20: USD | U20: 0 | V20: 0 | W20: 0 | X20: 0 | Y20: NoRestockExcessActionRequired | AB20: 0 | AC20: 0 | AE20: -1 | AH20: Standard | AJ20: US | AK20: gl_toy | AN20: 0 | AY20: 0 | BB20: 0 | BG20: 0 | BH20: 0 | CJ20: 0 | CK20: 0 | CL20: 0 | CM20: 0 | CN20: 0 | CP20: unassigned | CQ20: N
A21: 46189 | B21: X004JMW3F1 | C21: B0GFD9LS13 | D21: 149-MoTianGunZhu107pcs | E21: Motorized Marble Run Set, 107 Piece Magnetic Tile Building Toy with Ferris Wheel and Elevator, Music and Lights Marble Maze STEM Game for Kids Ages 4 to 12, Educational Gift | G21: 0 | H21: -1 | O21: USD | P21: 0 | Q21: 5 | R21: 5 | S21: 7 | U21: 0 | V21: 0 | W21: 0 | X21: 0 | Y21: CreateShippingPlan | AB21: 0 | AC21: 0 | AE21: -1 | AH21: Oversize | AJ21: US | AK21: gl_toy | AM21: 0 | AN21: 0 | AO21: 0 | AP21: 0 | AQ21: 119.99 | AR21: 0 | AS21: 339.45 | AT21: 339.45 | AU21: 479.43 | AY21: 0 | BB21: 0 | BC21: 0 | BD21: 0 | BE21: 0 | BG21: 0 | BH21: 0 | BY21: 9.4 | BZ21: 7 | CA21: Out of stock | CB21: 14 | CC21: 46188 | CD21: 46188 | CE21: Yes | CF21: No | CG21: 1 | CH21: 9.4 | CJ21: 0 | CK21: 0 | CL21: 0 | CM21: 0 | CN21: 0 | CO21: 0 | CP21: unassigned | CQ21: N
A22: 46189 | B22: X004PYADZ5 | C22: B0CZRT9PQ8 | D22: 149-LvHeGunZhu | E22: Glow in The Dark Marble Run 325Pcs Set with Motorized Elevator, Marble Maze STEM Toy with 113 Marbles, Construction Building Blocks for Kids Ages 3+, Best Easter & Birthday Gifts for Boys Girls | G22: 0 | H22: -1 | O22: USD | U22: 0 | V22: 0 | W22: 0 | X22: 0 | Y22: NoRestockExcessActionRequired | AB22: 0 | AC22: 0 | AE22: -1 | AH22: Oversize | AJ22: US | AK22: gl_toy | AM22: 0 | AN22: 0 | AQ22: 108.99 | AY22: 0 | BB22: 0 | BG22: 0 | BH22: 0 | CJ22: 0 | CK22: 0 | CL22: 0 | CM22: 0 | CN22: 0 | CO22: 0 | CP22: unassigned | CQ22: N
A23: 46189 | B23: X004QU266R | C23: B0CDGKZK2K | D23: 149-softblocks100PCS | E23: ROHSCE 100PCS Baby Blocks Set with Storage Bucket, Building Block Toys STEM Educational Toddler Gifts, Rubber Soft Blocks for Preschool, Sensory Stacking Toys to Improve Creativity | G23: 0 | H23: -1 | O23: USD | P23: 0 | Q23: 0 | R23: 0 | S23: 0 | U23: 0 | V23: 0 | W23: 0 | X23: 0 | Y23: NoRestockExcessActionRequired | AB23: 0 | AC23: 0 | AE23: -1 | AH23: Oversize | AJ23: US | AK23: gl_biss | AL23: 26497 | AN23: 0 | AQ23: 51.99 | AR23: 0 | AS23: 0 | AT23: 0 | AU23: 0 | AY23: 0 | BB23: 0 | BC23: 0 | BD23: 0 | BE23: 0 | BG23: 0 | BH23: 0 | CJ23: 0 | CK23: 0 | CL23: 0 | CM23: 0 | CN23: 0 | CP23: unassigned | CQ23: N
A24: 46189 | B24: X004Q9DR6V | C24: B0F2FG4SR1 | D24: 149-BangQiuZhiShengJi | E24: 2 in 1 Water Sprinklers T Ball Set for Kids & Toddlers, Outdoor Baseball and Spray Play Toy, Backyard Summer Yard Games, Connects to Garden Hose, Fun Water Toys for Lawn, Pool or Party Activities | G24: 0 | H24: -1 | O24: USD | P24: 1 | Q24: 12 | R24: 12 | S24: 19 | U24: 0 | V24: 0 | W24: 0 | X24: 0 | Y24: CreateShippingPlan | AB24: 0 | AC24: 0 | AE24: -1 | AH24: Standard | AJ24: US | AK24: gl_toy | AL24: 117152 | AM24: 0 | AN24: 0 | AO24: 0 | AP24: 0 | AQ24: 29.99 | AR24: 29.99 | AS24: 359.88 | AT24: 359.88 | AU24: 569.81 | AY24: 0 | BB24: 0 | BC24: 0 | BD24: 0 | BE24: 0 | BG24: 0 | BH24: 0 | BY24: 13.9 | BZ24: 17 | CA24: Out of stock | CD24: 46188 | CE24: Yes | CF24: No | CG24: 12.7 | CH24: 13.9 | CJ24: 0 | CK24: 0 | CL24: 0 | CM24: 0 | CN24: 0 | CO24: 0 | CP24: unassigned | CQ24: N
A25: 46189 | B25: X004S21DX5 | C25: B0F7GZ1D8D | D25: 149-YiCheHuaRongDao-2 | E25: Intelligent Car Maze Puzzle 1500 Challenges Brick Game Automatic Parking Logic Thinking Brain Game Toy for Kids Boys Girls Teens Gift | G25: 0 | H25: -1 | O25: USD | U25: 0 | V25: 0 | W25: 0 | X25: 0 | Y25: NoRestockExcessActionRequired | AB25: 0 | AC25: 0 | AE25: -1 | AH25: Standard | AJ25: US | AK25: gl_toy | AL25: 420629 | AM25: 0 | AN25: 0 | AQ25: 31.99 | AY25: 0 | BB25: 0 | BG25: 0 | BH25: 0 | CB25: 5 | CC25: 46186 | CJ25: 0 | CK25: 0 | CL25: 0 | CM25: 0 | CN25: 0 | CO25: 0 | CP25: unassigned | CQ25: N
A26: 46189 | B26: X004FNA441 | C26: B0BLKC4R77 | D26: 149-shuidantank-R77 | E26: RC Tank That Shoots BBS, Water Bullet Shooting RC Stunt Car for Kids, 2.4GHz Remote Control Truck with Light Spray, 360° Rotation & Drifting, Birthday Gift for Boys, 30+ Min Playtime | G26: 0 | H26: -1 | O26: USD | U26: 0 | V26: 0 | W26: 0 | X26: 0 | Y26: NoRestockExcessActionRequired | AB26: 0 | AC26: 0 | AE26: -1 | AH26: Oversize | AJ26: US | AK26: gl_toy | AM26: 0 | AN26: 0 | AQ26: 67.99 | AY26: 0 | BB26: 0 | BC26: 0 | BD26: 0 | BE26: 0 | BG26: 0 | BH26: 0 | CJ26: 0 | CK26: 0 | CL26: 0 | CM26: 0 | CN26: 0 | CO26: 0 | CP26: unassigned | CQ26: N
A27: 46189 | B27: X004PXU0U9 | C27: B0CL4H4HCF | D27: 149-LanHuDiepaopaoji | E27: bubble machine for kids,Automatic Bubble Machine with RGB LED Lights Music,Bubble Maker with 240ml Bubble Solution for Boys Girls,Electric Bubble Machine Making Toys for Outdoor Party Birthday Wedding | G27: 0 | H27: -1 | O27: USD | P27: 0 | Q27: 0 | R27: 0 | S27: 1 | U27: 0 | V27: 0 | W27: 0 | X27: 0 | Y27: CreateShippingPlan | AB27: 0 | AC27: 0 | AE27: -1 | AH27: Standard | AJ27: US | AK27: gl_toy | AM27: 0 | AN27: 0 | AP27: 0 | AQ27: 28.99 | AR27: 0 | AS27: 0 | AT27: 0 | AU27: 28.99 | AY27: 0 | BB27: 0 | BC27: 0 | BD27: 0 | BE27: 0 | BG27: 0 | BH27: 0 | BZ27: 1 | CA27: Out of stock | CH27: 30 | CJ27: 0 | CK27: 0 | CL27: 0 | CM27: 0 | CN27: 0 | CO27: 0 | CP27: unassigned | CQ27: N
A28: 46189 | B28: X004FBT7HD | C28: B0CT5HKGX6 | D28: 149-ChiLunPinTu-GX6 | E28: ROHSCE Gear Toys Interlocking Building Blocks, 150 Piece Educational Engineering Building Toys Set, Creative Construction STEM Kits for Boys Girls, Waffle Blocks for Kids Ages 3+ | F28: New | G28: 52 | H28: 0 | I28: 50 | J28: 9 | K28: 0 | L28: 0 | M28: 0 | N28: 0 | O28: USD | P28: 0 | Q28: 3 | R28: 40 | S28: 47 | T28: Low traffic | U28: 25.99 | V28: 19.99 | W28: 19.99 | X28: 0 | Y28: NoRestockExcessActionRequired | AA28: 0 | AB28: 0 | AC28: 0 | AD28: 0 | AE28: 1.04 | AF28: 0.151977 | AG28: cubic feet | AH28: Standard | AI28: 7.902804 | AJ28: US | AK28: gl_toy | AL28: 413849 | AM28: 142 | AN28: 0 | AO28: 122 | AP28: 25 | AQ28: 19.99 | AR28: 0 | AS28: 59.97 | AT28: 770.6 | AU28: 908.53 | AV28: 50 | AW28: 0 | AX28: 0 | AY28: 0 | AZ28: 0 | BA28: 8.24 | BB28: 40 | BC28: 30 | BD28: 10 | BE28: 0 | BG28: 0 | BH28: 0 | BY28: 195.2 | BZ28: 29 | CA28: Healthy | CD28: 46188 | CE28: Yes | CF28: No | CG28: 195.2 | CH28: 73 | CI28: 46186 | CJ28: 102 | CK28: 10 | CL28: 0 | CM28: 0 | CN28: 0 | CO28: 180 | CP28: unassigned | CQ28: N
A29: 46189 | B29: X004EGIAEF | C29: B0CT5RHX92 | D29: 149-MaiGan18Jian-X92 | E29: ROHSCE Baby Toy Set, 3 in 1 Baby Blocks, Teething Rings & Sensory Balls 6M+ | G29: 0 | H29: -1 | O29: USD | U29: 0 | V29: 0 | W29: 0 | X29: 0 | Y29: NoRestockExcessActionRequired | AB29: 0 | AC29: 0 | AE29: -1 | AJ29: US | AK29: gl_toy | AL29: 9437 | AN29: 0 | AQ29: 39.99 | AY29: 0 | BB29: 0 | BG29: 0 | BH29: 0 | CJ29: 0 | CK29: 0 | CL29: 0 | CM29: 0 | CN29: 0 | CP29: unassigned | CQ29: N
A30: 46189 | B30: X004Q3LDC7 | C30: B0DBYKPD1C | D30: 149US-XinKeQiMangLuBan | E30: Multifunctional Baby Walker, 3 in 1 Sit-to-Stand Push Toy with Musical Learning Panel, Early Developmental Walker for Infants 6-18 Months (Yellow) | G30: 0 | H30: -1 | O30: USD | U30: 0 | V30: 0 | W30: 0 | X30: 0 | Y30: NoRestockExcessActionRequired | AB30: 0 | AC30: 0 | AE30: -1 | AH30: Other | AJ30: US | AK30: gl_toy | AN30: 0 | AY30: 0 | BB30: 0 | BG30: 0 | BH30: 0 | CJ30: 0 | CK30: 0 | CL30: 0 | CM30: 0 | CN30: 0 | CP30: unassigned | CQ30: N
A31: 46189 | B31: X0051W38J3 | C31: B0GL21W9HL | D31: 149US-YaoKongQianTing-002 | E31: Flying Banana Mini RC Submarine Toy with LED Lights, Underwater Remote Control Submarine for Pool & Bathtub Play, USB Rechargeable, Gift for Boys & Girls Ages 6-12 | F31: New | G31: 0 | H31: -1 | O31: USD | U31: 75.99 | V31: 0 | W31: 0 | X31: 0 | Y31: Edit listing | AB31: 0 | AC31: 0 | AE31: -1 | AH31: Standard | AJ31: US | AK31: gl_toy | AN31: 0 | AQ31: 75.99 | AY31: 0 | BB31: 20 | BC31: 0 | BD31: 0 | BE31: 20 | BG31: 0 | BH31: 0 | CJ31: 20 | CK31: 0 | CL31: 0 | CM31: 0 | CN31: 0 | CP31: unassigned | CQ31: N
A32: 46189 | B32: X004EGTBBV | C32: B0DCNWK1GJ | D32: 149-shishangnvhai-1GJ | E32: Magnetic Paper Dolls for Girls ages 4-7 - 71 PC Fashion Girl Magnetic Dress Up Dolls Kits & Preschool Toddler Learning Activities, Travel-Friendly STEM Toy, Fun Fridge Magnets for Toddlers 3-12 | F32: New | G32: 32 | H32: 0 | I32: 1 | J32: 32 | K32: 0 | L32: 0 | M32: 0 | N32: 0 | O32: USD | P32: 0 | Q32: 0 | R32: 1 | S32: 9 | T32: Low traffic | U32: 28.99 | V32: 23.99 | W32: 23.99 | X32: 0 | Y32: NoRestockExcessActionRequired | AA32: 0 | AB32: 0 | AC32: 0 | AD32: 0 | AE32: 0.25 | AF32: 0.07886 | AG32: cubic feet | AH32: Standard | AI32: 2.52352 | AJ32: US | AK32: gl_toy | AL32: 190233 | AM32: 177 | AN32: 0 | AP32: 46 | AQ32: 23.99 | AR32: 0 | AS32: 0 | AT32: 23.99 | AU32: 214.41 | AV32: 0 | AW32: 0 | AX32: 1 | AY32: 0 | AZ32: 0 | BA32: 1.73 | BB32: 0 | BC32: 0 | BD32: 0 | BE32: 0 | BG32: 1 | BH32: 0 | BZ32: 10 | CA32: Healthy | CH32: 353.3 | CI32: 46186 | CJ32: 32 | CK32: 0 | CL32: 1 | CM32: 0 | CN32: 0 | CO32: 179 | CP32: unassigned | CQ32: N
A33: 46189 | B33: X0054KR0GT | C33: B0CRDMC78Z | D33: 149US-BlueCaiHongClaw | E33: ROHSCE Mini Claw Machine for Kids | Electric Vending Machine Toy Arcade Game Toy with Mini Prizes, Candy Claw Machine Toys Adjustable Sound and Music, Birthday Gifts for Girls | F33: New | G33: 9 | H33: 0 | I33: 9 | J33: 0 | K33: 0 | L33: 0 | M33: 0 | N33: 0 | O33: USD | T33: Low traffic | U33: 85.99 | V33: 0 | W33: 81.69 | X33: 0 | Y33: Lower price | AB33: 0 | AC33: 0 | AE33: 0 | AF33: 1.111111 | AG33: cubic feet | AH33: Oversize | AI33: 9.999999 | AJ33: US | AK33: gl_toy | AL33: 804557 | AN33: 0 | AQ33: 81.69 | AV33: 9 | AW33: 0 | AX33: 0 | AY33: 0 | AZ33: 0 | BB33: 0 | BC33: 0 | BD33: 0 | BE33: 0 | BG33: 0 | BH33: 1 | CI33: 46186 | CJ33: 9 | CK33: 0 | CL33: 0 | CM33: 0 | CN33: 0 | CP33: unassigned | CQ33: N
A34: 46189 | B34: X004EGIV21 | C34: B0CT5TKD1T | D34: 149-MaiGanZuQiu-D1T | E34: ROHSCE Bath Toys, Soft Sport Sensory Balls for Toddlers Boys Girls No Hole Wheat Straw Soft Montessori Toys for Babies 6 Months+, Swimming Pool Beach Shower Baby Toys | G34: 0 | H34: -1 | O34: USD | U34: 0 | V34: 0 | W34: 0 | X34: 0 | Y34: NoRestockExcessActionRequired | AB34: 0 | AC34: 0 | AE34: -1 | AJ34: US | AK34: gl_baby_product | AL34: 2409 | AN34: 0 | AQ34: 13.99 | AY34: 0 | BB34: 0 | BG34: 0 | BH34: 0 | CJ34: 0 | CK34: 0 | CL34: 0 | CM34: 0 | CN34: 0 | CP34: unassigned | CQ34: N
A35: 46189 | B35: X004U9P0AN | C35: B0C5CWSDGX | D35: 149US-PinkCaiHongWuClaw | E35: ROHSCE Mini Claw Machine for Kids | Girl Toys for Ages 8-13 Arcade Game Toy Claw Machine Electric Candy Vending Machine Toy with LED Lights & Adjustable Sound, Birthday Gifts for Girls Ages 4+, Pink | F35: New | G35: 22 | H35: 0 | I35: 0 | J35: 22 | K35: 0 | L35: 0 | M35: 0 | N35: 0 | O35: USD | P35: 1 | Q35: 6 | R35: 10 | S35: 14 | U35: 89.99 | V35: 0 | W35: 79.99 | X35: 0 | Y35: NoRestockExcessActionRequired | AA35: 75.99 | AB35: 2 | AC35: 0 | AD35: 36.54 | AE35: 0.46 | AF35: 1.111111 | AG35: cubic feet | AH35: Oversize | AI35: 24.444442 | AJ35: US | AK35: gl_toy | AL35: 192027 | AM35: 78 | AN35: 0 | AO35: 20 | AP35: 27 | AQ35: 75.99 | AR35: 75.99 | AS35: 471.94 | AT35: 775.9 | AU35: 1095.86 | AV35: 0 | AW35: 0 | AX35: 0 | AY35: 0 | AZ35: 0 | BA35: 11.66 | BB35: 8 | BC35: 8 | BD35: 0 | BE35: 0 | BG35: 0 | BH35: 1 | BY35: 193.8 | CD35: 46188 | CE35: Yes | CF35: No | CG35: 92.5 | CH35: 193.8 | CI35: 46186 | CJ35: 30 | CK35: 0 | CL35: 0 | CM35: 0 | CN35: 0 | CO35: 107 | CP35: unassigned | CQ35: N
A36: 46189 | B36: X004EG8HB1 | C36: B0FP52CS55 | D36: 149-niwajiang-0002 | E36: ROHSCE Brick and Mortar Construction Set, DIY Building Blocks for Kids Ages 6+, STEM Construction Kit, Versatile Creative Play, Great Birthday Gift | F36: New | G36: 52 | H36: 0 | I36: 0 | J36: 53 | K36: 0 | L36: 0 | M36: 0 | N36: 0 | O36: USD | P36: 3 | Q36: 8 | R36: 11 | S36: 21 | U36: 69.99 | V36: 0 | W36: 69.99 | X36: 0 | Y36: NoRestockExcessActionRequired | AA36: 0 | AB36: 0 | AC36: 0 | AD36: 13.04 | AE36: 0.28 | AF36: 0.46221 | AG36: cubic feet | AH36: Standard | AI36: 24.03492 | AJ36: US | AK36: gl_biss | AL36: 145796 | AM36: 132 | AN36: 0 | AO36: 26 | AP36: 32 | AQ36: 47.49 | AR36: 142.47 | AS36: 424.92 | AT36: 563.13 | AU36: 1028.68 | AV36: 0 | AW36: 0 | AX36: 0 | AY36: 0 | AZ36: 0 | BA36: 16.62 | BB36: 0 | BC36: 0 | BD36: 0 | BE36: 0 | BG36: 0 | BH36: 7 | BY36: 430.8 | BZ36: 27 | CA36: Healthy | CD36: 46188 | CE36: Yes | CF36: No | CG36: 430.8 | CH36: 322.9 | CI36: 46186 | CJ36: 52 | CK36: 0 | CL36: 0 | CM36: 0 | CN36: 0 | CO36: 132 | CP36: unassigned | CQ36: N
A37: 46189 | B37: X004UEQAMP | C37: B0FPC6D218 | D37: 149US-PinkNiuDanClaw | E37: Claw Machine for Kids, Mini Vending Machine Toy for Girls, Arcade Game Toy for Ages 8-13, Electronic Claw Game with Lights & Sound, Perfect for Parties & Birthday Gifts for Ages 4+ | F37: New | G37: 12 | H37: 0 | I37: 8 | J37: 4 | K37: 0 | L37: 0 | M37: 0 | N37: 0 | O37: USD | P37: 0 | Q37: 0 | R37: 0 | S37: 2 | T37: Low traffic | U37: 97.99 | V37: 79.99 | W37: 79.99 | X37: 0 | Y37: Advertise listing | AA37: 0 | AB37: 0 | AC37: 0 | AD37: 3631.81 | AE37: 0.31 | AF37: 1.46036 | AG37: cubic feet | AH37: Oversize | AI37: 17.52432 | AJ37: US | AK37: gl_toy | AL37: 989086 | AM37: 192 | AN37: 14 | AP37: 91 | AQ37: 79.99 | AR37: 0 | AS37: 0 | AT37: 0 | AU37: 159.98 | AV37: 8 | AW37: 0 | AX37: 0 | AY37: 0 | AZ37: 0 | BA37: 9.51 | BB37: 2 | BC37: 0 | BD37: 2 | BE37: 0 | BG37: 0 | BH37: 0 | BZ37: 3 | CA37: Excess | CH37: 271.5 | CI37: 46186 | CJ37: 14 | CK37: 0 | CL37: 0 | CM37: 0 | CN37: 0 | CO37: 192 | CP37: unassigned | CQ37: N
A38: 46189 | B38: X004KPM8EX | C38: B08FRGNGGZ | D38: 149-HeiseyulianGGZ | E38: ROHSCE Hookless Shower Curtain Set with Snap-in Liner, 250GSM Waffle Weave Fabric, Hotel Grade, Mesh Window, Weighted Hem, 72x74 Inch - Black | G38: 0 | H38: -1 | O38: USD | P38: 0 | Q38: 0 | R38: 0 | S38: 0 | U38: 0 | V38: 0 | W38: 0 | X38: 0 | Y38: NoRestockExcessActionRequired | AB38: 0 | AC38: 0 | AE38: -1 | AH38: Standard | AJ38: US | AK38: gl_home | AL38: 1351087 | AM38: 0 | AN38: 0 | AQ38: 33.99 | AR38: 0 | AS38: 0 | AT38: 0 | AU38: 0 | AY38: 0 | BB38: 0 | BC38: 0 | BD38: 0 | BE38: 0 | BG38: 0 | BH38: 0 | BZ38: 1 | CA38: Out of stock | CJ38: 0 | CK38: 0 | CL38: 0 | CM38: 0 | CN38: 0 | CO38: 0 | CP38: unassigned | CQ38: N
A39: 46189 | B39: X004ML1M47 | C39: B0DYXXZ9YT | D39: 149US-BaZYU | E39: Water Sprinkler Baseball Toy for Kids Outdoor Play – 2-in-1 Splash Game with Bat & Balls, Backyard Summer Water Toys for Toddlers and Children, Fun Lawn Activities for Boys Girls Ages 3-12 | G39: 0 | H39: -1 | O39: USD | P39: 0 | Q39: 1 | R39: 3 | S39: 4 | U39: 0 | V39: 0 | W39: 0 | X39: 0 | Y39: CreateShippingPlan | AB39: 0 | AC39: 0 | AE39: -1 | AH39: Standard | AJ39: US | AK39: gl_toy | AM39: 0 | AN39: 0 | AO39: 0 | AP39: 0 | AQ39: 26.59 | AR39: 0 | AS39: 26.59 | AT39: 81.17 | AU39: 111.16 | AY39: 0 | BB39: 0 | BC39: 0 | BD39: 0 | BE39: 0 | BG39: 0 | BH39: 0 | BY39: 41.8 | BZ39: 1 | CA39: Out of stock | CB39: 3 | CC39: 46186 | CD39: 46188 | CE39: Yes | CF39: No | CG39: 11 | CH39: 41.8 | CJ39: 0 | CK39: 0 | CL39: 0 | CM39: 0 | CN39: 0 | CO39: 0 | CP39: unassigned | CQ39: N
A40: 46189 | B40: X004U91N8L | C40: B0F28JGBPS | D40: 149US-PinkXueQiuQiang | E40: ROHSCE Snowball Launcher Gun Toys for Kids, Outdoor Winter Snow Toys Set, 24 Pcs Snow Maker Toy with Launcher, Unisex Children's Sand-Toys Gift Ages 3+ | G40: 0 | H40: -1 | O40: USD | P40: 0 | Q40: 0 | R40: 0 | S40: 0 | U40: 0 | V40: 0 | W40: 0 | X40: 0 | Y40: NoRestockExcessActionRequired | AB40: 0 | AC40: 0 | AE40: -1 | AH40: Standard | AJ40: US | AK40: gl_toy | AM40: 0 | AN40: 0 | AQ40: 23.99 | AR40: 0 | AS40: 0 | AT40: 0 | AU40: 0 | AY40: 0 | BB40: 0 | BC40: 0 | BD40: 0 | BE40: 0 | BG40: 0 | BH40: 0 | BZ40: 1 | CA40: Out of stock | CJ40: 0 | CK40: 0 | CL40: 0 | CM40: 0 | CN40: 0 | CO40: 0 | CP40: unassigned | CQ40: N
A41: 46189 | B41: X004PAEK9J | C41: B0GFDVDWGP | D41: GuiDaoGunZhu-FBA-us149 | E41: 325PCS Glow in The Dark Marble Run with Motorized Elevator, STEM Building Blocks Toy Includes 113 Marbles, for Kids Ages 3+, Easter Birthday Gift for Boys and Girls | G41: 0 | H41: 0 | I41: 0 | J41: 1 | K41: 8 | L41: 0 | M41: 0 | N41: 0 | O41: USD | P41: 0 | Q41: 0 | R41: 4 | S41: 6 | T41: Low traffic | U41: 0 | V41: 0 | W41: 99.99 | X41: 0 | Y41: CreateShippingPlan | AB41: 0 | AC41: 0 | AE41: 0.49 | AF41: 0.935229 | AG41: cubic feet | AH41: Oversize | AI41: 0 | AJ41: US | AK41: gl_toy | AL41: 391948 | AM41: 0 | AN41: 0 | AP41: 0 | AQ41: 94.99 | AR41: 0 | AS41: 0 | AT41: 384.96 | AU41: 584.94 | AV41: 0 | AW41: 0 | AX41: 0 | AY41: 8 | AZ41: 0 | BB41: 0 | BC41: 0 | BD41: 0 | BE41: 0 | BG41: 0 | BH41: 9 | BI41: 8 | BJ41: 3.75 | BK41: 0 | BL41: 0 | BM41: 0 | BN41: 0 | BO41: 0 | BP41: 0 | BQ41: 0 | BR41: 0 | BS41: 0 | BT41: 0 | BU41: 0 | BV41: 0 | BW41: 0 | BX41: 0 | BZ41: 6 | CA41: Out of stock | CH41: 185.8 | CI41: 46186 | CJ41: 0 | CK41: 0 | CL41: 0 | CM41: 0 | CN41: 0 | CO41: 0 | CP41: unassigned | CQ41: N
A42: 46189 | B42: X004YLNWWF | C42: B0CB1C5BM1 | D42: 149US-LanSeGuiDaoChe | E42: Logical Road Builder, STEM Board Games Brain Teaser, Kids Puzzle Games Educational Montessori Toys, Large Board Games Birthday Gifts for 4 5 6 7 Year Old Preschool Boys Girls | G42: 0 | H42: -1 | O42: USD | U42: 0 | V42: 0 | W42: 0 | X42: 0 | Y42: NoRestockExcessActionRequired | AB42: 0 | AC42: 0 | AE42: -1 | AH42: Standard | AJ42: US | AK42: gl_toy | AL42: 606948 | AN42: 0 | AQ42: 24.99 | AY42: 0 | BB42: 0 | BG42: 0 | BH42: 0 | CJ42: 0 | CK42: 0 | CL42: 0 | CM42: 0 | CN42: 0 | CP42: unassigned | CQ42: N
A43: 46189 | B43: X004LW6NPF | C43: B0C6T5HSPX | D43: 149-OYellowRocket-HoseSPX | E43: ROHSCE Water Rocket Sprinkler for Kids, Outdoor Sprinkler Rocket Launcher Toy for Backyard, Summer Water Toys for Kids Ages 3-12, Fun Water Powered Rocket Toy (Yellow-2) | G43: 0 | H43: -1 | O43: USD | U43: 0 | V43: 0 | W43: 0 | X43: 0 | Y43: NoRestockExcessActionRequired | AB43: 0 | AC43: 0 | AE43: -1 | AH43: Standard | AJ43: US | AK43: gl_toy | AN43: 0 | AQ43: 39.95 | AY43: 0 | BB43: 0 | BC43: 0 | BD43: 0 | BE43: 0 | BG43: 0 | BH43: 0 | CJ43: 0 | CK43: 0 | CL43: 0 | CM43: 0 | CN43: 0 | CP43: unassigned | CQ43: N
A44: 46189 | B44: X004UERPF1 | C44: B0FPC5R1ZY | D44: 149US-LvHeGuiDaoGunZhu | E44: Glow-in-The-Dark Marble Run 325Pcs Set with Motorized Elevator, STEM Marble Maze Toy with 113 Marbles, Construction Building Blocks for Kids Ages 6+, Perfect Easter & Birthday Gift for Boys and Girls | G44: 0 | H44: -1 | O44: USD | U44: 0 | V44: 0 | W44: 0 | X44: 0 | Y44: NoRestockExcessActionRequired | AB44: 0 | AC44: 0 | AE44: -1 | AH44: Oversize | AJ44: US | AK44: gl_toy | AM44: 0 | AN44: 0 | AQ44: 76.99 | AY44: 0 | BB44: 0 | BC44: 0 | BD44: 0 | BE44: 0 | BG44: 0 | BH44: 0 | CJ44: 0 | CK44: 0 | CL44: 0 | CM44: 0 | CN44: 0 | CO44: 0 | CP44: unassigned | CQ44: N
A45: 46189 | B45: X004P3GXFZ | C45: B0CVZVND5J | D45: 149US-LvSeDoMiNuo | E45: ROHSCE Domino Train Toy, 80 PCS Kids Games Automatic Dominos Set, STEM Montessori Toys for 3 Year Old, Colorful Lights & Music Creative Gifts for Boys Girls Autistic Age 3 4 5 6+ | G45: 0 | H45: -1 | O45: USD | P45: 0 | Q45: 0 | R45: 0 | S45: 0 | U45: 0 | V45: 0 | W45: 0 | X45: 0 | Y45: NoRestockExcessActionRequired | AB45: 0 | AC45: 0 | AE45: -1 | AH45: Standard | AJ45: US | AK45: gl_toy | AL45: 359544 | AN45: 0 | AQ45: 33.99 | AR45: 0 | AS45: 0 | AT45: 0 | AU45: 0 | AY45: 0 | BB45: 0 | BC45: 0 | BD45: 0 | BE45: 0 | BG45: 0 | BH45: 0 | CJ45: 0 | CK45: 0 | CL45: 0 | CM45: 0 | CN45: 0 | CP45: unassigned | CQ45: N
A46: 46189 | B46: X004ZG6JRJ | C46: B0GGQDW816 | D46: 149US-XiaoHaoTuZiMaoXianJi | E46: ROHSCE Sentro 22 Needle Knitting Machine with Built-in Row Counter, Hand Crank Knitting Loom Machine for Beginners, Hat and Scarf Making, DIY Crafts for Kids and Adults | F46: New | G46: 10 | H46: 0 | I46: 0 | J46: 10 | K46: 0 | L46: 0 | M46: 0 | N46: 0 | O46: USD | P46: 0 | Q46: 0 | R46: 0 | S46: 0 | T46: Low traffic | U46: 49.89 | V46: 0 | W46: 37.99 | X46: 0 | Y46: Lower price | AA46: 0 | AB46: 0 | AC46: 0 | AD46: 1000.36 | AE46: 0.1 | AF46: 0.361675 | AG46: cubic feet | AH46: Standard | AI46: 3.61675 | AJ46: US | AK46: gl_home | AL46: 215750 | AM46: 203 | AN46: 10 | AQ46: 37.99 | AR46: 0 | AS46: 0 | AT46: 0 | AU46: 0 | AV46: 0 | AW46: 0 | AX46: 0 | AY46: 0 | AZ46: 0 | BA46: 2.59 | BB46: 0 | BC46: 0 | BD46: 0 | BE46: 0 | BG46: 0 | BH46: 0 | BZ46: 2 | CA46: Excess | CH46: 450.5 | CI46: 46186 | CJ46: 10 | CK46: 0 | CL46: 0 | CM46: 0 | CN46: 0 | CO46: 203 | CP46: unassigned | CQ46: N
A47: 46189 | B47: X004U9SP0Z | C47: B0CRDLS3LR | D47: 149US-MeiHongDuJiaoShouClaw | E47: ROHSCE Interactive Claw Toy Arcade Machine with Prizes, Kids Vending Machine with Lights, Music, Plush Toys & Capsules, Mini Claw Machine USB Rechargeable, Birthday Gift for Girls Ages 6-12 | F47: New | G47: 6 | H47: 0 | I47: 6 | J47: 0 | K47: 0 | L47: 0 | M47: 0 | N47: 0 | O47: USD | T47: Low traffic | U47: 109.99 | V47: 0 | W47: 109.99 | X47: 0 | Y47: Advertise listing | AB47: 0 | AC47: 0 | AE47: 0 | AF47: 1.29974 | AG47: cubic feet | AH47: Oversize | AI47: 7.79844 | AJ47: US | AK47: gl_toy | AL47: 1388024 | AM47: 366 | AN47: 0 | AQ47: 109.99 | AV47: 6 | AW47: 0 | AX47: 0 | AY47: 0 | AZ47: 0 | BB47: 2 | BC47: 0 | BD47: 2 | BE47: 0 | BG47: 0 | BH47: 0 | CI47: 46186 | CJ47: 8 | CK47: 0 | CL47: 0 | CM47: 0 | CN47: 0 | CO47: 366 | CP47: unassigned | CQ47: N
A48: 46189 | B48: X0051THII3 | C48: B0GL7ZCK1C | D48: 149US-YaoKongQianTing-003 | E48: Flying Banana Mini Submarine Pool Toy with LED Lights, Underwater Swimming Toy for Pool and Bathtub Play, USB Rechargeable, for Kids Ages 8-12 | G48: 0 | H48: -1 | O48: USD | U48: 0 | V48: 0 | W48: 0 | X48: 0 | Y48: Edit listing | AB48: 0 | AC48: 0 | AE48: -1 | AH48: Standard | AJ48: US | AK48: gl_toy | AN48: 0 | AQ48: 75.99 | AY48: 0 | BB48: 28 | BC48: 0 | BD48: 0 | BE48: 28 | BG48: 0 | BH48: 0 | CJ48: 28 | CK48: 0 | CL48: 0 | CM48: 0 | CN48: 0 | CP48: unassigned | CQ48: N
A49: 46189 | B49: X004SQHCWH | C49: B0FHHDCYFL | D49: 149-Reminxiangji-Pink | E49: ROHSCE Instant Camera for Kids, Digital Print Camera 48MP 1080P, Color & B&W Printing, 2.4" Display, USB-C Rechargeable, 32GB Card, Christmas & Birthday Gifts for 3-12 Year Old Girls Boys (Pink) | F49: New | G49: 21 | H49: 0 | I49: 10 | J49: 11 | K49: 0 | L49: 0 | M49: 0 | N49: 0 | O49: USD | P49: 1 | Q49: 1 | R49: 7 | S49: 13 | T49: Low traffic | U49: 59.99 | V49: 44.99 | W49: 44.99 | X49: 0 | Y49: NoRestockExcessActionRequired | AA49: 0 | AB49: 0 | AC49: 0 | AD49: 0 | AE49: 0.66 | AF49: 0.051042 | AG49: cubic feet | AH49: Standard | AI49: 1.071882 | AJ49: US | AK49: gl_camera | AL49: 354967 | AM49: 147 | AN49: 0 | AO49: 124 | AP49: 31 | AQ49: 44.99 | AR49: 44.99 | AS49: 44.99 | AT49: 314.93 | AU49: 584.87 | AV49: 10 | AW49: 0 | AX49: 0 | AY49: 0 | AZ49: 0 | BA49: 1.14 | BB49: 10 | BC49: 10 | BD49: 0 | BE49: 0 | BG49: 0 | BH49: 2 | BY49: 558 | BZ49: 7 | CA49: Healthy | CD49: 46188 | CE49: Yes | CF49: No | CG49: 558 | CH49: 109.2 | CI49: 46186 | CJ49: 36 | CK49: 5 | CL49: 0 | CM49: 0 | CN49: 0 | CO49: 181 | CP49: unassigned | CQ49: N
A50: 46189 | B50: X004U97IG7 | C50: B0F28K5ZNP | D50: 149US-BlueXueQiuQiang002 | E50: ROHSCE Reusable Water Toys Launcher Set – 28 Soft Water Balls for Kids Backyard & Yard Games – Outdoor Summer Toys for Toddlers Ages 4-8, 8-12, Splash Fun, Toddler Summer Activities | G50: 0 | H50: -1 | O50: USD | P50: 0 | Q50: 0 | R50: 0 | S50: 0 | U50: 0 | V50: 0 | W50: 0 | X50: 0 | Y50: NoRestockExcessActionRequired | AB50: 0 | AC50: 0 | AE50: -1 | AH50: Standard | AJ50: US | AK50: gl_toy | AM50: 0 | AN50: 0 | AQ50: 32.39 | AR50: 0 | AS50: 0 | AT50: 0 | AU50: 0 | AY50: 0 | BB50: 0 | BC50: 0 | BD50: 0 | BE50: 0 | BG50: 0 | BH50: 0 | BZ50: 1 | CA50: Out of stock | CJ50: 0 | CK50: 0 | CL50: 0 | CM50: 0 | CN50: 0 | CO50: 0 | CP50: unassigned | CQ50: N
A51: 46189 | B51: X00530YW9D | C51: B0GXTMFDSG | D51: 149-duijiangji008 | E51: Kids Video Walkie Talkies, Toy Walkie Talkies with Screen Display, Real-Time Video & Voice Intercom for Boys Girls Ages 3-12, Indoor Outdoor Play Travel Xmas Birthday Gift Set | G51: 0 | H51: -1 | O51: USD | U51: 0 | V51: 0 | W51: 0 | X51: 0 | Y51: NoRestockExcessActionRequired | AB51: 0 | AC51: 0 | AE51: -1 | AH51: Standard | AJ51: US | AK51: gl_wireless | AN51: 0 | AY51: 0 | BB51: 0 | BG51: 0 | BH51: 0 | CJ51: 0 | CK51: 0 | CL51: 0 | CM51: 0 | CN51: 0 | CP51: unassigned | CQ51: N
A52: 46189 | B52: X004C2CMAJ | C52: B0CB1947NZ | D52: 149-shuangqiangshejijiqiren-7NZ | E52: ROHSCE Shooting Game Toy for Boys 4-6 & Up - Movable Shooting Targets for Kids, Sound and Spray Effect Dinosaur Toys for Kids 3-5-7 with 2 Guns and 24 Foam Balls, Shooting Toy Gift for Boys and Girls | G52: 0 | H52: -1 | O52: USD | P52: 0 | Q52: 0 | R52: 0 | S52: 0 | U52: 0 | V52: 0 | W52: 0 | X52: 0 | Y52: NoRestockExcessActionRequired | AB52: 0 | AC52: 0 | AE52: -1 | AH52: Standard | AJ52: US | AK52: gl_toy | AM52: 0 | AN52: 0 | AQ52: 46.99 | AR52: 0 | AS52: 0 | AT52: 0 | AU52: 0 | AY52: 0 | BB52: 0 | BC52: 0 | BD52: 0 | BE52: 0 | BG52: 0 | BH52: 0 | BZ52: 1 | CA52: Out of stock | CJ52: 0 | CK52: 0 | CL52: 0 | CM52: 0 | CN52: 0 | CO52: 0 | CP52: unassigned | CQ52: N
A53: 46189 | B53: X004Q1PWXZ | C53: B0F299SJCM | D53: 149-taoyiji-Green | E53: ROHSCE Electric Pottery Wheel Kit, Ceramic Pottery and Painting Crafts Set for Kids 3+ | G53: 0 | H53: -1 | O53: USD | U53: 0 | V53: 0 | W53: 0 | X53: 0 | Y53: NoRestockExcessActionRequired | AB53: 0 | AC53: 0 | AE53: -1 | AH53: Other | AJ53: US | AK53: gl_toy | AN53: 0 | AY53: 0 | BB53: 0 | BG53: 0 | BH53: 0 | CJ53: 0 | CK53: 0 | CL53: 0 | CM53: 0 | CN53: 0 | CP53: unassigned | CQ53: N
A54: 46189 | B54: X004S25IZT | C54: B0F7H2HJ9K | D54: 149HuaRongDaoYellow2 | E54: Smart Car Huarong Road Puzzle Game 1500 Levels Brain Teaser Desktop Brick Game Maze Escape Blocks Logic Challenge Kids Toys Gift for Boys/Girls/Teens | F54: New | G54: 21 | H54: 0 | I54: 1 | J54: 17 | K54: 3 | L54: 0 | M54: 0 | N54: 0 | O54: USD | P54: 0 | Q54: 1 | R54: 1 | S54: 2 | T54: Low traffic | U54: 38.99 | V54: 31.99 | W54: 31.99 | X54: 0 | Y54: Advertise listing | AA54: 0 | AB54: 0 | AC54: 0 | AD54: 635.36 | AE54: 0.09 | AF54: 0.088542 | AG54: cubic feet | AH54: Standard | AI54: 1.859382 | AJ54: US | AK54: gl_toy | AL54: 445845 | AM54: 366 | AN54: 21 | AO54: 84 | AP54: 136 | AR54: 0 | AS54: 31.99 | AT54: 31.99 | AU54: 63.98 | AV54: 0 | AW54: 1 | AX54: 0 | AY54: 3 | AZ54: 0 | BA54: 2.83 | BB54: 0 | BC54: 0 | BD54: 0 | BE54: 0 | BG54: 0 | BH54: 0 | BI54: 0 | BJ54: 0 | BK54: 0 | BL54: 0 | BM54: 0 | BN54: 0 | BO54: 3 | BP54: 1.45 | BQ54: 0 | BR54: 0 | BS54: 0 | BT54: 0 | BU54: 0 | BV54: 0 | BW54: 0 | BX54: 0 | BY54: 970.5 | BZ54: 3 | CA54: Excess | CD54: 46188 | CE54: Yes | CF54: No | CG54: 641 | CH54: 970.5 | CI54: 46186 | CJ54: 21 | CK54: 0 | CL54: 0 | CM54: 0 | CN54: 0 | CO54: 366 | CP54: unassigned | CQ54: N
A55: 46189 | B55: X0052GA6EN | C55: B0F2MKWCCT | D55: 149US-WoNiuBangQiu | E55: Snail T-Ball Water Sprinkler – Summer Backyard & Lawn Toys, Great for Kids Ages 3-8, Birthday Party & Pool Play | G55: 0 | H55: -1 | O55: USD | U55: 0 | V55: 0 | W55: 0 | X55: 0 | Y55: NoRestockExcessActionRequired | AB55: 0 | AC55: 0 | AE55: -1 | AH55: Standard | AJ55: US | AK55: gl_toy | AN55: 0 | AQ55: 9.99 | AY55: 0 | BB55: 0 | BG55: 0 | BH55: 0 | CJ55: 0 | CK55: 0 | CL55: 0 | CM55: 0 | CN55: 0 | CP55: unassigned | CQ55: N
A56: 46189 | B56: X004UBFH8L | C56: B0FK4FYRZJ | D56: HeJinLuoSiJiMu-0002 | E56: ROHSCE 496 Pcs Metal Building Toys for Boys & Girls 8-12 Years Old, Off-Road Vehicle Model Truck Kits, STEM Engineering Construction Set, Monster Car Educational Gift for Kids Ages 8 9 10+ | F56: New | G56: 19 | H56: 0 | I56: 28 | J56: 0 | K56: 0 | L56: 0 | M56: 0 | N56: 0 | O56: USD | P56: 1 | Q56: 12 | R56: 28 | S56: 41 | T56: Low traffic | U56: 35.99 | V56: 29.99 | W56: 29.99 | X56: 0 | Y56: NoRestockExcessActionRequired | AA56: 0 | AB56: 0 | AC56: 0 | AD56: 0 | AE56: 1.52 | AF56: 0.186875 | AG56: cubic feet | AH56: Standard | AI56: 3.550625 | AJ56: US | AK56: gl_toy | AL56: 337906 | AM56: 85 | AN56: 0 | AO56: 19 | AP56: 18 | AQ56: 28.49 | AR56: 28.49 | AS56: 343.38 | AT56: 805.22 | AU56: 1195.09 | AV56: 6 | AW56: 22 | AX56: 0 | AY56: 0 | AZ56: 0 | BA56: 5.45 | BB56: 39 | BC56: 15 | BD56: 24 | BE56: 0 | BG56: 1 | BH56: 2 | BY56: 62.8 | BZ56: 26 | CA56: Low stock | CD56: 46188 | CE56: Yes | CF56: No | CG56: 62.8 | CH56: 50.2 | CI56: 46186 | CJ56: 64 | CK56: 6 | CL56: 0 | CM56: 1 | CN56: 0 | CO56: 115 | CP56: unassigned | CQ56: N
A57: 46189 | B57: X004T19SXH | C57: B0FG7DXS9Y | D57: 149-3DLiTiDuiJiangJiPingTu-003 | E57: STEM Toys for Kids Ages 5-12, DIY Walkie Talkie Building Kit for Outdoor Play, Science Kits for Kids 8-10 8-12, Educational Engineering Toys for Home, School Projects, and Camp Activities | F57: New | G57: 27 | H57: 0 | I57: 12 | J57: 0 | K57: 13 | L57: 0 | M57: 0 | N57: 0 | O57: USD | P57: 0 | Q57: 0 | R57: 1 | S57: 1 | T57: Low traffic | U57: 45.99 | V57: 25.99 | W57: 25.99 | X57: 0 | Y57: Create removal order | AA57: 0 | AB57: 0 | AC57: 0 | AD57: 330.19 | AE57: 0.04 | AF57: 0.041759 | AG57: cubic feet | AH57: Standard | AI57: 1.127493 | AJ57: US | AK57: gl_baby_product | AL57: 1037383 | AM57: 366 | AN57: 27 | AP57: 351 | AQ57: 25.99 | AR57: 0 | AS57: 0 | AT57: 25.99 | AU57: 25.99 | AV57: 0 | AW57: 0 | AX57: 12 | AY57: 13 | AZ57: 0 | BA57: 1.39 | BB57: 0 | BC57: 0 | BD57: 0 | BE57: 0 | BG57: 1 | BH57: 0 | BI57: 13 | BJ57: 0.26 | BK57: 0 | BL57: 0 | BM57: 0 | BN57: 0 | BO57: 0 | BP57: 0 | BQ57: 0 | BR57: 0 | BS57: 0 | BT57: 0 | BU57: 0 | BV57: 0 | BW57: 0 | BX57: 0 | BZ57: 3 | CA57: Excess | CH57: 2137 | CI57: 46186 | CJ57: 27 | CK57: 0 | CL57: 1 | CM57: 0 | CN57: 0 | CO57: 366 | CP57: unassigned | CQ57: N
A58: 46189 | B58: X004RPX36D | C58: B0CRDNDFLC | D58: 149-BlueNiuDanWaWaJi | E58: ROHSCE Kids Claw Machine, Arcade Game Toy for Ages 8-13, Candy Vending Toys for Girls and Boys, Electronic Claw Game Machine for Party with Lights Sound, Birthday Gifts for 6 7 9 10 12 Years Old | F58: New | G58: 43 | H58: 0 | I58: 43 | J58: 0 | K58: 0 | L58: 0 | M58: 0 | N58: 0 | O58: USD | P58: 2 | Q58: 14 | R58: 32 | S58: 58 | U58: 99.99 | V58: 79.99 | W58: 79.99 | X58: 0 | Y58: NoRestockExcessActionRequired | AA58: 0 | AB58: 0 | AC58: 0 | AD58: 0 | AE58: 1.45 | AF58: 1.335208 | AG58: cubic feet | AH58: Oversize | AI58: 57.413944 | AJ58: US | AK58: gl_toy | AL58: 192027 | AM58: 63 | AN58: 0 | AO58: 22 | AP58: 17 | AQ58: 79.99 | AR58: 159.98 | AS58: 1119.86 | AT58: 2559.68 | AU58: 4639.42 | AV58: 36 | AW58: 7 | AX58: 0 | AY58: 0 | AZ58: 0 | BA58: 28.39 | BB58: 34 | BC58: 28 | BD58: 6 | BE58: 0 | BG58: 0 | BH58: 0 | BY58: 63.5 | BZ58: 32 | CA58: Healthy | CD58: 46188 | CE58: Yes | CF58: No | CG58: 63.5 | CH58: 53.8 | CI58: 46186 | CJ58: 77 | CK58: 0 | CL58: 0 | CM58: 0 | CN58: 0 | CO58: 94 | CP58: unassigned | CQ58: N
A59: 46189 | B59: B08FRGNGGZ | C59: B08FRGNGGZ | D59: 149-HeiYuLianGGZ | E59: ROHSCE Hookless Shower Curtain Set with Snap-in Liner, 250GSM Waffle Weave Fabric, Hotel Grade, Mesh Window, Weighted Hem, 72x74 Inch - Black | G59: 0 | H59: -1 | O59: USD | U59: 0 | V59: 0 | W59: 0 | X59: 0 | Y59: NoRestockExcessActionRequired | AB59: 0 | AC59: 0 | AE59: -1 | AH59: Standard | AJ59: US | AK59: gl_home | AL59: 1351087 | AM59: 0 | AN59: 0 | AQ59: 33.99 | AY59: 0 | BB59: 0 | BG59: 0 | BH59: 0 | CJ59: 0 | CK59: 0 | CL59: 0 | CM59: 0 | CN59: 0 | CO59: 0 | CP59: unassigned | CQ59: N
A60: 46189 | B60: X0051PS65L | C60: B0GQZ5S8NC | D60: 149US-YaoKongQianTing-006 | E60: Flying Banana Mini RC Submarine with LED Lights, Remote Control Underwater Pool and Bathtub Watercraft, Rechargeable Gift for Ages 6-12 | G60: 0 | H60: -1 | O60: USD | U60: 0 | V60: 0 | W60: 0 | X60: 0 | Y60: Edit listing | AB60: 0 | AC60: 0 | AE60: -1 | AH60: Standard | AJ60: US | AK60: gl_toy | AN60: 0 | AQ60: 75.99 | AY60: 0 | BB60: 28 | BC60: 0 | BD60: 0 | BE60: 28 | BG60: 0 | BH60: 0 | CJ60: 28 | CK60: 0 | CL60: 0 | CM60: 0 | CN60: 0 | CP60: unassigned | CQ60: N
A61: 46189 | B61: X004YTQB0H | C61: B09M8D5Z9S | D61: 149US-HongHeJiMu | E61: Wooden Cubes, IQ Puzzle, Building Cube Express Toy Faces, Magic Face Building Block Wooden Puzzle Montessori Toy | F61: New | G61: 30 | H61: 0 | I61: 0 | J61: 30 | K61: 0 | L61: 0 | M61: 0 | N61: 0 | O61: USD | T61: Low traffic | U61: 22.99 | V61: 0 | W61: 19.99 | X61: 0 | Y61: Lower price | AA61: 0 | AB61: 0 | AC61: 0 | AD61: 682.06 | AE61: 0 | AF61: 0.09614 | AG61: cubic feet | AH61: Standard | AI61: 2.8842 | AJ61: US | AK61: gl_toy | AL61: 621422 | AM61: 366 | AN61: 30 | AQ61: 19.99 | AV61: 0 | AW61: 0 | AX61: 0 | AY61: 0 | AZ61: 0 | BA61: 2.06 | BB61: 0 | BC61: 0 | BD61: 0 | BE61: 0 | BG61: 0 | BH61: 0 | CA61: Excess | CI61: 46186 | CJ61: 30 | CK61: 0 | CL61: 0 | CM61: 0 | CN61: 0 | CO61: 366 | CP61: unassigned | CQ61: N
A62: 46189 | B62: X004S1P3E1 | C62: B0F7GZ1D8D | D62: 149-YiCheHuaRongDao-1 | E62: Intelligent Car Maze Puzzle 1500 Challenges Brick Game Automatic Parking Logic Thinking Brain Game Toy for Kids Boys Girls Teens Gift | F62: New | G62: 23 | H62: -1 | O62: USD | U62: 38.99 | V62: 0 | W62: 0 | X62: 0 | Y62: Edit listing | AA62: 0 | AB62: 0 | AC62: 0 | AD62: 764.57 | AE62: -1 | AH62: Standard | AJ62: US | AK62: gl_toy | AL62: 420629 | AM62: 282 | AN62: 0 | AQ62: 31.99 | AY62: 0 | BA62: 1.46 | BB62: 0 | BC62: 0 | BD62: 0 | BE62: 0 | BG62: 3 | BH62: 0 | BY62: 1199.5 | BZ62: 3 | CA62: Healthy | CD62: 46188 | CE62: Yes | CF62: No | CG62: 773 | CH62: 1199.5 | CJ62: 23 | CK62: 0 | CL62: 3 | CM62: 0 | CN62: 0 | CO62: 327 | CP62: unassigned | CQ62: N
A63: 46189 | B63: X004PZTQON | C63: B0CCTHB771 | D63: 149-FeiDiePenShui-B | E63: ROHSCE Water Rocket Sprinkler for Kids, Outdoor Sprinkler Rocket Launcher Toy for Backyard, Summer Water Toys for Kids Ages 3-12, Fun Water Powered Rocket Toy (UFO) | G63: 0 | H63: -1 | O63: USD | P63: 0 | Q63: 0 | R63: 0 | S63: 0 | U63: 0 | V63: 0 | W63: 0 | X63: 0 | Y63: NoRestockExcessActionRequired | AB63: 0 | AC63: 0 | AE63: -1 | AH63: Standard | AJ63: US | AK63: gl_toy | AM63: 0 | AN63: 0 | AQ63: 33.99 | AR63: 0 | AS63: 0 | AT63: 0 | AU63: 0 | AY63: 0 | BB63: 0 | BC63: 0 | BD63: 0 | BE63: 0 | BG63: 0 | BH63: 0 | BZ63: 1 | CA63: Out of stock | CJ63: 0 | CK63: 0 | CL63: 0 | CM63: 0 | CN63: 0 | CO63: 0 | CQ63: N
A64: 46189 | B64: X004UBLE3D | C64: B0FMK6R2HS | D64: ZiMuYouXi-0003 | E64: ROHSCE Interactive Word Game for Family, Board Games with 24-Letter Board & Timer 2025 & Toys for 1-6 Year Olds Boys & Girls, Dual Category Modes for Adults Kids Party Nights | F64: New | G64: 36 | H64: 0 | I64: 0 | J64: 36 | K64: 0 | L64: 0 | M64: 0 | N64: 0 | O64: USD | P64: 0 | Q64: 0 | R64: 1 | S64: 5 | T64: Low traffic | U64: 39.99 | V64: 19.99 | W64: 19.99 | X64: 0 | Y64: Advertise listing | AA64: 0 | AB64: 0 | AC64: 0 | AD64: 1176.41 | AE64: 0.13 | AF64: 0.114396 | AG64: cubic feet | AH64: Standard | AI64: 4.118256 | AJ64: US | AK64: gl_toy | AL64: 749084 | AM64: 287 | AN64: 36 | AP64: 93 | AQ64: 19.99 | AR64: 0 | AS64: 0 | AT64: 19.99 | AU64: 90.95 | AV64: 0 | AW64: 0 | AX64: 0 | AY64: 0 | AZ64: 0 | BA64: 2.94 | BB64: 0 | BC64: 0 | BD64: 0 | BE64: 0 | BG64: 0 | BH64: 0 | BZ64: 5 | CA64: Excess | CH64: 665.8 | CI64: 46186 | CJ64: 36 | CK64: 0 | CL64: 0 | CM64: 0 | CN64: 0 | CO64: 287 | CP64: unassigned | CQ64: N
A65: 46189 | B65: X004C5HM1Z | C65: B0D9M5SKC9 | D65: 149-UFO-KC9 | E65: Bubble Machine for Kids - Automatic Bubble Maker with LED Light & Music, Rotating 360° UFO Toys, Safe Bubble Blower for Pets Dogs Cats, Cool Outdoor Toy for 1-3 3-8 Year Old Boys Girls Birthday Gifts | G65: 0 | H65: -1 | O65: USD | P65: 0 | Q65: 0 | R65: 9 | S65: 10 | U65: 0 | V65: 0 | W65: 0 | X65: 0 | Y65: CreateShippingPlan | AB65: 0 | AC65: 0 | AE65: -1 | AH65: Standard | AJ65: US | AK65: gl_toy | AL65: 247408 | AM65: 0 | AN65: 0 | AP65: 0 | AQ65: 26.99 | AR65: 0 | AS65: 0 | AT65: 230.76 | AU65: 256.4 | AY65: 0 | BB65: 0 | BC65: 0 | BD65: 0 | BE65: 0 | BG65: 0 | BH65: 7 | BZ65: 1 | CA65: Out of stock | CH65: 34.3 | CJ65: 0 | CK65: 0 | CL65: 0 | CM65: 0 | CN65: 0 | CO65: 0 | CP65: unassigned | CQ65: N
A66: 46189 | B66: X00556DYSP | C66: B0H2VVGDFC | D66: 149US-PenShuiHuoJian-07 | E66: Summer Water Rocket Toy for Kids, Outdoor Sprinkler Rocket Launcher, Backyard Water Powered Toy for Boys and Girls | G66: 0 | H66: -1 | O66: USD | U66: 0 | V66: 0 | W66: 0 | X66: 0 | Y66: NoRestockExcessActionRequired | AB66: 0 | AC66: 0 | AE66: -1 | AH66: Standard | AJ66: US | AK66: gl_toy | AN66: 0 | AY66: 0 | BB66: 0 | BG66: 0 | BH66: 0 | CJ66: 0 | CK66: 0 | CL66: 0 | CM66: 0 | CN66: 0 | CP66: unassigned | CQ66: N
A67: 46189 | B67: X004NYU2XZ | C67: B0CYPXQLGL | D67: 149-BaoJianCiJiMu | E67: ROHSCE Magnetic Blocks 160PCS - Sword Theme Construction Cubes, STEM Preschool kit, Safe ABS no-Odor, CPC ASTM Certified, Travel-Ready Ages 3–12, Perfect for Birthday | F67: New | G67: 10 | H67: 0 | I67: 0 | J67: 0 | K67: 0 | L67: 0 | M67: 10 | N67: 0 | O67: USD | P67: 1 | Q67: 1 | R67: 1 | S67: 3 | T67: Low traffic | U67: 69.99 | V67: 19.99 | W67: 19.99 | X67: 0 | Y67: NoRestockExcessActionRequired | AA67: 0 | AB67: 0 | AC67: 0 | AD67: 615.98 | AE67: 0.27 | AF67: 0.226431 | AG67: cubic feet | AH67: Standard | AI67: 2.26431 | AJ67: US | AK67: gl_toy | AL67: 244622 | AM67: 186 | AN67: 10 | AO67: 40 | AP67: 43 | AQ67: 19.99 | AR67: 19.99 | AS67: 19.99 | AT67: 19.99 | AU67: 75.97 | AV67: 0 | AW67: 0 | AX67: 0 | AY67: 0 | AZ67: 0 | BA67: 17.1 | BB67: 0 | BC67: 0 | BD67: 0 | BE67: 0 | BG67: 0 | BH67: 0 | BI67: 0 | BJ67: 0 | BK67: 0 | BL67: 0 | BM67: 0 | BN67: 0 | BO67: 0 | BP67: 0 | BQ67: 0 | BR67: 0 | BS67: 0 | BT67: 0 | BU67: 10 | BV67: 15.62 | BW67: 0 | BX67: 0 | BZ67: 3 | CA67: Excess | CH67: 511 | CI67: 46186 | CJ67: 10 | CK67: 0 | CL67: 0 | CM67: 0 | CN67: 0 | CO67: 186 | CP67: unassigned | CQ67: N
A68: 46189 | B68: X004C289JH | C68: B0FP58Q9WV | D68: 149-dawoya-YXS | E68: ROHSCE Kids Shooting Game | Dinosaur Moving Target with Sound & Mist | 2 Blasters + 24 Foam Balls | Fun Gift for Boys 4–6 & Up and Girls 3–7 | G68: 0 | H68: -1 | O68: USD | P68: 0 | Q68: 0 | R68: 0 | S68: 0 | U68: 0 | V68: 0 | W68: 0 | X68: 0 | Y68: NoRestockExcessActionRequired | AB68: 0 | AC68: 0 | AE68: -1 | AH68: Standard | AJ68: US | AK68: gl_toy | AM68: 0 | AN68: 0 | AQ68: 20.53 | AR68: 0 | AS68: 0 | AT68: 0 | AU68: 0 | AY68: 0 | BB68: 0 | BC68: 0 | BD68: 0 | BE68: 0 | BG68: 0 | BH68: 0 | BZ68: 1 | CA68: Out of stock | CJ68: 0 | CK68: 0 | CL68: 0 | CM68: 0 | CN68: 0 | CO68: 0 | CP68: unassigned | CQ68: N
A69: 46189 | B69: X004FQY52F | C69: B0CYPY1SBN | D69: 149-108magneticblock-SBN | E69: ROHSCE Magnetic Blocks Toys for Kids - 108PCS Magnetic Blocks for Kids, STEM Preschool Stacking Construction Toys Educational Sensory Toy for Children Development and Creativity | G69: 0 | H69: -1 | O69: USD | U69: 0 | V69: 0 | W69: 0 | X69: 0 | Y69: NoRestockExcessActionRequired | AB69: 0 | AC69: 0 | AE69: -1 | AJ69: US | AK69: gl_toy | AN69: 0 | AQ69: 59.99 | AY69: 0 | BB69: 0 | BG69: 0 | BH69: 0 | CJ69: 0 | CK69: 0 | CL69: 0 | CM69: 0 | CN69: 0 | CP69: unassigned | CQ69: N
A70: 46189 | B70: X004UBFFD3 | C70: B0FK4GKPTM | D70: HeJinLuoSiJiMu-0008 | E70: ROHSCE STEM Metal Airplane Building Kits for Kids Ages 8-16, 285 Pieces DIY Mechanical Engineering Construction Toys, Large Model Aircraft Project for Boys & Girls, Educational Science Plane Gift | F70: New | G70: 28 | H70: 0 | I70: 21 | J70: 8 | K70: 0 | L70: 0 | M70: 0 | N70: 0 | O70: USD | P70: 0 | Q70: 2 | R70: 4 | S70: 9 | T70: Low traffic | U70: 39.99 | V70: 27.99 | W70: 27.99 | X70: 0 | Y70: NoRestockExcessActionRequired | AA70: 25.59 | AB70: 10 | AC70: 0 | AD70: 11.92 | AE70: 0.33 | AF70: 0.190315 | AG70: cubic feet | AH70: Standard | AI70: 5.32882 | AJ70: US | AK70: gl_toy | AL70: 548923 | AM70: 171 | AN70: 9 | AO70: 56 | AP70: 40 | AQ70: 26.59 | AR70: 0 | AS70: 53.18 | AT70: 106.36 | AU70: 246.31 | AV70: 1 | AW70: 0 | AX70: 20 | AY70: 0 | AZ70: 0 | BA70: 3.61 | BB70: 0 | BC70: 0 | BD70: 0 | BE70: 0 | BG70: 0 | BH70: 0 | BY70: 286.3 | BZ70: 6 | CA70: Excess | CD70: 46188 | CE70: Yes | CF70: No | CG70: 286.3 | CH70: 272.4 | CI70: 46186 | CJ70: 28 | CK70: 0 | CL70: 0 | CM70: 0 | CN70: 0 | CO70: 171 | CP70: unassigned | CQ70: N
A71: 46189 | B71: X004LW6SN7 | C71: B0C6T1N7MS | D71: 149-ORedRocket-7MS | E71: Rocket Launcher for Kids 2025, Outdoor Electric Water Rocket with Parachute, Sprinkler Toy for Boys & Girls Ages 6-12, Water Powered Summer Backyard Toy (Red-2) | G71: 0 | H71: -1 | O71: USD | P71: 0 | Q71: 0 | R71: 0 | S71: 0 | U71: 0 | V71: 0 | W71: 0 | X71: 0 | Y71: NoRestockExcessActionRequired | AB71: 0 | AC71: 0 | AE71: -1 | AH71: Standard | AJ71: US | AK71: gl_toy | AM71: 0 | AN71: 0 | AQ71: 9.99 | AR71: 0 | AS71: 0 | AT71: 0 | AU71: 0 | AY71: 0 | BB71: 0 | BC71: 0 | BD71: 0 | BE71: 0 | BG71: 0 | BH71: 1 | BZ71: 1 | CA71: Out of stock | CJ71: 0 | CK71: 0 | CL71: 0 | CM71: 0 | CN71: 0 | CO71: 0 | CP71: unassigned | CQ71: N
A72: 46189 | B72: X004UBFD0N | C72: B0FR4KKXG7 | D72: 149-DuJiaoShouMang-001 | E72: Unicorn Advent Calendar 2025 for Girls, 24-Day Christmas Countdown Surprise Box with Jewelry & Hair Accessories, Sunglasses, Coin Purse & Keychain, Stocking Stuffer Gifts for Kids Ages 4-10 | G72: 0 | H72: -1 | O72: USD | P72: 0 | Q72: 0 | R72: 0 | S72: 0 | U72: 0 | V72: 0 | W72: 0 | X72: 0 | Y72: NoRestockExcessActionRequired | AB72: 0 | AC72: 0 | AE72: -1 | AH72: Standard | AJ72: US | AK72: gl_toy | AM72: 0 | AN72: 0 | AQ72: 22.05 | AR72: 0 | AS72: 0 | AT72: 0 | AU72: 0 | AY72: 0 | BB72: 0 | BC72: 0 | BD72: 0 | BE72: 0 | BG72: 0 | BH72: 0 | BZ72: 3 | CA72: Out of stock | CB72: 4 | CC72: 46186 | CJ72: 0 | CK72: 0 | CL72: 0 | CM72: 0 | CN72: 0 | CO72: 0 | CP72: unassigned | CQ72: N
A73: 46189 | B73: X00536YKFN | C73: B0GY4BS1MX | D73: radio-008 | E73: Physics Experiment FM Radio Kit - STEM Science Building Toy for Students Ages 7-13 Educational Wooden Craft Electronics Gift | G73: 0 | H73: -1 | O73: USD | U73: 0 | V73: 0 | W73: 0 | X73: 0 | Y73: NoRestockExcessActionRequired | AB73: 0 | AC73: 0 | AE73: -1 | AH73: Standard | AJ73: US | AK73: gl_toy | AN73: 0 | AY73: 0 | BB73: 0 | BG73: 0 | BH73: 0 | CJ73: 0 | CK73: 0 | CL73: 0 | CM73: 0 | CN73: 0 | CP73: unassigned | CQ73: N
A74: 46189 | B74: X004PALXM1 | C74: B0CRDLV5P8 | D74: 149-ZiSeNiuDanJi | E74: ROHSCE 2 in 1 Big Claw Machine for Kids with Toys Inside, Arcade Games Vending Machine, Mini Claw Game Arcade Toy, Home Party Easter Birthday Gifts for Girl & Boys Age 3+ | F74: New | G74: 6 | H74: 0 | I74: 6 | J74: 0 | K74: 0 | L74: 0 | M74: 0 | N74: 0 | O74: USD | P74: 0 | Q74: 0 | R74: 0 | S74: 0 | T74: Low traffic | U74: 109.89 | V74: 0 | W74: 98.99 | X74: 0 | Y74: Lower price | AA74: 0 | AB74: 0 | AC74: 0 | AD74: 1645.39 | AE74: 0 | AF74: 1.29974 | AG74: cubic feet | AH74: Oversize | AI74: 7.79844 | AJ74: US | AK74: gl_toy | AL74: 813560 | AM74: 123 | AN74: 0 | AQ74: 98.99 | AR74: 0 | AS74: 0 | AT74: 0 | AU74: 0 | AV74: 2 | AW74: 4 | AX74: 0 | AY74: 0 | AZ74: 0 | BA74: 4 | BB74: 0 | BC74: 0 | BD74: 0 | BE74: 0 | BG74: 0 | BH74: 0 | BZ74: 2 | CA74: Healthy | CI74: 46186 | CJ74: 6 | CK74: 0 | CL74: 0 | CM74: 0 | CN74: 0 | CO74: 123 | CP74: unassigned | CQ74: N
A75: 46189 | B75: X004UB2NLF | C75: B0CRDLNXBS | D75: 149US-Shengdanclaw-zuzhuang | E75: ROHSCE Claw Machine for Kids, Mini Vending Machines Arcade Claw Game Prizes Toy, Indoor Electronic Cool Fun Toys for Girls Birthday Gifts for 6 7 9 10 12 Years Old | G75: 0 | H75: -1 | O75: USD | U75: 0 | V75: 0 | W75: 0 | X75: 0 | Y75: NoRestockExcessActionRequired | AB75: 0 | AC75: 0 | AE75: -1 | AH75: Standard | AJ75: US | AK75: gl_toy | AM75: 0 | AN75: 0 | AQ75: 45.49 | AY75: 0 | BB75: 0 | BG75: 0 | BH75: 0 | CJ75: 0 | CK75: 0 | CL75: 0 | CM75: 0 | CN75: 0 | CO75: 0 | CP75: unassigned | CQ75: N
A76: 46189 | B76: X004LWWRAP | C76: B0CD7TVJ66 | D76: 149US-HongSePenShuiDaiGuan-J66 | E76: ROHSCE Water Rocket Sprinkler for Kids, Outdoor Sprinkler Rocket Launcher Toy for Backyard, Summer Water Toys for Kids Ages 3-12, Fun Water Powered Rocket Toy (Red-5) | F76: New | G76: 4 | H76: 0 | I76: 0 | J76: 0 | K76: 0 | L76: 0 | M76: 4 | N76: 0 | O76: USD | P76: 1 | Q76: 3 | R76: 3 | S76: 4 | T76: Low traffic | U76: 29.99 | V76: 0 | W76: 26.59 | X76: 0 | Y76: NoRestockExcessActionRequired | AA76: 0 | AB76: 0 | AC76: 3 | AD76: 182.88 | AE76: 0.62 | AF76: 0.231084 | AG76: cubic feet | AH76: Standard | AI76: 0.924336 | AJ76: US | AK76: gl_toy | AL76: 117152 | AM76: 28 | AN76: 0 | AO76: 5 | AP76: 13 | AR76: 26.59 | AS76: 82.57 | AT76: 82.57 | AU76: 112.56 | AV76: 0 | AW76: 0 | AX76: 0 | AY76: 0 | AZ76: 0 | BA76: 6.98 | BB76: 0 | BC76: 0 | BD76: 0 | BE76: 0 | BG76: 0 | BH76: 0 | BI76: 0 | BJ76: 0 | BK76: 0 | BL76: 0 | BM76: 0 | BN76: 0 | BO76: 0 | BP76: 0 | BQ76: 0 | BR76: 0 | BS76: 0 | BT76: 0 | BU76: 4 | BV76: 6.38 | BW76: 0 | BX76: 0 | BY76: 151.3 | CB76: 7 | CC76: 46193 | CD76: 46188 | CE76: Yes | CF76: No | CG76: 57.3 | CH76: 151.3 | CI76: 46186 | CJ76: 4 | CK76: 0 | CL76: 0 | CM76: 0 | CN76: 0 | CO76: 28 | CP76: unassigned | CQ76: N
A77: 46189 | B77: X004TU5VJN | C77: B0FDKPSJ23 | D77: ShouTiBaoHuaZhuangHe-0004 | E77: ROHSCE Kids Makeup Kit for Girl 15 Pcs - Real Washable Cosmetic Toy Set, Non-Toxic Play Makeup Set for Toddlers, Princess Birthday Gift for 3 4 5 6 7 8 9 10 12 Year Old Girls | F77: New | G77: 27 | H77: 0 | I77: 0 | J77: 15 | K77: 12 | L77: 0 | M77: 0 | N77: 0 | O77: USD | P77: 0 | Q77: 0 | R77: 0 | S77: 0 | T77: Low traffic | U77: 34.99 | V77: 18.99 | W77: 18.99 | X77: 0 | Y77: Advertise listing | AA77: 0 | AB77: 0 | AC77: 0 | AD77: 661.3 | AE77: 0 | AF77: 0.074514 | AG77: cubic feet | AH77: Standard | AI77: 2.011878 | AJ77: US | AK77: gl_toy | AL77: 752770 | AM77: 366 | AN77: 27 | AQ77: 18.99 | AR77: 0 | AS77: 0 | AT77: 0 | AU77: 0 | AV77: 0 | AW77: 0 | AX77: 0 | AY77: 12 | AZ77: 0 | BA77: 2.77 | BB77: 0 | BC77: 0 | BD77: 0 | BE77: 0 | BG77: 0 | BH77: 0 | BI77: 0 | BJ77: 0 | BK77: 12 | BL77: 0.89 | BM77: 0 | BN77: 0 | BO77: 0 | BP77: 0 | BQ77: 0 | BR77: 0 | BS77: 0 | BT77: 0 | BU77: 0 | BV77: 0 | BW77: 0 | BX77: 0 | BZ77: 3 | CA77: Excess | CI77: 46186 | CJ77: 27 | CK77: 0 | CL77: 0 | CM77: 0 | CN77: 0 | CO77: 366 | CP77: unassigned | CQ77: N
A78: 46189 | B78: X005313X8D | C78: B0GXTFCVWG | D78: 149-duijiangji007 | E78: Video Walkie Talkies for Kids Boys Girls, Kids Toy Walkie Talkies with Screen Display, Real-Time Video & Voice Intercom, Ages 3-12, Indoor Outdoor Play Travel Set | G78: 0 | H78: -1 | O78: USD | U78: 0 | V78: 0 | W78: 0 | X78: 0 | Y78: NoRestockExcessActionRequired | AB78: 0 | AC78: 0 | AE78: -1 | AH78: Standard | AJ78: US | AK78: gl_toy | AN78: 0 | AY78: 0 | BB78: 0 | BG78: 0 | BH78: 0 | CJ78: 0 | CK78: 0 | CL78: 0 | CM78: 0 | CN78: 0 | CP78: unassigned | CQ78: N
A79: 46189 | B79: X004MJ8UFN | C79: B0C65SQ3DV | D79: 149US-DongWuChiLun | E79: ROHSCE Motorized Gear Building Blocks Toys, Electric Farm Animal Spinning Set Ages 3-6, STEM Learning Construction Kit, Fine Motor Cause-Effect Gift for Boys Girls | F79: New | G79: 39 | H79: 0 | I79: 37 | J79: 0 | K79: 2 | L79: 0 | M79: 0 | N79: 0 | O79: USD | P79: 0 | Q79: 2 | R79: 4 | S79: 12 | T79: Low traffic | U79: 43.99 | V79: 29.99 | W79: 29.99 | X79: 0 | Y79: NoRestockExcessActionRequired | AA79: 0 | AB79: 0 | AC79: 0 | AD79: 2415.98 | AE79: 0.55 | AF79: 0.367664 | AG79: cubic feet | AH79: Standard | AI79: 14.338896 | AJ79: US | AK79: gl_toy | AL79: 475568 | AM79: 193 | AN79: 34 | AO79: 78 | AP79: 42 | AQ79: 29.99 | AR79: 0 | AS79: 59.98 | AT79: 119.96 | AU79: 359.88 | AV79: 13 | AW79: 24 | AX79: 0 | AY79: 2 | AZ79: 0 | BA79: 12.21 | BB79: 0 | BC79: 0 | BD79: 0 | BE79: 0 | BG79: 0 | BH79: 0 | BI79: 1 | BJ79: 0.18 | BK79: 1 | BL79: 0.37 | BM79: 0 | BN79: 0 | BO79: 0 | BP79: 0 | BQ79: 0 | BR79: 0 | BS79: 0 | BT79: 0 | BU79: 0 | BV79: 0 | BW79: 0 | BX79: 0 | BY79: 472 | BZ79: 10 | CA79: Excess | CD79: 46188 | CE79: Yes | CF79: No | CG79: 472 | CH79: 138.5 | CI79: 46186 | CJ79: 39 | CK79: 0 | CL79: 0 | CM79: 0 | CN79: 0 | CO79: 193 | CP79: unassigned | CQ79: N
A80: 46189 | B80: X004SJLWUR | C80: B0F1Y548MZ | D80: 149-qiuqianniwaA10 | E80: ROHSCE Construction Toy Set — Mini Bricks for Model Building | F80: New | G80: 2 | H80: 0 | I80: 0 | J80: 2 | K80: 0 | L80: 0 | M80: 0 | N80: 0 | O80: USD | P80: 0 | Q80: 0 | R80: 0 | S80: 0 | T80: Low traffic | U80: 29.99 | V80: 0 | W80: 29.99 | X80: 0 | Y80: Advertise listing | AA80: 0 | AB80: 0 | AC80: 0 | AD80: 99.18 | AE80: 0 | AF80: 0.144573 | AG80: cubic feet | AH80: Standard | AI80: 0.289146 | AJ80: US | AK80: gl_toy | AM80: 27 | AN80: 0 | AQ80: 29.99 | AR80: 0 | AS80: 0 | AT80: 0 | AU80: 0 | AV80: 0 | AW80: 0 | AX80: 0 | AY80: 0 | AZ80: 0 | BA80: 0.21 | BB80: 0 | BC80: 0 | BD80: 0 | BE80: 0 | BG80: 0 | BH80: 0 | BZ80: 7 | CA80: Low stock | CB80: 8 | CC80: 46195 | CI80: 46186 | CJ80: 2 | CK80: 0 | CL80: 0 | CM80: 0 | CN80: 0 | CO80: 27 | CP80: unassigned | CQ80: N
A81: 46189 | B81: X004DUX6HN | C81: B0DBZBTLVN | D81: rideontrain 0007 | E81: Ride On Toys for Toddlers 1-3 Boys Girls, 4-in-1 Push Pull Sit and Ride Train, Walking Car Toy for 1 Year Old Learning to Walk, Sit-to-Stand Walker for Baby Kids Ages 1 2 3 4 Outdoor Indoor Toy | F81: New | G81: 16 | H81: 0 | I81: 15 | J81: 7 | K81: 0 | L81: 0 | M81: 0 | N81: 0 | O81: USD | P81: 1 | Q81: 4 | R81: 10 | S81: 15 | T81: Low traffic | U81: 129.99 | V81: 99.99 | W81: 99.99 | X81: 0 | Y81: NoRestockExcessActionRequired | AA81: 0 | AB81: 0 | AC81: 0 | AD81: 183.13 | AE81: 0.83 | AF81: 1.597327 | AG81: cubic feet | AH81: Oversize | AI81: 25.557232 | AJ81: US | AK81: gl_baby_product | AL81: 353349 | AM81: 178 | AN81: 14 | AO81: 16 | AP81: 13 | AQ81: 99.99 | AR81: 99.99 | AS81: 399.96 | AT81: 999.9 | AU81: 1498.65 | AV81: 15 | AW81: 0 | AX81: 0 | AY81: 0 | AZ81: 0 | BA81: 17.49 | BB81: 0 | BC81: 0 | BD81: 0 | BE81: 0 | BG81: 0 | BH81: 0 | BY81: 107.8 | BZ81: 3 | CA81: Excess | CD81: 46188 | CE81: Yes | CF81: No | CG81: 107.8 | CH81: 94.1 | CI81: 46186 | CJ81: 22 | CK81: 6 | CL81: 0 | CM81: 0 | CN81: 0 | CO81: 178 | CP81: unassigned | CQ81: N
A82: 46189 | B82: X004N8C789 | C82: B0F4JS21NB | D82: 149US-HelicopterBlue | E82: Sprinkler for Kids Outdoor Water Toys, Helicopter Kids Sprinkler Toys, Water Powered for Yard, Lawn & Garden – Water Play for Summer Outside Fun for Girls Boys Ages 3-12, Ideal Birthday | F82: New | G82: 6 | H82: 0 | I82: 0 | J82: 0 | K82: 0 | L82: 0 | M82: 6 | N82: 0 | O82: USD | P82: 4 | Q82: 8 | R82: 10 | S82: 10 | T82: Low traffic | U82: 29.99 | V82: 0 | W82: 29.99 | X82: 0 | Y82: CreateShippingPlan | AA82: 0 | AB82: 0 | AC82: 0 | AD82: 440.08 | AE82: 0.67 | AF82: 0.22562 | AG82: cubic feet | AH82: Standard | AI82: 1.35372 | AJ82: US | AK82: gl_toy | AL82: 117152 | AM82: 63 | AN82: 0 | AO82: 3 | AP82: 7 | AQ82: 29.99 | AR82: 119.96 | AS82: 239.92 | AT82: 299.9 | AU82: 299.9 | AV82: 0 | AW82: 0 | AX82: 0 | AY82: 0 | AZ82: 0 | BA82: 10.22 | BB82: 0 | BC82: 0 | BD82: 0 | BE82: 0 | BG82: 0 | BH82: 1 | BI82: 0 | BJ82: 0 | BK82: 0 | BL82: 0 | BM82: 0 | BN82: 0 | BO82: 0 | BP82: 0 | BQ82: 0 | BR82: 0 | BS82: 0 | BT82: 0 | BU82: 6 | BV82: 9.34 | BW82: 0 | BX82: 0 | BY82: 160.8 | BZ82: 7 | CA82: Low stock | CD82: 46188 | CE82: Yes | CF82: No | CG82: 59.7 | CH82: 160.8 | CI82: 46186 | CJ82: 6 | CK82: 0 | CL82: 0 | CM82: 0 | CN82: 0 | CO82: 63 | CQ82: N
A83: 46189 | B83: X00531178L | C83: B0GXTWG6C8 | D83: MatsPuzzlePads-003 | E83: Kids Foam Floor Tiles Puzzle Mat, Soft EVA Interlocking Play Mat, Safe Non-Toxic Baby Crawling Surface, Thick Protective Flooring for Nursery, Playroom, Exercise & Indoor Activities | G83: 0 | H83: -1 | O83: USD | U83: 0 | V83: 0 | W83: 0 | X83: 0 | Y83: NoRestockExcessActionRequired | AB83: 0 | AC83: 0 | AE83: -1 | AH83: Standard | AJ83: US | AK83: gl_toy | AN83: 0 | AY83: 0 | BB83: 0 | BG83: 0 | BH83: 0 | CJ83: 0 | CK83: 0 | CL83: 0 | CM83: 0 | CN83: 0 | CP83: unassigned | CQ83: N
A84: 46189 | B84: X004LVWDVJ | C84: B0C8CLTGHR | D84: 149-ORedRocket-HoseGHR | E84: ROHSCE Water Powered Rocket Sprinkler for Kids, Outdoor Yard Sprinkler 360° Rotating Rocket Water Toys,Garden Hose Attachment Splashing Fun for 3 4 5 6 7 8 Year Old Boys Girls Gift (with Water Pipe) | G84: 0 | H84: -1 | O84: USD | U84: 0 | V84: 0 | W84: 0 | X84: 0 | Y84: NoRestockExcessActionRequired | AB84: 0 | AC84: 0 | AE84: -1 | AH84: Standard | AJ84: US | AK84: gl_toy | AM84: 0 | AN84: 0 | AQ84: 27.99 | AY84: 0 | BB84: 0 | BC84: 0 | BD84: 0 | BE84: 0 | BG84: 0 | BH84: 0 | CJ84: 0 | CK84: 0 | CL84: 0 | CM84: 0 | CN84: 0 | CO84: 0 | CP84: unassigned | CQ84: N
A85: 46189 | B85: X004VT0CPF | C85: B0CYLSL2MX | D85: 149US-TuZiMaoXianJi22 | E85: ROHSCE Sentro Knitting Machine 22 Needles with Row Counter, Smart Weaving Loom Round, Board Rotating Double, Crochet Loom Knitting Machine for Adults and Kids, Kit for Hat, Scarves, Gloves, Socks. | F85: New | G85: 16 | H85: 0 | I85: 0 | J85: 16 | K85: 0 | L85: 0 | M85: 0 | N85: 0 | O85: USD | P85: 1 | Q85: 2 | R85: 3 | S85: 5 | T85: Low traffic | U85: 45.99 | V85: 38.99 | W85: 38.99 | X85: 0 | Y85: NoRestockExcessActionRequired | AA85: 0 | AB85: 0 | AC85: 0 | AD85: 1039.31 | AE85: 0.27 | AF85: 0.375499 | AG85: cubic feet | AH85: Standard | AI85: 6.007984 | AJ85: US | AK85: gl_home | AL85: 215750 | AM85: 173 | AN85: 2 | AO85: 32 | AP85: 41 | AQ85: 38.99 | AR85: 38.99 | AS85: 77.98 | AT85: 116.97 | AU85: 180.79 | AV85: 0 | AW85: 0 | AX85: 0 | AY85: 0 | AZ85: 0 | BA85: 4.3 | BB85: 0 | BC85: 0 | BD85: 0 | BE85: 0 | BG85: 0 | BH85: 0 | BY85: 330.4 | BZ85: 3 | CA85: Excess | CD85: 46188 | CE85: Yes | CF85: No | CG85: 258.5 | CH85: 330.4 | CI85: 46186 | CJ85: 16 | CK85: 0 | CL85: 0 | CM85: 0 | CN85: 0 | CO85: 173 | CP85: unassigned | CQ85: N
A86: 46189 | B86: X004P3Z5LX | C86: B0CT5GKHRM | D86: 149US-XiaoHaoBingXiangChiLun | E86: ROHSCE 7PCS Magnetic Gear Toy Set, Train-Themed Gear Toys for Toddlers 1-3, Educational STEM Gears Toys for Kids, Cute Fridge Magnets for Toddlers, Montessori Learning Toy Gift for Boys Girls | F86: New | G86: 22 | H86: 0 | I86: 22 | J86: 0 | K86: 0 | L86: 0 | M86: 0 | N86: 0 | O86: USD | P86: 2 | Q86: 18 | R86: 30 | S86: 36 | T86: Low traffic | U86: 35.99 | V86: 23.99 | W86: 23.99 | X86: 0 | Y86: NoRestockExcessActionRequired | AA86: 0 | AB86: 0 | AC86: 0 | AD86: 0 | AE86: 1.92 | AF86: 0.1875 | AG86: cubic feet | AH86: Standard | AI86: 4.125 | AJ86: US | AK86: gl_toy | AM86: 63 | AN86: 0 | AO86: 15 | AP86: 25 | AQ86: 23.99 | AR86: 47.98 | AS86: 431.82 | AT86: 718.2 | AU86: 850.14 | AV86: 0 | AW86: 22 | AX86: 0 | AY86: 0 | AZ86: 0 | BA86: 3.91 | BB86: 48 | BC86: 38 | BD86: 10 | BE86: 0 | BG86: 0 | BH86: 0 | BY86: 54.8 | BZ86: 27 | CA86: Low stock | CD86: 46188 | CE86: Yes | CF86: No | CG86: 46.9 | CH86: 54.8 | CI86: 46186 | CJ86: 70 | CK86: 0 | CL86: 0 | CM86: 0 | CN86: 0 | CO86: 140 | CP86: unassigned | CQ86: N
A87: 46189 | B87: X004EGB9XJ | C87: B0CTQG25QM | D87: 149-HuangSeMaiGanYaoLing-5QM | E87: ROHSCE Sensory Rattle Balls, Textured Teething Sensory Toy for Babies 6-12M | G87: 0 | H87: -1 | O87: USD | U87: 0 | V87: 0 | W87: 0 | X87: 0 | Y87: NoRestockExcessActionRequired | AB87: 0 | AC87: 0 | AE87: -1 | AJ87: US | AK87: gl_toy | AL87: 397496 | AN87: 0 | AQ87: 13.49 | AY87: 0 | BB87: 0 | BG87: 0 | BH87: 0 | CJ87: 0 | CK87: 0 | CL87: 0 | CM87: 0 | CN87: 0 | CP87: unassigned | CQ87: N
A88: 46189 | B88: X004YLS243 | C88: B0CRDKZL4M | D88: 149US-ZuZhuangMengXiongClaw | E88: ROHSCE Kids Claw Machine - Toy Vending Machine for Kids with Plush Prizes, Lights & Sound, Electronic Claw Game Machine for Boys & Girls, Arcade Prize Dispenser for Party & Birthday Gifts | F88: New | G88: 4 | H88: -1 | O88: USD | U88: 69.99 | V88: 0 | W88: 0 | X88: 0 | Y88: Edit listing | AA88: 0 | AB88: 0 | AC88: 0 | AD88: 393.5 | AE88: -1 | AH88: Standard | AJ88: US | AK88: gl_toy | AL88: 192027 | AM88: 76 | AN88: 0 | AQ88: 69.99 | AY88: 0 | BA88: 1.22 | BB88: 0 | BC88: 0 | BD88: 0 | BE88: 0 | BG88: 0 | BH88: 0 | CJ88: 4 | CK88: 0 | CL88: 0 | CM88: 0 | CN88: 0 | CO88: 76 | CP88: unassigned | CQ88: N
A89: 46189 | B89: X004NYIFZH | C89: B0CYPYCDNC | D89: 149-CongLinXiaoXi-CiXingJiMu | E89: ROHSCE Magnetic Blocks 96PCS - River Scene Construction Cubes, STEM Preschool kit, Safe ABS no-Odor, CPC ASTM Certified, Travel-Ready Ages 3–12, Perfect for Birthday | G89: 0 | H89: -1 | O89: USD | P89: 0 | Q89: 0 | R89: 0 | S89: 0 | U89: 0 | V89: 0 | W89: 0 | X89: 0 | Y89: NoRestockExcessActionRequired | AB89: 0 | AC89: 0 | AE89: -1 | AH89: Standard | AJ89: US | AK89: gl_toy | AM89: 0 | AN89: 0 | AQ89: 36.99 | AR89: 0 | AS89: 0 | AT89: 0 | AU89: 0 | AY89: 0 | BB89: 0 | BC89: 0 | BD89: 0 | BE89: 0 | BG89: 0 | BH89: 0 | BZ89: 1 | CA89: Out of stock | CJ89: 0 | CK89: 0 | CL89: 0 | CM89: 0 | CN89: 0 | CO89: 0 | CP89: unassigned | CQ89: N
A90: 46189 | B90: X004P3IH13 | C90: B0F7FBDB45 | D90: 149-XiShuizhuo-Blue | E90: ROHSCE Water Table for Toddlers 1-3, 4-in-1 Outdoor Sand and Water Play Tables with Pump, Summer Kitchen Sink Toy with Fishing Game, Floating Boat, Sensory Gifts for Kids Ages 3-8 | G90: 0 | H90: -1 | O90: USD | P90: 0 | Q90: 0 | R90: 0 | S90: 0 | U90: 0 | V90: 0 | W90: 0 | X90: 0 | Y90: NoRestockExcessActionRequired | AB90: 0 | AC90: 0 | AE90: -1 | AH90: Oversize | AJ90: US | AK90: gl_toy | AM90: 0 | AN90: 0 | AQ90: 109.99 | AR90: 0 | AS90: 0 | AT90: 0 | AU90: 0 | AY90: 0 | BB90: 0 | BC90: 0 | BD90: 0 | BE90: 0 | BG90: 0 | BH90: 0 | BZ90: 1 | CA90: Out of stock | CJ90: 0 | CK90: 0 | CL90: 0 | CM90: 0 | CN90: 0 | CO90: 0 | CP90: unassigned | CQ90: N
